Workbook
Name datapoint0: 'CF Historical'!$D$13
Name datapoint0: 'CF Intergrated'!$D$13
Name datapoint0: 'FY''26 Statements'!$D$13
Name datapoint0: 'IS Historical'!$D$13
Name PctChange: _xlfn.LAMBDA(_xlpm.final,_xlpm.initial,(_xlpm.final-_xlpm.initial)/_xlpm.initial)

Sheet Cover
A1: COVER PAGE
A2: NASDAQ:TEAM
A3: Macquarie University Research Group
A4: MURG
D5: Scenario Switch | E5: Base Case
D7: Weight:
D8: DCF | E8: =IF(E9<=0,1,1-E9) -> 1
D9: VWAP | E9: 0
D10: Implied Share Price (USD$) | E10: =E8*'DCF FINAL'!J61+E9*AVERAGE('Comp. Multi & Imp. Val'!Y48:Z50) -> 107.76789
D12: Downside/Upside | E12: =(E10-E13)/E13 -> -0.39497607
D13: VWAP Share Price | E13: ='VWAP LIVE'!I5 -> 178.1217

Sheet DCF FINAL
B1: Atlassian DCF
B2: NASDAQ:TEAM | D2: =D12/D11 -> 0.1137598 | E2: =E12/E11 -> 0.1215141 | F2: =F12/F11 -> 0.14640431 | G2: =G12/G11 -> 0.16445348 | H2: =H12/H11 -> 0.16628195 | I2: =I12/I11 -> 0.15648426 | J2: =J12/J11 -> 0.13026809 | K2: =K12/K11 -> 0.158406 | ... P2: =P12/P11 -> 0.183406
C3: Gross Margin % | D3: =D13/D11 -> 0.8862402 | E3: =E13/E11 -> 0.8784859 | F3: =F13/F11 -> 0.85359569 | G3: =G13/G11 -> 0.83554652 | H3: =H13/H11 -> 0.83371805 | I3: =I13/I11 -> 0.84351574 | J3: =J13/J11 -> 0.86973191 | K3: =K13/K11 -> 0.841594 | ... P3: =P13/P11 -> 0.816594
C4: Opex/Revenue % | D4: =SUM(D14:D16)/D11 -> 0.82474431 | E4: =SUM(E14:E16)/E11 -> 0.79050869 | F4: =SUM(F14:F16)/F11 -> 0.87182835 | G4: =SUM(G14:G16)/G11 -> 0.91836724 | H4: =SUM(H14:H16)/H11 -> 0.84251422 | I4: =SUM(I14:I16)/I11 -> 0.85342005 | J4: =SUM(J14:J16)/J11 -> 0.84675323 | K4: =SUM(K14:K16)/K11 -> 0.81654138 | ... P4: =SUM(P14:P16)/P11 -> 0.65654138
D5: 43983 | E5: 44377 | F5: =EDATE(E5,12) -> 44742 | G5: =EDATE(F5,12) -> 45107 | H5: =EDATE(G5,12) -> 45473 | I5: =EDATE(H5,12) -> 45838 | J5: =EDATE(I5,12) -> 46203 | K5: =EDATE(J5,12) -> 46568 | L5: =EDATE(K5,12) -> 46934 | M5: =EDATE(L5,12) -> 47299 | ... P5: =EDATE(O5,12) -> 48395
B6: Currently Running | C6: =Cover!E5 -> Base Case | D6: Actuals | E6: Actuals | F6: Actuals | G6: Actuals | H6: Actuals | I6: Actuals | J6: Actuals | K6: Forecast | L6: Forecast | M6: Forecast | N6: Forecast | O6: Forecast | P6: Forecast | T6: H-Model DCF
K7: 1 | L7: 2 | M7: 3 | N7: 4 | O7: 5 | P7: 6 | T7: Source: Team 2 Atlassian DCF
T8: Inputs
T9: FCF Final Explicit Year, FY32 ($M) | U9: =P31 -> 2422.7727
E10: =E11/D11-1 -> 0.29424293 | F10: =F11/E11-1 -> 0.34164907 | G10: =G11/F11-1 -> 0.26107592 | H10: =H11/G11-1 -> 0.23310843 | I10: =I11/H11-1 -> 0.19655403 | J10: =J11/I11-1 -> 0.26019653 | K10: =K11/J11-1 -> 0.14729193 | L10: =L11/K11-1 -> 0.21108027 | ... P10: =P11/O11-1 -> 0.10145761 | T10: WACC | U10: =WACC!H55 -> 0.098174268
B11: Revenue | D11: ='IS Intergrated'!E10 -> 1614.173 | E11: ='IS Intergrated'!F10 -> 2089.132 | F11: ='IS Intergrated'!G10 -> 2802.882 | G11: ='IS Intergrated'!H10 -> 3534.647 | H11: ='IS Intergrated'!I10 -> 4358.603 | I11: ='IS Intergrated'!J10 -> 5215.304 | J11: ='IS Intergrated'!K10 -> 6572.308 | K11: ='IS Intergrated'!L10 -> 7540.3559 | ... P11: ='IS Intergrated'!Q10 -> 16156.084 | T11: g_S Exit growth rate (FY32) | U11: =P36 -> 0.10145761
B12: COGS (Excl. D&A) | D12: ='IS Intergrated'!E17 -> 183.628 | E12: ='IS Intergrated'!F17 -> 253.859 | F12: ='IS Intergrated'!G17 -> 410.354 | G12: ='IS Intergrated'!H17 -> 581.285 | H12: ='IS Intergrated'!I17 -> 724.757 | I12: ='IS Intergrated'!J17 -> 816.113 | J12: ='IS Intergrated'!K17 -> 856.162 | K12: ='IS Intergrated'!L17 -> 1194.4376 | ... P12: ='IS Intergrated'!Q17 -> 2963.1227 | T12: g_L Long-run perpetuity growth | U12: =J44 -> 0.035
B13: Gross Profit | D13: =D11-D12 -> 1430.545 | E13: =E11-E12 -> 1835.273 | F13: =F11-F12 -> 2392.528 | G13: =G11-G12 -> 2953.362 | H13: =H11-H12 -> 3633.846 | I13: =I11-I12 -> 4399.191 | J13: =J11-J12 -> 5716.146 | K13: =K11-K12 -> 6345.9183 | ... P13: =P11-P12 -> 13192.961 | T13: Fade Period (Years) | U13: 8
B14: R&D Expense | D14: ='IS Intergrated'!E25 -> 763.188 | E14: ='IS Intergrated'!F25 -> 963.326 | F14: ='IS Intergrated'!G25 -> 1397.568 | G14: ='IS Intergrated'!H25 -> 1869.881 | H14: ='IS Intergrated'!I25 -> 2184.111 | I14: ='IS Intergrated'!J25 -> 2669.312 | J14: ='IS Intergrated'!K25 -> 3269.257 | K14: ='IS Intergrated'!L25 -> 3488.1887 | ... P14: ='IS Intergrated'!Q25 -> 5454.3368 | T14: H (Fade Period / 2) | U14: =U13/2 -> 4
B15: M&S Expense | D15: ='IS Intergrated'!E26 -> 299.683 | E15: ='IS Intergrated'!F26 -> 372.909 | F15: ='IS Intergrated'!G26 -> 567.691 | G15: ='IS Intergrated'!H26 -> 769.861 | H15: ='IS Intergrated'!I26 -> 877.497 | I15: ='IS Intergrated'!J26 -> 1134.535 | J15: ='IS Intergrated'!K26 -> 1541.178 | K15: ='IS Intergrated'!L26 -> 1768.1811 | ... P15: ='IS Intergrated'!Q26 -> 3626.9714
B16: G&A Expense | D16: ='IS Intergrated'!E27 -> 268.409 | E16: ='IS Intergrated'!F27 -> 315.242 | F16: ='IS Intergrated'!G27 -> 478.373 | G16: ='IS Intergrated'!H27 -> 606.362 | H16: ='IS Intergrated'!I27 -> 610.577 | I16: ='IS Intergrated'!J27 -> 646.998 | J16: ='IS Intergrated'!K27 -> 754.688 | K16: ='IS Intergrated'!L27 -> 900.64289 | ... P16: ='IS Intergrated'!Q27 -> 1525.8293 | T16: Terminal Value H-Model EOFY '32/ Year 6
B17: EBITDA | D17: =D13-SUM(D14:D16) -> 99.265 | E17: =E13-SUM(E14:E16) -> 183.796 | F17: =F13-SUM(F14:F16) -> -51.104 | G17: =G13-SUM(G14:G16) -> -292.742 | H17: =H13-SUM(H14:H16) -> -38.339 | I17: =I13-SUM(I14:I16) -> -51.654 | J17: =J13-SUM(J14:J16) -> 151.023 | K17: =K13-SUM(K14:K16) -> 188.90568 | ... P17: =P13-SUM(P14:P16) -> 2585.8235 | T17: Gordon component = FCF * (1+g_L)/(WACC-g_L) | U17: =U9*(1+U12)/(U10-U12) -> 39692.897
B18: D&A | D18: ='IS Intergrated'!E18 -> 85.179 | E18: ='IS Intergrated'!F18 -> 82.162 | F18: ='IS Intergrated'!G18 -> 55.353 | G18: ='IS Intergrated'!H18 -> 52.48 | H18: ='IS Intergrated'!I18 -> 78.738 | I18: ='IS Intergrated'!J18 -> 78.738 | J18: ='IS Intergrated'!K18 -> 140.67 | K18: ='IS Intergrated'!L18 -> 139.14995 | ... P18: ='IS Intergrated'!Q18 -> 80.690798 | T18: Fade Premium: FCF * H*(g_S-g_L)/(WACC-g_L) | U18: =U9*U14*(U11-U12)/(U10-U12) -> 10194.763
B19: EBIT | D19: =D17-D18 -> 14.086 | E19: =E17-E18 -> 101.634 | F19: =F17-F18 -> -106.457 | G19: =G17-G18 -> -345.222 | H19: =H17-H18 -> -117.077 | I19: =I17-I18 -> -130.392 | J19: =J17-J18 -> 10.353 | K19: =K17-K18 -> 49.755724 | ... P19: =P17-P18 -> 2505.1327 | T19: Terminal Value (H-Model) | U19: =SUM(U17+U18) -> 49887.66
B20: Non-Operating Income | D20: ='IS Intergrated'!E31+'IS Intergrated'!E39 -> -360.295 | E20: ='IS Intergrated'!F31+'IS Intergrated'!F39 -> -736.298 | F20: ='IS Intergrated'!G31+'IS Intergrated'!G39 -> -458.085 | G20: ='IS Intergrated'!H31+'IS Intergrated'!H39 -> 34.086 | H20: ='IS Intergrated'!I31+'IS Intergrated'!I39 -> 31.67 | I20: ='IS Intergrated'!J31+'IS Intergrated'!J39 -> 31.497 | J20: ='IS Intergrated'!K31 -> 11.695 | K20: ='IS Intergrated'!L31 -> 12.104538 | L20: ='IS Intergrated'!M31 -> 22.941378 | M20: ='IS Intergrated'!N31 -> 35.760401 | N20: ='IS Intergrated'!O31 -> 57.610478 | O20: ='IS Intergrated'!P31 -> 88.971914 | P20: ='IS Intergrated'!Q31 -> 132.86386 | T20: PV of Terminal Value = TV/(1+WACC)^6 | U20: =U19/(1+U10)^P7 -> 28442.355
B21: Taxes | D21: ='IS Intergrated'!E38 -> 4.445 | E21: ='IS Intergrated'!F38 -> 61.651 | F21: ='IS Intergrated'!G38 -> 49.582 | G21: ='IS Intergrated'!H38 -> 175.625 | H21: ='IS Intergrated'!I38 -> 215.112 | I21: ='IS Intergrated'!J38 -> 157.792 | J21: ='IS Intergrated'!K38 -> 75.878 | K21: ='IS Intergrated'!L38 -> 14.846463 | ... P21: ='IS Intergrated'!Q38 -> 633.11919 | T21: Cross-Check (Reg. GGM)
B22: Net Income | D22: =D19+D20-D21 -> -350.654 | E22: =E19+E20-E21 -> -696.315 | F22: =F19+F20-F21 -> -614.124 | G22: =G19+G20-G21 -> -486.761 | H22: =H19+H20-H21 -> -300.519 | I22: =I19+I20-I21 -> -256.687 | J22: =J19+J20-J21 -> -53.83 | K22: =K19+K20-K21 -> 47.013799 | ... P22: =P19+P20-P21 -> 2004.8774 | T22: Terminal Value (Gordon) = FCF * (1+g_L)(WACC-g_L) | U22: =U9*(1+J44)/(U10-U12) -> 39692.897
T23: H-Model Premium vs. Gordon (%) | U23: =U19/U22-1 -> 0.25684099
B24: (+) D&A | D24: =D18 -> 85.179 | E24: =E18 -> 82.162 | F24: =F18 -> 55.353 | G24: =G18 -> 52.48 | H24: =H18 -> 78.738 | I24: =I18 -> 78.738 | J24: =J18 -> 140.67 | K24: =K18 -> 139.14995 | ... P24: =P18 -> 80.690798
B25: (-) CapEx | D25: ='CF Intergrated'!E30 -> -35.709 | E25: ='CF Intergrated'!F30 -> -33.32 | F25: ='CF Intergrated'!G30 -> -74.601 | G25: ='CF Intergrated'!H30 -> -25.812 | H25: ='CF Intergrated'!I30 -> -33.112 | I25: ='CF Intergrated'!J30 -> -44.85 | J25: ='CF Intergrated'!K30 -> -34.06 | K25: ='CF Intergrated'!L30 -> -58.709653 | ... P25: ='CF Intergrated'!Q30 -> -59.486081
B26: (-) Change in NWC | D26: ='CF Intergrated'!E18 -> 143.019 | E26: ='CF Intergrated'!F18 -> 233.502 | F26: ='CF Intergrated'!G18 -> 253.237 | G26: ='CF Intergrated'!H18 -> 308.556 | H26: ='CF Intergrated'!I18 -> 576.989 | I26: ='CF Intergrated'!J18 -> 264.809 | J26: ='CF Intergrated'!K18 -> -375.999 | K26: ='CF Intergrated'!L18 -> 413.03206 | ... P26: ='CF Intergrated'!Q18 -> 437.97892 | T26: H-Model Share Price
B27: (+) Int Exp | D27: ='IS Intergrated'!E34*(1-'DCS Detail'!$D$57) -> -37.7036 | E27: ='IS Intergrated'!F34*(1-'DCS Detail'!$D$57) -> -93.26188 | F27: ='IS Intergrated'!G34*(1-'DCS Detail'!$D$57) -> -19.62624 | G27: ='IS Intergrated'!H34*(1-'DCS Detail'!$D$57) -> -22.91172 | H27: ='IS Intergrated'!I34*(1-'DCS Detail'!$D$57) -> -25.89852 | I27: ='IS Intergrated'!J34*(1-'DCS Detail'!$D$57) -> -23.218 | J27: ='IS Intergrated'!K34*(1-'DCS Detail'!$D$57) -> -37.582 | K27: ='IS Intergrated'!L34*(1-'DCS Detail'!$D$57) -> -41.288401 | ... P27: ='IS Intergrated'!Q34*(1-'DCS Detail'!$D$57) -> -41.288401 | T27: H-Model Terminal Value | W27: =U19 -> 49887.66
B28: (+) Stock Based Compensation | D28: ='SBC Ratios'!E6 -> 313.395 | E28: ='SBC Ratios'!F6 -> 385.732 | F28: ='SBC Ratios'!G6 -> 707.087 | G28: ='SBC Ratios'!H6 -> 948.087 | H28: ='SBC Ratios'!I6 -> 1081.433 | I28: ='SBC Ratios'!J6 -> 1362.222 | J28: ='SBC Ratios'!K6 -> 1606.561 | K28: ='CF Intergrated'!L14 -> 1780.6478 | L28: ='CF Intergrated'!M14 -> 2110.8476 | M28: ='CF Intergrated'!N14 -> 2491.149 | N28: ='CF Intergrated'!O14 -> 2869.8171 | O28: ='CF Intergrated'!P14 -> 3170.4552 | P28: ='CF Intergrated'!Q14 -> 3411.3416 | Q28: NON LIVE | T28: PV terminal value | W28: =W27/(1+U10)^P7 -> 28442.355
B29: (-) Adjustment For SBC | D29: =-(1-'Chaffe-Finnerty DLOM'!$J$14)*'DCF FINAL'!D28 -> -231.29476 | E29: =-(1-'Chaffe-Finnerty DLOM'!$J$14)*'DCF FINAL'!E28 -> -284.68159 | F29: =-(1-'Chaffe-Finnerty DLOM'!$J$14)*'DCF FINAL'!F28 -> -521.85106 | G29: =-(1-'Chaffe-Finnerty DLOM'!$J$14)*'DCF FINAL'!G28 -> -699.71617 | H29: =-(1-'Chaffe-Finnerty DLOM'!$J$14)*'DCF FINAL'!H28 -> -798.12946 | I29: =-(1-'Chaffe-Finnerty DLOM'!$J$14)*'DCF FINAL'!I28 -> -1005.36 | J29: =-(1-'Chaffe-Finnerty DLOM'!$J$14)*'DCF FINAL'!J28 -> -1185.6894 | K29: =-(1-'Chaffe-Finnerty DLOM'!$J$14)*'DCF FINAL'!K28 -> -1314.1706 | ... P29: =-(1-'Chaffe-Finnerty DLOM'!$J$14)*'DCF FINAL'!P28 -> -2517.6707 | Q29: NON LIVE | T29: PV FCF (JUN '27 to JUN '32) | W29: =SUM(K32:P32) -> 5400.2587
T30: Enterprise value | W30: =W28+W29 -> 33842.614
B31: Total FCF | D31: =SUM(D22:D27) -> -195.8686 | E31: =SUM(E22:E27) -> -507.23288 | F31: =SUM(F22:F27) -> -399.76124 | G31: =SUM(G22:G27) -> -174.44872 | H31: =SUM(H22:H27) -> 296.19748 | I31: =SUM(I22:I27) -> 18.792 | J31: =SUM(J22:J27) -> -360.801 | K31: =SUM(K22:K27) -> 499.19776 | ... P31: =SUM(P22:P27) -> 2422.7727 | T31: Cash | W31: ='BS Intergrated'!K11 -> 1239.512
B32: (PV) FCF | K32: =K31/(1+$J$43)^K7 -> 454.57062 | L32: =L31/(1+$J$43)^L7 -> 612.67767 | M32: =M31/(1+$J$43)^M7 -> 765.30508 | N32: =N31/(1+$J$43)^N7 -> 1004.276 | O32: =O31/(1+$J$43)^O7 -> 1182.1386 | P32: =P31/(1+$J$43)^P7 -> 1381.2907 | T32: Debt | W32: =J57 -> 1232.91
T33: Net debt | W33: =W32-W31 -> -6.602
B34: FCF Margin (%) | D34: =D31/D11 -> -0.121343 | E34: =E31/E11 -> -0.24279599 | F34: =F31/F11 -> -0.14262507 | G34: =G31/G11 -> -0.04935393 | H34: =H31/H11 -> 0.067956976 | I34: =I31/I11 -> 0.0036032415 | J34: =J31/J11 -> -0.054897153 | K34: =K31/K11 -> 0.066203474 | ... P34: =P31/P11 -> 0.14996039 | T34: Equity Value | W34: =W30+W31-W32 -> 33849.216
B35: FCF Margin (5dp) | D35: =D34 -> -0.121343 | E35: =E34 -> -0.24279599 | F35: =F34 -> -0.14262507 | G35: =G34 -> -0.04935393 | H35: =H34 -> 0.067956976 | I35: =I34 -> 0.0036032415 | J35: =J34 -> -0.054897153 | K35: =K34 -> 0.066203474 | ... P35: =P34 -> 0.14996039
B36: Sales Growth (5dp) | E36: =E11/D11-1 -> 0.29424293 | F36: =F11/E11-1 -> 0.34164907 | G36: =G11/F11-1 -> 0.26107592 | H36: =H11/G11-1 -> 0.23310843 | I36: =I11/H11-1 -> 0.19655403 | J36: =J11/I11-1 -> 0.26019653 | K36: =K11/J11-1 -> 0.14729193 | L36: =L11/K11-1 -> 0.21108027 | ... P36: =P11/O11-1 -> 0.10145761 | T36: No. Diluted Shares (M) | W36: ='Comp. Multi & Imp. Val'!W13 -> 260.16
B37: Net Income Margin (%) | D37: =D22/D11 -> -0.21723446 | E37: =E22/E11 -> -0.3333035 | F37: =F22/F11 -> -0.21910448 | G37: =G22/G11 -> -0.13771135 | H37: =H22/H11 -> -0.068948468 | I37: =I22/I11 -> -0.049218032 | J37: =J22/J11 -> -0.0081904256 | K37: =K22/K11 -> 0.0062349576 | ... P37: =P22/P11 -> 0.12409427
B38: PV SBC | K38: =(K28+K29)/((1+$J$43)^K7) -> 424.77521 | L38: =(L28+L29)/((1+$J$43)^L7) -> 458.52892 | M38: =(M28+M29)/((1+$J$43)^M7) -> 492.76325 | N38: =(N28+N29)/((1+$J$43)^N7) -> 516.91788 | O38: =(O28+O29)/((1+$J$43)^O7) -> 520.01719 | P38: =(P28+P29)/((1+$J$43)^P7) -> 509.50684 | T38: Estimated Share Price (DCF) - H-Model | W38: =W34/W36 -> 130.10922
T39: Upside/(Discount) to Valuation | W39: =W38/W40-1 -> -0.26954874
T40: VWAP Share Price | W40: ='VWAP LIVE'!I5 -> 178.1217
B41: Gordon Growth Model DCF
B43: WACC | J43: =WACC!H55 -> 0.098174268
B44: Terminal Growth Rate | J44: 0.035
B45: Forecast Revenue CAGR (%) | J45: =_xlfn.RRI(P7,J11,P11) -> 0.16172419
B47: Terminal Value | J47: =P31*(1+J44)/(J43-J44) -> 39692.897
B48: PV of Terminal Value | J48: =J47/(1+J43)^P7 -> 22630.034 | K48: =J48/(J48+J49) -> 0.80734205
B49: Sum of PV of FCF | J49: =SUM(K32:P32) -> 5400.2587
B51: Terminal Value SBC | J51: =((P28+P29)*(1+J44))/(J43-J44) -> 14641.236 | K51: NON LIVE
B52: PV of Terminal Value of SBC | J52: =J51/(1+J43)^P7 -> 8347.3794 | K52: NON LIVE
B53: Sum of PV of SBC | J53: =SUM(K38:P38) -> 2922.5093 | K53: NON LIVE
B55: Enterprise Value | J55: =(J48+J49) -> 28030.293
B56: (+) Cash | J56: ='BS Intergrated'!K11 -> 1239.512
B57: (-) Debt | J57: ='BS Intergrated'!K58+'BS Intergrated'!K59+'BS Intergrated'!K51 -> 1232.91
B58: Equity Value | J58: =J55+J56-J57 -> 28036.895
B59: Number of Shares Outstanding | J59: ='Comp. Multi & Imp. Val'!W13 -> 260.16
B61: Implied Share Price | J61: =J58/J59 -> 107.76789
B62: =IF(J61>$J$63,"Upside of : ","Downside of :") -> Downside of : | J62: =(J61-J63)/J63 -> -0.39497607
B63: VWAP Share Price | J63: ='VWAP LIVE'!I5 -> 178.1217

Sheet Comp. Multi & Imp. Val
A1: Atlassian Comp. Multiples | V1: Implied Valuation - Trading Comparables (6 True Peers)
A2: NASDAQ: TEAM | H2: =H15/G15 -> 0.26742591 | V2: Peer Set: ServiceNow, HubSpot, GitLab, Monday.com, Freshworks, Asana. Atlassian and Microsoft excluded from peer statistics.
A3: #VALUE! | H3: =H16/G16 -> 0.34041542 | AS3: X suffix | AT3: 0.00"x";(0.00"x")
A4: #VALUE! | H4: =H17/G17 -> 0.21108888 | V4: Atlassian Target Metrics | AS4: 2DP | AT4: #,##0.00;(#,##0.00)
A5: #VALUE! | H5: =H18/G18 -> 0.15356752 | V5: NTM Sales ($M) | W5: =M15 -> 7540.3559 | AS5: Percentages | AT5: 0.0%;(0.0%)
A6: #VALUE! | H6: =H19/G19 -> 0.16955949 | V6: NTM Adj. EBITDA ($M) | W6: =N15 -> 1969.5535
A7: #VALUE! | H7: =H20/G20 -> 0.18837261 | V7: LTM FCF ($M) | W7: =K15 -> 1319.069
A8: #VALUE! | H8: =H21/G21 -> 0.058669305 | V8: TEV ($M) | W8: =E15 -> 46333.541
A9: #VALUE! | V9: Market Cap ($M) | W9: =D15 -> 46340.143
A10: #VALUE! | V10: Share Price ($/share) | W10: =C15 -> 178.1217
A11: Comparable Multiples
C12: Market Data | G12: Financial Data (LTM)1 | M12: Financial Data (NTM) | P12: Metrics | V12: Net Debt = TEV - Market Cap ($M) | W12: =E15-D15 -> -6.602
C13: Price | D13: Fully Diluted Market Cap | E13: TEV | G13: Sales | H13: Adjusted EBITDA 2 | I13: EBIT | J13: Earnings | K13: FCF | M13: Sales (NTM) | N13: Adjusted EBITDA (NTM)2 | P13: EV/Revenue (NTM) | Q13: EV/EBITDA (NTM) | R13: Revenue Growth (LTM, implied) | S13: Rule of 40 | T13: EV/FCF (LTM) | V13: Diluted Shares (Market Cap ÷ Price, M) | W13: =W9/W10 -> 260.16
A14: Company Name | B14: Market Category | C14: ($/share) | D14: ($M) | E14: ($M) | G14: ($M) | H14: ($M) | I14: ($M) | J14: ($M) | K14: ($M) | M14: ($M) | N14: ($M) | P14: X | Q14: X | R14: (%) | S14: (%) | T14: X
A15: Atlassian Corp | B15: Enterprise Software | C15: ='VWAP LIVE'!I5 -> 178.1217 | D15: =C15*260.16 -> 46340.143 | E15: =D15+('BS Historical Updated'!J47+'BS Historical Updated'!J54+'BS Historical Updated'!J55)-'BS Historical Updated'!J7 -> 46333.541 | G15: 6572.31 | H15: ='IS Historical'!K52+K32 -> 1757.606 | I15: ='IS Historical'!K28 -> 10.353 | J15: -53.8 | K15: ='CF Intergrated'!K53 -> 1319.069 | M15: ='IS Intergrated'!L10 -> 7540.3559 | N15: ='IS Intergrated'!L55+'CF Assumptions'!F38 -> 1969.5535 | P15: =E15/M15 -> 6.1447418 | Q15: =E15/N15 -> 23.524896 | R15: =(G15/'IS Intergrated'!J10)-1 -> 0.26019691 | S15: =R15+K15/G15 -> 0.46089788 | T15: =E15/K15 -> 35.125942 | V15: Method 1: EV/Revenue (NTM) - Implied Valuation
A16: ServiceNow | B16: IT Service Management | C16: {=_FV(A4,"Price")} -> 142.35 | D16: =C16*1034.33 -> 147236.88 | E16: =D16-6290+1491 -> 142437.88 | G16: 14732 | H16: =2983+K33 -> 5015 | I16: 2001 | J16: 1670 | K16: 4580 | M16: =0.5*16209+0.5*19245 -> 17727 | N16: =0.5*6323+0.5*7554 -> 6938.5 | P16: =E16/M16 -> 8.0350807 | Q16: =E16/N16 -> 20.528627 | R16: =(M16/G16)-1 -> 0.20329894 | S16: =R16+K16/G16 -> 0.5141868 | T16: =E16/K16 -> 31.099973 | V16: Statisitic | W16: Peer Mutliple | X16: Target Metric | Y16: Implied EV | Z16: (-) Net Debt | AA16: Implied Equity Value | AB16: Implied Share Price
A17: HubSpot | B17: Customer Relationship Management | C17: {=_FV(A5,"Price")} -> 250.61 | D17: =C17*51.34 -> 12866.317 | E17: =10027.88-1337.94-119.46 -> 8570.48 | G17: 3448.5 | H17: =321.34+K38 -> 727.94 | I17: 134.23 | J17: 146.9 | K17: 694.88 | M17: =0.5*3683+0.5*4204 -> 3943.5 | N17: =0.5*922+0.5*1113 -> 1017.5 | P17: =E17/M17 -> 2.1733181 | Q17: =E17/N17 -> 8.4230762 | R17: =(M17/G17)-1 -> 0.14354067 | S17: =R17+K17/G17 -> 0.34504277 | T17: =E17/K17 -> 12.333755
A18: GitLab | B18: Development & Security Operations | C18: {=_FV(A6,"Price")} -> 49.25 | D18: =C18*184.51 -> 9087.1175 | E18: =D18-1357.51+46.18 -> 7775.7875 | G18: 1004.9 | H18: =-32.98+K34 -> 154.32 | I18: -45.06 | J18: -25.1 | K18: 263.44 | M18: =((0.5)*1117)+((0.5)*1286) -> 1201.5 | N18: =((10/12)*145)+((2/12)*184) -> 151.5 | P18: =E18/M18 -> 6.4717333 | Q18: =E18/N18 -> 51.32533 | R18: =(M18/G18)-1 -> 0.19564136 | S18: =R18+K18/G18 -> 0.4577968 | T18: =E18/K18 -> 29.516351 | V18: Low | W18: =MIN($P16:$P21) -> 1.8793972 | X18: =W5 -> 7540.3559 | Y18: =W18*X18 -> 14171.324 | Z18: =$W$12 -> -6.602 | AA18: =Y18+Z18 -> 14164.722 | AB18: =AA18/$W$13 -> 54.446195
A19: Monday.com | B19: Project Management | C19: {=_FV(A7,"Price")} -> 96.105 | D19: =C19*43.97 -> 4225.7369 | E19: =D19+0-1212.28 -> 3013.4569 | G19: 1366.6 | H19: =54.71+K35 -> 231.72 | I19: 39.65 | J19: 121.24 | K19: 318.2 | M19: =((5/12)*1471)+((7/12)*1698) -> 1603.4167 | N19: =((5/12)*234)+((7/12)*296) -> 270.16667 | P19: =E19/M19 -> 1.8793972 | Q19: =E19/N19 -> 11.154066 | R19: =(M19/G19)-1 -> 0.17328894 | S19: =R19+K19/G19 -> 0.40612957 | T19: =E19/K19 -> 9.4703232 | V19: 25th Percentile | W19: =_xlfn.QUARTILE.INC(P16:P21,1) -> 2.1962557 | X19: =W5 -> 7540.3559 | Y19: =W19*X19 -> 16560.55 | Z19: =$W$12 -> -6.602 | AA19: =Y19+Z19 -> 16553.948 | AB19: =AA19/$W$13 -> 63.629874 | AE19: =P13 -> EV/Revenue (NTM) | AF19: =Q13 -> EV/EBITDA (NTM) | AG19: =T13 -> EV/FCF (LTM)
A20: Freshworks | B20: IT Service Management | C20: {=_FV(A8,"Price")} -> 12.64 | D20: =C20*292.11 -> 3692.2704 | E20: =D20+13-665.26 -> 3040.0104 | G20: 903.9 | H20: =68.17+K39 -> 170.27 | I20: 37.31 | J20: 185.19 | K20: 220.56 | M20: =((10/12)*965+(2/12)*1102) -> 987.83333 | N20: =((10/12)*250.2+(2/12)*292.2) -> 257.2 | P20: =E20/M20 -> 3.0774527 | Q20: =E20/N20 -> 11.819636 | R20: =(M20/G20)-1 -> 0.092856879 | S20: =R20+K20/G20 -> 0.33686617 | T20: =E20/K20 -> 13.783145 | V20: Median | W20: =MEDIAN(P16:P21) -> 2.6712607 | X20: =W5 -> 7540.3559 | Y20: =W20*X20 -> 20142.256 | Z20: =$W$12 -> -6.602 | AA20: =Y20+Z20 -> 20135.654 | AB20: =AA20/$W$13 -> 77.397194 | AD20: Peers (Average) | AE20: =P22 -> 3.9836751 | AF20: =Q22 -> 20.172586 | AG20: =T22 -> 19.101425
A21: Asana | B21: Project Management | C21: {=_FV(A9,"Price")} -> 9.66 | D21: =C21*244.58 -> 2362.6428 | E21: =D21-425.35+38.3 -> 1975.5928 | G21: 808.6 | H21: =-112.93+K36 -> 47.44 | I21: -136.05 | J21: -163.41 | K21: 107.34 | M21: =((10/12)*860.8)+((2/12)*929.2) -> 872.2 | N21: =((10/12)*106.6)+((2/12)*133.5) -> 111.08333 | P21: =E21/M21 -> 2.2650686 | Q21: =E21/N21 -> 17.784781 | R21: =(M21/G21)-1 -> 0.078654465 | S21: =R21+K21/G21 -> 0.21140242 | T21: =E21/K21 -> 18.405001 | V21: Mean | W21: =AVERAGE(P16:P21) -> 3.9836751 | X21: =W5 -> 7540.3559 | Y21: =W21*X21 -> 30038.328 | Z21: =$W$12 -> -6.602 | AA21: =Y21+Z21 -> 30031.726 | AB21: =AA21/$W$13 -> 115.4356 | AD21: Atlassian | AE21: =P15 -> 6.1447418 | AF21: =Q15 -> 23.524896 | AG21: =T15 -> 35.125942
A22: Average (peers only) | C22: =AVERAGE(C16:C21) -> 93.435833 | D22: =AVERAGE(D16:D21) -> 29911.827 | E22: =AVERAGE(E16:E21) -> 27802.201 | G22: =AVERAGE(G16:G21) -> 3710.75 | H22: =AVERAGE(H16:H21) -> 1057.7817 | I22: =AVERAGE(I16:I21) -> 338.51333 | J22: =AVERAGE(J16:J21) -> 322.47 | K22: =AVERAGE(K16:K21) -> 1030.7367 | M22: =AVERAGE(M16:M21) -> 4389.2417 | N22: =AVERAGE(N16:N21) -> 1457.6583 | P22: =AVERAGE(P16:P21) -> 3.9836751 | Q22: =AVERAGE(Q16:Q21) -> 20.172586 | R22: =AVERAGE(R16:R21) -> 0.14788021 | S22: =AVERAGE(S16:S21) -> 0.37857076 | T22: =AVERAGE(T16:T21) -> 19.101425 | V22: 75th Percentile | W22: =_xlfn.QUARTILE.INC(P16:P21,3) -> 5.6231631 | X22: =W5 -> 7540.3559 | Y22: =W22*X22 -> 42400.651 | Z22: =$W$12 -> -6.602 | AA22: =Y22+Z22 -> 42394.049 | AB22: =AA22/$W$13 -> 162.95376
A23: Median (peers only) | C23: =MEDIAN(C16:C21) -> 72.6775 | D23: =MEDIAN(D16:D21) -> 6656.4272 | E23: =MEDIAN(E16:E21) -> 5407.899 | G23: =MEDIAN(G16:G21) -> 1185.75 | H23: =MEDIAN(H16:H21) -> 200.995 | I23: =MEDIAN(I16:I21) -> 38.48 | J23: =MEDIAN(J16:J21) -> 134.07 | K23: =MEDIAN(K16:K21) -> 290.82 | M23: =MEDIAN(M16:M21) -> 1402.4583 | N23: =MEDIAN(N16:N21) -> 263.68333 | P23: =MEDIAN(P16:P21) -> 2.6712607 | Q23: =MEDIAN(Q16:Q21) -> 14.802209 | R23: =MEDIAN(R16:R21) -> 0.15841481 | S23: =MEDIAN(S16:S21) -> 0.37558617 | T23: =MEDIAN(T16:T21) -> 16.094073 | V23: High | W23: =MAX(P16:P21) -> 8.0350807 | X23: =W5 -> 7540.3559 | Y23: =W23*X23 -> 60587.368 | Z23: =$W$12 -> -6.602 | AA23: =Y23+Z23 -> 60580.766 | AB23: =AA23/$W$13 -> 232.85965
A24: Microsoft4 | B24: Diversified Enterprise Software | C24: {=_FV(A10,"Price")} -> 505.41 | D24: =C24*7503.55 -> 3792369.2 | E24: =D24+40294-(76843+27240) -> 3728580.2 | G24: =331.84*1000 -> 331840 | H24: =(198.69*1000)+K37 -> 211095 | I24: =155.24*1000 -> 155240 | J24: =133.75*1000 -> 133750 | K24: =66.92*1000 -> 66920 | M24: 390396 | N24: 242166 | P24: =E24/M24 -> 9.5507644 | Q24: =E24/N24 -> 15.396795 | R24: =(M24/G24)-1 -> 0.17645853 | S24: =R24+K24/G24 -> 0.37812199 | T24: =E24/K24 -> 55.716979
A25: 1Financial data as of March 31, 2026 (GitLab reflects LTM/NTM through April 30, 2026 per fiscal reporting calendar) | V25: Method 2: EV/EBITDA (NTM) - Implied Valuation
A26: 2EBITDA is presented on an adjusted basis throughout: LTM figures represent GAAP EBITDA plus stock-based compensation (self-calculated via financial statements); NTM figures reflect non-GAAP consensus estimates. This approach ensures consistency across the peer set given inconsistent GAAP estimates | V26: Statisitic | W26: Peer Mutliple | X26: Target Metric | Y26: Implied EV | Z26: (-) Net Debt | AA26: Implied Equity Value | AB26: Implied Share Price
A27: P/E is excluded as Atlassian and several peers report negative LTM net income
A28: 4Microsoft is included as a reference, excluded from average/median due to scale mismatch | V28: Low | W28: =MIN(Q16:Q21) -> 8.4230762 | X28: =$N$15 -> 1969.5535 | Y28: =W28*X28 -> 16589.699 | Z28: =Z18 -> -6.602 | AA28: =Y28+Z28 -> 16583.097 | AB28: =AA28/$W$13 -> 63.741917
A29: Source: Factset, Team Analysis | V29: 25th Percentile | W29: =_xlfn.QUARTILE.INC(Q16:Q21,1) -> 11.320459 | X29: =$N$15 -> 1969.5535 | Y29: =W29*X29 -> 22296.249 | Z29: =Z19 -> -6.602 | AA29: =Y29+Z29 -> 22289.647 | AB29: =AA29/$W$13 -> 85.676687
V30: Median | W30: =MEDIAN(Q16:Q21) -> 14.802209 | X30: =$N$15 -> 1969.5535 | Y30: =W30*X30 -> 29153.742 | Z30: =Z20 -> -6.602 | AA30: =Y30+Z30 -> 29147.14 | AB30: =AA30/$W$13 -> 112.03544
J31: Rolling LTM SBC | V31: Mean | W31: =AVERAGE(Q16:Q21) -> 20.172586 | X31: =$N$15 -> 1969.5535 | Y31: =W31*X31 -> 39730.988 | Z31: =Z21 -> -6.602 | AA31: =Y31+Z31 -> 39724.386 | AB31: =AA31/$W$13 -> 152.69213
A32: Metric | C32: Measurement | J32: Atlassian Corp | K32: 1606.561 | V32: 75th Percentile | W32: =_xlfn.QUARTILE.INC(Q16:Q21,3) -> 19.842665 | X32: =$N$15 -> 1969.5535 | Y32: =W32*X32 -> 39081.191 | Z32: =Z22 -> -6.602 | AA32: =Y32+Z32 -> 39074.589 | AB32: =AA32/$W$13 -> 150.19445
A33: EV/Rev (NTM) | C33: Measures market valuation of Atlassian's top-line sales (independent of profitability) | J33: ServiceNow | K33: =1955+547-470 -> 2032 | V33: High | W33: =MAX(Q16:Q21) -> 51.32533 | X33: =$N$15 -> 1969.5535 | Y33: =W33*X33 -> 101087.98 | Z33: =Z23 -> -6.602 | AA33: =Y33+Z33 -> 101081.38 | AB33: =AA33/$W$13 -> 388.53545
A34: =Q13 -> EV/EBITDA (NTM) | C34: Determines whether a company is undervalued/overvalued by comparing its total business value to its core cash earnings | J34: GitLab | K34: =50.1+53.2+41.1+42.9 -> 187.3
A35: =R13 -> Revenue Growth (LTM, implied) | C35: Increase in company's YoY sales | J35: Monday.com | K35: 177.01 | V35: Method 3: EV/FCF (LTM) - Implied Valuation
A36: Rule of 40 (EBITDA) | C36: SaaS industry multiple that states a company's annual revenue growth rate and its profit margin should total 40% or more | J36: Asana | K36: 160.37 | V36: Statisitic | W36: Peer Mutliple | X36: Target Metric | Y36: Implied EV | Z36: (-) Net Debt | AA36: Implied Equity Value | AB36: Implied Share Price
A37: =T13 -> EV/FCF (LTM) | C37: Measures how many dollars of company valuation you pay for each dollar generated | J37: MSFT | K37: 12405
J38: HubSpot | K38: 406.6 | V38: Low | W38: =MIN(T16:T21) -> 9.4703232 | X38: =$W$7 -> 1319.069 | Y38: =W38*X38 -> 12492.01 | Z38: =Z28 -> -6.602 | AA38: =Y38+Z38 -> 12485.408 | AB38: =AA38/$W$13 -> 47.991266
J39: Freshworks | K39: 102.1 | V39: 25th Percentile | W39: =_xlfn.QUARTILE.INC(T16:T21,1) -> 12.696103 | X39: =$W$7 -> 1319.069 | Y39: =W39*X39 -> 16747.036 | Z39: =Z29 -> -6.602 | AA39: =Y39+Z39 -> 16740.434 | AB39: =AA39/$W$13 -> 64.346685
V40: Median | W40: =T23 -> 16.094073 | X40: =$W$7 -> 1319.069 | Y40: =W40*X40 -> 21229.193 | Z40: =Z30 -> -6.602 | AA40: =Y40+Z40 -> 21222.591 | AB40: =AA40/$W$13 -> 81.575148
V41: Mean | W41: =T22 -> 19.101425 | X41: =$W$7 -> 1319.069 | Y41: =W41*X41 -> 25196.097 | Z41: =Z31 -> -6.602 | AA41: =Y41+Z41 -> 25189.495 | AB41: =AA41/$W$13 -> 96.82309
V42: 75th Percentile | W42: =_xlfn.QUARTILE.INC(T16:T21,3) -> 26.738513 | X42: =$W$7 -> 1319.069 | Y42: =W42*X42 -> 35269.944 | Z42: =Z32 -> -6.602 | AA42: =Y42+Z42 -> 35263.342 | AB42: =AA42/$W$13 -> 135.54483
V43: High | W43: =MAX(T16:T21) -> 31.099973 | X43: =$W$7 -> 1319.069 | Y43: =W43*X43 -> 41023.01 | Z43: =Z33 -> -6.602 | AA43: =Y43+Z43 -> 41016.408 | AB43: =AA43/$W$13 -> 157.6584
V45: Summary: Implied Share Price Range by Method
V46: Method | W46: Low (25th Pctl.) | Y46: Median | AA46: High (75th Pctl.)
V48: EV/ Revenue (NTM) | W48: =AB19 -> 63.629874 | Y48: =AB20 -> 77.397194 | AA48: =AB22 -> 162.95376
V49: EV/EBITDA (NTM) | W49: =AB29 -> 85.676687 | Y49: =AB30 -> 112.03544 | AA49: =AB32 -> 150.19445
V50: EV/FCF (LTM) | W50: =AB39 -> 64.346685 | Y50: =AB40 -> 81.575148 | AA50: =AB42 -> 135.54483
V51: Blended Average (all methods) | W51: =AVERAGE(W48:W50) -> 71.217749 | Y51: =AVERAGE(Y48:Y50) -> 90.335928 | AA51: =AVERAGE(AA48:AA50) -> 149.56435
V53: VWAP Share Price (USD$) | W53: =C15 -> 178.1217
V54: Premium/(Discount) to Blended Median | W54: =Y51/W53-1 -> -0.49284155

Sheet Monte Carlo, VaR &CVaR
A1: Updated 5/08/2026
B2: Atlassian (TEAM) - DCF Monte Carlo Simulation Results | I2: Monte Carlo Python Data
B3: Implied Share Price Distribution - 50,000 Simulations | I3: Variable | J3: Distribution | L3: Standard Deviation | M3: Justification
I4: Sales Growth (YoY) | J4: Normal, centered on detrended sales growth (2016 to 2026) | L4: 0.041041 | M4: FCF driver
B5: Percentile (%) | D5: Implied Share Price (USD$) | F5: Interpretation | I5: FCF Margin | J5: Normal, centered on FCF/sales ratio (2023 to 2026) | L5: 0.056499 | M5: CAPEX/WC/NI uncertainty
I6: WACC | J6: Normal, centered at 9.49% | L6: ='WACC FF Data'!B26*WACC!H19 -> 0.020873254 | M6: Discount rate risk
B7: 5th Percentile | D7: 35.49 | F7: Bearish tail - only 5% of outcomes fall below | I7: Long-run growth rate (g_L) | J7: Normal, centered at 3.5% (1986 to 2026) | L7: 0.010689 | M7: Terminal value sensitivity
B8: 10th Percentile | D8: 44.25
B9: 25th Percentile | D9: 64.45
B10: 50th Percentile | D10: 99.31 | F10: Median - Central Estimate
B11: Mean | D11: 125.01 | F11: Simulation Average
B12: 75th Percentile | D12: 155.35
B13: 90th Percentile | D13: 233.8
B14: 95th Percentile | D14: 302.2 | F14: Bullish tail - only 5% of outcomes exceed above
B15: Current Share Price: | F15: ='VWAP LIVE'!I5 -> 178.1217 | I15: 529.5 | J15: 748.4 | K15: 1024.3 | L15: 1397 | M15: 1768 | N15: 2124 | O15: 2543 | P15: 2960 | Q15: 3261
I16: 2608 | J16: 2460 | K16: 4519 | L16: 5896 | M16: 7245 | N16: 8971 | O16: 10984 | P16: 13278 | Q16: 14732
E17: ="90% Confidence Range: "&TEXT(D7,"$#,##0.00")&" - "&TEXT(D14,"$#,##0.00") -> 90% Confidence Range: $35.49 - $302.20 | I17: =I15/I16 -> 0.20302914 | J17: =J15/J16 -> 0.30422764 | K17: =K15/K16 -> 0.22666519 | L17: =L15/L16 -> 0.2369403 | M17: =M15/M16 -> 0.24403037 | N17: =N15/N16 -> 0.2367629 | O17: =O15/O16 -> 0.23151857 | P17: =P15/P16 -> 0.22292514 | Q17: =Q15/Q16 -> 0.22135487
I19: 78.1 | J19: 161.1 | K19: 308.2 | L19: 519 | M19: 729.7 | N19: 972 | O19: 1232 | P19: 1366.6
I20: 24.6 | J20: 43.5 | K20: 73.7 | L20: 127 | M20: 156.5 | N20: 213.7 | O20: 320.8 | P20: 355.7
I21: =I20/I19 -> 0.31498079 | J21: =J20/J19 -> 0.27001862 | K21: =K20/K19 -> 0.23913043 | L21: =L20/L19 -> 0.24470135 | M21: =M20/M19 -> 0.2144717 | N21: =N20/N19 -> 0.21985597 | O21: =O20/O19 -> 0.26038961 | P21: =P20/P19 -> 0.26028099
I22: `

Sheet Sensitivity Analysis
A1: Atlassian Sensitivity Analysis
A2: NASDAQ: TEAM
C4: TGR | D4: WACC
D5: =K49 -> 107.76789 | E5: 0.08 | F5: 0.085 | G5: 0.09 | H5: =WACC!H55 -> 0.098174268 | I5: 0.1 | J5: 0.105 | K5: 0.11
D6: 0.02 | E6: 122.02928 | F6: 111.41606 | G6: 102.34399 | H6: 90.058526 | I6: 87.665054 | J6: 81.649436 | K6: 76.319605
D7: 0.025 | E7: 131.63233 | F7: 119.35621 | G7: 108.99516 | H7: 95.154928 | I7: 92.483727 | J7: 85.805879 | K7: 79.931756
D8: 0.03 | E8: 143.156 | F8: 128.74003 | G8: 116.75486 | H8: 100.99888 | I8: 97.990782 | J8: 90.516515 | K8: 83.995425
D9: 0.0325 | E9: 149.8276 | F9: 134.10221 | G9: 121.14078 | H9: 104.25455 | I9: 101.05026 | J9: 93.115486 | K9: 86.223888
D10: ='DCF FINAL'!J44 -> 0.035 | E10: 157.24048 | F10: 140.00061 | G10: 125.92542 | H10: 107.76789 | I10: 104.34508 | J10: 95.900098 | K10: 88.600916
D11: 0.0375 | E11: 165.52547 | F11: 146.51989 | G11: 131.16574 | H11: 111.57076 | I11: 107.90348 | J11: 98.890978 | K11: 91.141877
D12: 0.04 | E12: 174.84608 | F12: 153.76354 | G12: 136.93009 | H12: 115.70048 | I12: 111.75842 | J12: 102.11193 | K12: 93.864335
F18: 43983 | G18: 44377 | H18: =EDATE(G18,12) -> 44742 | I18: =EDATE(H18,12) -> 45107 | J18: =EDATE(I18,12) -> 45473 | K18: =EDATE(J18,12) -> 45838 | L18: =EDATE(K18,12) -> 46203 | M18: =EDATE(L18,12) -> 46568 | N18: =EDATE(M18,12) -> 46934 | O18: =EDATE(N18,12) -> 47299 | ... R18: =EDATE(Q18,12) -> 48395
C19: =Cover!E5 -> Base Case | F19: Actuals | G19: Actuals | H19: Actuals | I19: Actuals | J19: Actuals | K19: Actuals | L19: Actuals | M19: Forecast | N19: Forecast | O19: Forecast | P19: Forecast | Q19: Forecast | R19: Forecast
L20: 0 | M20: 1 | N20: 2 | O20: 3 | P20: 4 | Q20: 5 | R20: 6
C22: Revenue | F22: ='IS Intergrated'!E10 -> 1614.173 | G22: ='DCF FINAL'!E11 -> 2089.132 | H22: ='DCF FINAL'!F11 -> 2802.882 | I22: ='DCF FINAL'!G11 -> 3534.647 | J22: ='DCF FINAL'!H11 -> 4358.603 | K22: ='DCF FINAL'!I11 -> 5215.304 | L22: ='DCF FINAL'!J11 -> 6572.308 | M22: ='DCF FINAL'!K11 -> 7540.3559 | N22: ='DCF FINAL'!L11 -> 9131.9763 | ... R22: ='DCF FINAL'!P11 -> 16156.084
C23: COGS (Excl. D&A) | F23: ='IS Intergrated'!E17 -> 183.628 | G23: ='IS Intergrated'!F17 -> 253.859 | H23: ='IS Intergrated'!G17 -> 410.354 | I23: ='IS Intergrated'!H17 -> 581.285 | J23: ='IS Intergrated'!I17 -> 724.757 | K23: ='IS Intergrated'!J17 -> 816.113 | L23: ='IS Intergrated'!K17 -> 856.162 | M23: ='IS Intergrated'!L17 -> 1194.4376 | ... R23: ='IS Intergrated'!Q17 -> 2963.1227
C24: Gross Profit | F24: ='IS Intergrated'!E22 -> 1345.366 | G24: ='IS Intergrated'!F22 -> 1753.111 | H24: ='IS Intergrated'!G22 -> 2337.175 | I24: ='IS Intergrated'!H22 -> 2900.882 | J24: ='IS Intergrated'!I22 -> 3555.108 | K24: ='IS Intergrated'!J22 -> 4320.453 | L24: ='IS Intergrated'!K22 -> 5575.476 | M24: ='IS Intergrated'!L22 -> 6206.7684 | ... R24: ='IS Intergrated'!Q22 -> 13112.27
C26: EBITDA | F26: ='DCF FINAL'!D17 -> 99.265 | G26: ='DCF FINAL'!E17 -> 183.796 | H26: ='DCF FINAL'!F17 -> -51.104 | I26: ='DCF FINAL'!G17 -> -292.742 | J26: ='DCF FINAL'!H17 -> -38.339 | K26: ='DCF FINAL'!I17 -> -51.654 | L26: ='DCF FINAL'!J17 -> 151.023 | M26: ='DCF FINAL'!K17 -> 188.90568 | ... R26: ='DCF FINAL'!P17 -> 2585.8235
C28: EBIT | F28: ='IS Intergrated'!E29 -> 14.086 | G28: ='IS Intergrated'!F29 -> 101.634 | H28: ='IS Intergrated'!G29 -> -106.457 | I28: ='IS Intergrated'!H29 -> -345.222 | J28: ='IS Intergrated'!I29 -> -117.077 | K28: ='IS Intergrated'!J29 -> -130.392 | L28: ='IS Intergrated'!K29 -> 10.353 | M28: ='IS Intergrated'!L29 -> 49.755724 | ... R28: ='IS Intergrated'!Q29 -> 2505.1327
C30: Net Income | F30: ='IS Intergrated'!E41 -> -350.654 | G30: ='IS Intergrated'!F41 -> -696.315 | H30: ='IS Intergrated'!G41 -> -614.124 | I30: ='IS Intergrated'!H41 -> -486.761 | J30: ='IS Intergrated'!I41 -> -300.519 | K30: ='IS Intergrated'!J41 -> -256.687 | L30: ='IS Intergrated'!K41 -> -53.83 | M30: ='IS Intergrated'!L41 -> 47.013799 | ... R30: ='IS Intergrated'!Q41 -> 2004.8774
C32: Unlevered FCF | F32: ='DCF FINAL'!D31 -> -195.8686 | G32: ='DCF FINAL'!E31 -> -507.23288 | H32: ='DCF FINAL'!F31 -> -399.76124 | I32: ='DCF FINAL'!G31 -> -174.44872 | J32: ='DCF FINAL'!H31 -> 296.19748 | K32: ='DCF FINAL'!I31 -> 18.792 | L32: ='DCF FINAL'!J31 -> -360.801 | M32: ='DCF FINAL'!K31 -> 499.19776 | ... R32: ='DCF FINAL'!P31 -> 2422.7727
C33: PV FCF | M33: =M32/(1+$K$52)^M20 -> 454.57062 | N33: =N32/(1+$K$52)^N20 -> 612.67767 | O33: =O32/(1+$K$52)^O20 -> 765.30508 | P33: =P32/(1+$K$52)^P20 -> 1004.276 | Q33: =Q32/(1+$K$52)^Q20 -> 1182.1386 | R33: =R32/(1+$K$52)^R20 -> 1381.2907
C35: Terminal Value | K35: =R32*(1+K53)/(K52-K53) -> 39692.897
C36: PV of Terminal Value | K36: =K35/(1+K52)^R20 -> 22630.034
C37: PV of FCF | K37: =SUM(L33:R33) -> 5400.2587
C39: Terminal Value SBC | K39: ='DCF FINAL'!J51 -> 14641.236
C40: PV of Terminal Value of SBC | K40: ='DCF FINAL'!J52 -> 8347.3794
C41: Sum of PV of SBC | K41: ='DCF FINAL'!J53 -> 2922.5093
C43: Enterprise Value | K43: =(K36+K37) -> 28030.293
C44: (+) Cash | K44: ='BS Intergrated'!K11 -> 1239.512
C45: (-) Debt | K45: ='DCF FINAL'!J57 -> 1232.91
C46: Equity Value | K46: =K43+K44-K45 -> 28036.895
C47: Number of Shares Outstanding (m) | K47: ='Comp. Multi & Imp. Val'!W13 -> 260.16
C49: Implied Share Price | K49: =K46/K47 -> 107.76789
C50: Current Share Price | K50: ='VWAP LIVE'!I5 -> 178.1217
C52: WACC | K52: =WACC!H55 -> 0.098174268
C53: Terminal Growth Rate | K53: 0.035

Sheet Reverse DCF
B2: Reverse DCF Model | G2: 46174 | H2: 46539 | I2: 46905 | J2: 47270 | K2: 47635 | L2: 48000 | M2: 48366
B3: ($ in millions) | F3: =Cover!E5 -> Base Case | G3: Actuals | H3: Forecast | I3: Forecast | J3: Forecast | K3: Forecast | L3: Forecast | M3: Forecast
G4: 0 | H4: 1 | I4: 2 | J4: 3 | K4: 4 | L4: 5 | M4: 6
B6: Growth Scaling Factor (Goalseek) | G6: 1.6071837
B7: Revenue | G7: ='DCF FINAL'!J11 -> 6572.308 | H7: =G7*(1+H9) -> 8128.1389 | I7: =H7*(1+I9) -> 10885.567 | J7: =I7*(1+J9) -> 14494.072 | K7: =J7*(1+K9) -> 18641.712 | L7: =K7*(1+L9) -> 22546.009 | M7: =L7*(1+M9) -> 26222.384
B8: Base Compound Annual Growth Rate | F8: =_xlfn.RRI('DCF FINAL'!P7,'DCF FINAL'!J11,'DCF FINAL'!P11) -> 0.16172419 | H8: ='DCF FINAL'!K10 -> 0.14729193 | I8: ='DCF FINAL'!L10 -> 0.21108027 | J8: ='DCF FINAL'!M10 -> 0.20625793 | K8: ='DCF FINAL'!N10 -> 0.17805129 | L8: ='DCF FINAL'!O10 -> 0.13031412 | M8: ='DCF FINAL'!P10 -> 0.10145761
B9: Scaled Growth Rate | H9: =H8*$G$6 -> 0.23672519 | I9: =I8*$G$6 -> 0.33924477 | J9: =J8*$G$6 -> 0.33149438 | K9: =K8*$G$6 -> 0.28616114 | L9: =L8*$G$6 -> 0.20943874 | M9: =M8*$G$6 -> 0.16306102
B10: Scaled Compound Annual Growth Rate % | F10: =_xlfn.RRI(M4,G7,M7) -> 0.25938653
B11: EBIT | G11: =G7*G12 -> 10.353 | H11: =H7*H12 -> 53.634263 | I11: =I7*I12 -> 260.64917 | J11: =J7*J12 -> 592.0075 | K11: =K7*K12 -> 1439.8358 | L11: =L7*L12 -> 2666.4099 | M11: =M7*M12 -> 4065.9948
B12: % EBIT Margin | G12: ='IS Intergrated'!K29/'IS Intergrated'!K10 -> 0.0015752457 | H12: ='IS Intergrated'!L29/'IS Intergrated'!L10 -> 0.0065985909 | I12: ='IS Intergrated'!M29/'IS Intergrated'!M10 -> 0.023944473 | J12: ='IS Intergrated'!N29/'IS Intergrated'!N10 -> 0.040844802 | K12: ='IS Intergrated'!O29/'IS Intergrated'!O10 -> 0.077237315 | L12: ='IS Intergrated'!P29/'IS Intergrated'!P10 -> 0.11826527 | M12: ='IS Intergrated'!Q29/'IS Intergrated'!Q10 -> 0.15505817
B13: Non-Operating Income | G13: ='IS Intergrated'!K31 -> 11.695 | H13: ='IS Intergrated'!L31 -> 12.104538 | I13: ='IS Intergrated'!M31 -> 22.941378 | J13: ='IS Intergrated'!N31 -> 35.760401 | K13: ='IS Intergrated'!O31 -> 57.610478 | L13: ='IS Intergrated'!P31 -> 88.971914 | M13: ='IS Intergrated'!Q31 -> 132.86386
B14: Less: Taxes | G14: ='IS Intergrated'!K38 -> 75.878 | H14: =(H11+H13)*WACC!$H$23 -> 15.777312 | I14: =(I11+I13)*WACC!$H$23 -> 68.061732 | J14: =(J11+J13)*WACC!$H$23 -> 150.6643 | K14: =(K11+K13)*WACC!$H$23 -> 359.38711 | L14: =(L11+L13)*WACC!$H$23 -> 661.29164 | M14: =(M11+M13)*WACC!$H$23 -> 1007.7261
B15: Net Income | G15: =G11+G13-G14 -> -53.83 | H15: =H11+H13-H14 -> 49.961489 | I15: =I11+I13-I14 -> 215.52882 | J15: =J11+J13-J14 -> 477.10361 | K15: =K11+K13-K14 -> 1138.0592 | L15: =L11+L13-L14 -> 2094.0902 | M15: =M11+M13-M14 -> 3191.1326
B16: % NI Margin | G16: =G15/G7 -> -0.0081904256 | H16: =H15/H7 -> 0.0061467317 | I16: =I15/I7 -> 0.019799502 | J16: =J15/J7 -> 0.032917155 | K16: =K15/K7 -> 0.061049069 | L16: =L15/L7 -> 0.092880749 | M16: =M15/M7 -> 0.12169498 | P16: =26.37-25.94 -> 0.43 | R16: =25.94-16.17 -> 9.77
B17: (+) D&A | G17: =G18*G7 -> 140.67 | H17: =H18*H7 -> 149.99692 | I17: =I18*I7 -> 175.34633 | J17: =J18*J7 -> 205.92914 | K17: =K18*K7 -> 238.89923 | L17: =L18*L7 -> 153.02756 | M17: =M18*M7 -> 130.96646
B18: % D&A Margin | G18: ='IS Intergrated'!K18/'IS Intergrated'!K10 -> 0.02140344 | H18: ='IS Intergrated'!L18/'IS Intergrated'!L10 -> 0.01845403 | I18: ='IS Intergrated'!M18/'IS Intergrated'!M10 -> 0.016108148 | J18: ='IS Intergrated'!N18/'IS Intergrated'!N10 -> 0.014207818 | K18: ='IS Intergrated'!O18/'IS Intergrated'!O10 -> 0.012815305 | L18: ='IS Intergrated'!P18/'IS Intergrated'!P10 -> 0.006787346 | M18: ='IS Intergrated'!Q18/'IS Intergrated'!Q10 -> 0.0049944528
B19: (-) CapEx | G19: =G20*G7 -> -34.06 | H19: =H20*H7 -> -63.286166 | I19: =I20*I7 -> -75.838234 | J19: =J20*J7 -> -99.0657 | K19: =K20*K7 -> -112.62354 | L19: =L20*L7 -> -103.90213 | M19: =M20*M7 -> -96.549812
B20: % CapEx Margin | G20: ='CF Intergrated'!K30/'IS Intergrated'!K10 -> -0.0051823499 | H20: ='CF Intergrated'!L30/'IS Intergrated'!L10 -> -0.0077860586 | I20: ='CF Intergrated'!M30/'IS Intergrated'!M10 -> -0.0069668608 | J20: ='CF Intergrated'!N30/'IS Intergrated'!N10 -> -0.0068349115 | K20: ='CF Intergrated'!O30/'IS Intergrated'!O10 -> -0.0060414803 | L20: ='CF Intergrated'!P30/'IS Intergrated'!P10 -> -0.0046084487 | M20: ='CF Intergrated'!Q30/'IS Intergrated'!Q10 -> -0.0036819616
B21: (-) Change in NWC | G21: =G22*G7 -> -375.999 | H21: =H22*H7 -> 445.22858 | I21: =I22*I7 -> 611.59859 | J21: =J22*J7 -> 795.40262 | K21: =K22*K7 -> 874.10224 | L21: =L22*L7 -> 786.12255 | M21: =M22*M7 -> 710.86852
B22: % Δ NWC Margin | G22: ='CF Intergrated'!K18/'IS Intergrated'!K10 -> -0.057209583 | H22: ='CF Intergrated'!L18/'IS Intergrated'!L10 -> 0.054776203 | I22: ='CF Intergrated'!M18/'IS Intergrated'!M10 -> 0.056184355 | J22: ='CF Intergrated'!N18/'IS Intergrated'!N10 -> 0.054877789 | K22: ='CF Intergrated'!O18/'IS Intergrated'!O10 -> 0.04688959 | L22: ='CF Intergrated'!P18/'IS Intergrated'!P10 -> 0.034867482 | M22: ='CF Intergrated'!Q18/'IS Intergrated'!Q10 -> 0.027109226
B23: (+) Int Exp | G23: =G24*G7 -> -37.582 | H23: =H24*H7 -> -44.506899 | I23: =I24*I7 -> -49.216913 | J23: =J24*J7 -> -54.326725 | K23: =K24*K7 -> -59.312293 | L23: =L24*L7 -> -63.464291 | M23: =M24*M7 -> -67.013784
B24: % Int. Exp Margin | G24: ='DCF FINAL'!J27/'DCF FINAL'!J11 -> -0.0057182348 | H24: ='DCF FINAL'!K27/'DCF FINAL'!K11 -> -0.0054756568 | I24: ='DCF FINAL'!L27/'DCF FINAL'!L11 -> -0.0045212997 | J24: ='DCF FINAL'!M27/'DCF FINAL'!M11 -> -0.0037482031 | K24: ='DCF FINAL'!N27/'DCF FINAL'!N11 -> -0.0031816977 | L24: ='DCF FINAL'!O27/'DCF FINAL'!O11 -> -0.0028148792 | M24: ='DCF FINAL'!P27/'DCF FINAL'!P11 -> -0.0025555947
B25: (+) Stock Based Compensation | G25: =G26*G7 -> 1606.561 | H25: =H26*H7 -> 1919.4522 | I25: =I26*I7 -> 2516.1885 | J25: =J26*J7 -> 3277.8205 | K25: =K26*K7 -> 4122.5968 | L25: =L26*L7 -> 4873.2982 | M25: =M26*M7 -> 5536.8313
B26: % SBC Margin | G26: ='DCF FINAL'!J28/'DCF FINAL'!J11 -> 0.24444396 | H26: ='DCF FINAL'!K28/'DCF FINAL'!K11 -> 0.23614904 | I26: ='DCF FINAL'!L28/'DCF FINAL'!L11 -> 0.23114904 | J26: ='DCF FINAL'!M28/'DCF FINAL'!M11 -> 0.22614904 | K26: ='DCF FINAL'!N28/'DCF FINAL'!N11 -> 0.22114904 | L26: ='DCF FINAL'!O28/'DCF FINAL'!O11 -> 0.21614904 | M26: ='DCF FINAL'!P28/'DCF FINAL'!P11 -> 0.21114904
B27: (-) Adjustment For SBC | G27: =G28*G7 -> -1185.6894 | H27: =H28*H7 -> -1416.6124 | I27: =I28*I7 -> -1857.0213 | J27: =J28*J7 -> -2419.1282 | K27: =K28*K7 -> -3042.5981 | L27: =L28*L7 -> -3596.6378 | M27: =M28*M7 -> -4086.3448
B28: % SBC Adjustment | G28: ='DCF FINAL'!J29/'DCF FINAL'!J11 -> -0.18040685 | H28: ='DCF FINAL'!K29/'DCF FINAL'!K11 -> -0.17428496 | I28: ='DCF FINAL'!L29/'DCF FINAL'!L11 -> -0.17059481 | J28: ='DCF FINAL'!M29/'DCF FINAL'!M11 -> -0.16690466 | K28: ='DCF FINAL'!N29/'DCF FINAL'!N11 -> -0.16321452 | L28: ='DCF FINAL'!O29/'DCF FINAL'!O11 -> -0.15952437 | M28: ='DCF FINAL'!P29/'DCF FINAL'!P11 -> -0.15583422
B30: Free Cash Flow to Firm (FCFF) | G30: =G15+G17+G19+G21+G23 -> -360.801 | H30: =H15+H17+H19+H21+H23 -> 537.39392 | I30: =I15+I17+I19+I21+I23 -> 877.41859 | J30: =J15+J17+J19+J21+J23 -> 1325.0429 | K30: =K15+K17+K19+K21+K23 -> 2079.1248 | L30: =L15+L17+L19+L21+L23 -> 2865.8739 | M30: =M15+M17+M19+M21+M23 -> 3869.404
B31: Discount Factor (WACC) | F31: =WACC!H8 -> 0.098174268
B32: Present Value of SBC | H32: =(H25+H27)/(1+$F$31)^H4 -> 457.88712 | I32: =(I25+I27)/(1+$F$31)^I4 -> 546.57912 | J32: =(J25+J27)/(1+$F$31)^J4 -> 648.37128 | K32: =(K25+K27)/(1+$F$31)^K4 -> 742.57136 | L32: =(L25+L27)/(1+$F$31)^L4 -> 799.31702 | M32: =(M25+M27)/(1+$F$31)^M4 -> 826.96304
B33: Present Value of FCFF | H33: =H30/(1+$F$31)^H4 -> 489.35213 | I33: =I30/(1+$F$31)^I4 -> 727.55245 | J33: =J30/(1+$F$31)^J4 -> 1000.4979 | K33: =K30/(1+$F$31)^K4 -> 1429.5374 | L33: =L30/(1+$F$31)^L4 -> 1794.3236 | M33: =M30/(1+$F$31)^M4 -> 2206.0558
B37: Implied DCF Valuation | I37: Share Price Calculation
B38: Present Value of FCFFs | G38: =+SUM(H33:M33) -> 7647.3192 | I38: Diluted Shares Outstanding (mm) | L38: ='Comp. Multi & Imp. Val'!W13 -> 260.16
B39: Long-Term Growth Rate | G39: ='DCF FINAL'!J44 -> 0.035 | I39: Implied Share Price | L39: =G51/L38 -> 168.34368
B40: Final Year FCF × (1 + g) | G40: =M30*(1+G39) -> 4004.8331 | I40: Current Market Share Price | L40: ='VWAP LIVE'!I5 -> 178.1217
B41: Terminal Value in Final Year | G41: =G40/(F31-G39) -> 63393.423 | I41: Implied Growth Rate | L41: =F10 -> 0.25938653
B42: Present Value of Terminal Value | G42: =G41/(1+F31)^M4 -> 36142.37
B44: Terminal Value SBC | G44: =((M25+M27)*(1+G39))/(F31-G39) -> 23763.686
B45: PV of Terminal Value of SBC | G45: =G44/(1+F31)^M4 -> 13548.344
B46: Sum of PV of SBC | G46: =SUM(H32:M32) -> 4021.6889
B48: Total Enterprise Value (TEV) | G48: =(G38+G42) -> 43789.689
B49: (+) Cash | G49: ='DCF FINAL'!J56 -> 1239.512
B50: (-) Net Debt | G50: ='BS Intergrated'!K58+'BS Intergrated'!K59+'BS Intergrated'!K51 -> 1232.91
B51: Equity Value | G51: =G48+G49-G50 -> 43796.291

Sheet DuPont Analysis
D5: Year | E5: 2020A | F5: 2021A | G5: 2022A | H5: 2023A | I5: 2024A | J5: 2025A | K5: 2026A | L5: 2027E | M5: 2028E | N5: 2029E | O5: 2030E | P5: 2031E | Q5: 2032E
D6: DuPont Analysis
D7: Gross Margin | E7: ='DCF FINAL'!D13/'DCF FINAL'!D11 -> 0.8862402 | F7: ='DCF FINAL'!E13/'DCF FINAL'!E11 -> 0.8784859 | G7: ='DCF FINAL'!F13/'DCF FINAL'!F11 -> 0.85359569 | H7: ='DCF FINAL'!G13/'DCF FINAL'!G11 -> 0.83554652 | I7: ='DCF FINAL'!H13/'DCF FINAL'!H11 -> 0.83371805 | J7: ='DCF FINAL'!I13/'DCF FINAL'!I11 -> 0.84351574 | K7: ='DCF FINAL'!J13/'DCF FINAL'!J11 -> 0.86973191 | L7: ='DCF FINAL'!K13/'DCF FINAL'!K11 -> 0.841594 | ... Q7: ='DCF FINAL'!P13/'DCF FINAL'!P11 -> 0.816594
D8: EBITDA Margin | E8: ='IS Intergrated'!E55/'IS Intergrated'!E10 -> 0.061495887 | F8: ='IS Intergrated'!F55/'IS Intergrated'!F10 -> 0.087977208 | G8: ='IS Intergrated'!G55/'IS Intergrated'!G10 -> -0.018232662 | H8: ='IS Intergrated'!H55/'IS Intergrated'!H10 -> -0.082820717 | I8: ='IS Intergrated'!I55/'IS Intergrated'!I10 -> -0.008796167 | J8: ='IS Intergrated'!J55/'IS Intergrated'!J10 -> -0.0099043124 | K8: ='IS Intergrated'!K55/'IS Intergrated'!K10 -> 0.022978686 | L8: ='IS Intergrated'!L55/'IS Intergrated'!L10 -> 0.025052621 | ... Q8: ='IS Intergrated'!Q55/'IS Intergrated'!Q10 -> 0.16005262
D9: Net Profit Margin | E9: ='IS Intergrated'!E41/'IS Intergrated'!E10 -> -0.21723446 | F9: ='IS Intergrated'!F41/'IS Intergrated'!F10 -> -0.3333035 | G9: ='IS Intergrated'!G41/'IS Intergrated'!G10 -> -0.21910448 | H9: ='IS Intergrated'!H41/'IS Intergrated'!H10 -> -0.13771135 | I9: ='IS Intergrated'!I41/'IS Intergrated'!I10 -> -0.068948468 | J9: ='IS Intergrated'!J41/'IS Intergrated'!J10 -> -0.049218032 | K9: ='IS Intergrated'!K41/'IS Intergrated'!K10 -> -0.0081904256 | L9: ='IS Intergrated'!L41/'IS Intergrated'!L10 -> 0.0062349576 | ... Q9: ='IS Intergrated'!Q41/'IS Intergrated'!Q10 -> 0.12409427
D10: Asset Turnover | E10: - | F10: ='IS Intergrated'!F10/(('BS Intergrated'!F42+'BS Intergrated'!E42)/2) -> 0.61090947 | G10: ='IS Intergrated'!G10/(('BS Intergrated'!G42+'BS Intergrated'!F42)/2) -> 0.88887966 | H10: ='IS Intergrated'!H10/(('BS Intergrated'!H42+'BS Intergrated'!G42)/2) -> 0.94661204 | I10: ='IS Intergrated'!I10/(('BS Intergrated'!I42+'BS Intergrated'!H42)/2) -> 0.93543073 | J10: ='IS Intergrated'!J10/(('BS Intergrated'!J42+'BS Intergrated'!I42)/2) -> 0.92682713 | K10: ='IS Intergrated'!K10/(('BS Intergrated'!K42+'BS Intergrated'!J42)/2) -> 1.0822623 | L10: ='IS Intergrated'!L10/(('BS Intergrated'!L42+'BS Intergrated'!K42)/2) -> 1.1966916 | M10: ='IS Intergrated'!M10/(('BS Intergrated'!M42+'BS Intergrated'!L42)/2) -> 1.3016542 | ... Q10: ='IS Intergrated'!Q10/(('BS Intergrated'!Q42+'BS Intergrated'!P42)/2) -> 1.1295075
D11: Return on Assets | E11: - | F11: ='IS Intergrated'!F41/(('BS Intergrated'!F42+'BS Intergrated'!E42)/2) -> -0.20361826 | G11: ='IS Intergrated'!G41/(('BS Intergrated'!G42+'BS Intergrated'!F42)/2) -> -0.19475751 | H11: ='IS Intergrated'!H41/(('BS Intergrated'!H42+'BS Intergrated'!G42)/2) -> -0.13035922 | I11: ='IS Intergrated'!I41/(('BS Intergrated'!I42+'BS Intergrated'!H42)/2) -> -0.064496516 | J11: ='IS Intergrated'!J41/(('BS Intergrated'!J42+'BS Intergrated'!I42)/2) -> -0.045616608 | K11: ='IS Intergrated'!K41/(('BS Intergrated'!K42+'BS Intergrated'!J42)/2) -> -0.0088641891 | L11: ='IS Intergrated'!L41/(('BS Intergrated'!L42+'BS Intergrated'!K42)/2) -> 0.0074613212 | M11: ='IS Intergrated'!M41/(('BS Intergrated'!M42+'BS Intergrated'!L42)/2) -> 0.026172456 | ... Q11: ='IS Intergrated'!Q41/(('BS Intergrated'!Q42+'BS Intergrated'!P42)/2) -> 0.14016541
D12: Financial Leverage (A/E) | E12: - | F12: =(AVERAGE('BS Intergrated'!E42:F42)/AVERAGE('BS Intergrated'!E72:F72)) -> 7.8594103 | G12: =(AVERAGE('BS Intergrated'!F42:G42)/AVERAGE('BS Intergrated'!F72:G72)) -> 10.002189 | H12: =(AVERAGE('BS Intergrated'!G42:H42)/AVERAGE('BS Intergrated'!G72:H72)) -> 7.5412583 | I12: =(AVERAGE('BS Intergrated'!H42:I42)/AVERAGE('BS Intergrated'!H72:I72)) -> 5.5222162 | J12: =(AVERAGE('BS Intergrated'!I42:J42)/AVERAGE('BS Intergrated'!I72:J72)) -> 4.7315928 | K12: =(AVERAGE('BS Intergrated'!J42:K42)/AVERAGE('BS Intergrated'!J72:K72)) -> 5.0520151 | L12: =(AVERAGE('BS Intergrated'!K42:L42)/AVERAGE('BS Intergrated'!K72:L72)) -> 5.823768 | M12: =(AVERAGE('BS Intergrated'!L42:M42)/AVERAGE('BS Intergrated'!L72:M72)) -> 5.8597645 | ... Q12: =(AVERAGE('BS Intergrated'!P42:Q42)/AVERAGE('BS Intergrated'!P72:Q72)) -> 2.9478971
D13: Return on Equity | E13: - | F13: ='IS Intergrated'!F41/(AVERAGE('BS Intergrated'!E72:F72)) -> -1.6003195 | G13: ='IS Intergrated'!G41/(AVERAGE('BS Intergrated'!F72:G72)) -> -1.9480014 | H13: ='IS Intergrated'!H41/(AVERAGE('BS Intergrated'!G72:H72)) -> -0.98307255 | I13: ='IS Intergrated'!I41/(AVERAGE('BS Intergrated'!H72:I72)) -> -0.3561637 | J13: ='IS Intergrated'!J41/(AVERAGE('BS Intergrated'!I72:J72)) -> -0.21583921 | K13: ='IS Intergrated'!K41/(AVERAGE('BS Intergrated'!J72:K72)) -> -0.044782017 | L13: ='IS Intergrated'!L41/(AVERAGE('BS Intergrated'!K72:L72)) -> 0.043453004 | M13: ='IS Intergrated'!M41/(AVERAGE('BS Intergrated'!L72:M72)) -> 0.15336443 | ... Q13: ='IS Intergrated'!Q41/(AVERAGE('BS Intergrated'!P72:Q72)) -> 0.41319322 | U13: Weight (%) | V13: Value
D14: Rule of 40 | E14: - | F14: =('DCF FINAL'!E11/'DCF FINAL'!D11-1)+('CF Intergrated'!F53/'DCF FINAL'!E11) -> 0.62375921 | G14: =('DCF FINAL'!F11/'DCF FINAL'!E11-1)+('CF Intergrated'!G53/'DCF FINAL'!F11) -> 0.57420577 | H14: =('DCF FINAL'!G11/'DCF FINAL'!F11-1)+('CF Intergrated'!H53/'DCF FINAL'!G11) -> 0.49937383 | I14: =('DCF FINAL'!H11/'DCF FINAL'!G11-1)+('CF Intergrated'!I53/'DCF FINAL'!H11) -> 0.55776451 | J14: =('DCF FINAL'!I11/'DCF FINAL'!H11-1)+('CF Intergrated'!J53/'DCF FINAL'!I11) -> 0.46797503 | K14: =('DCF FINAL'!J11/'DCF FINAL'!I11-1)+('CF Intergrated'!K53/'DCF FINAL'!J11) -> 0.46089756 | L14: =('DCF FINAL'!K11/'DCF FINAL'!J11-1)+('CF Intergrated'!L53/'DCF FINAL'!K11) -> 0.4551201 | M14: =('DCF FINAL'!L11/'DCF FINAL'!K11-1)+('CF Intergrated'!M53/'DCF FINAL'!L11) -> 0.52766202 | ... Q14: =('DCF FINAL'!P11/'DCF FINAL'!O11-1)+('CF Intergrated'!Q53/'DCF FINAL'!P11) -> 0.46512264 | T14: DCF Valuation | U14: 1 | V14: ='DCF FINAL'!J61 -> 107.76789
D15: Liquidity | T15: Comparables Valuation | U15: 0 | V15: =83.6 -> 83.6
D16: Current Ratio | E16: ='BS Intergrated'!E18/'BS Intergrated'!E54 -> 0.87577991 | F16: ='BS Intergrated'!F18/'BS Intergrated'!F54 -> 0.7045447 | G16: ='BS Intergrated'!G18/'BS Intergrated'!G54 -> 1.19146 | H16: ='BS Intergrated'!H18/'BS Intergrated'!H54 -> 1.3495648 | I16: ='BS Intergrated'!I18/'BS Intergrated'!I54 -> 1.1785883 | J16: ='BS Intergrated'!J18/'BS Intergrated'!J54 -> 1.2233278 | K16: ='BS Intergrated'!K18/'BS Intergrated'!K54 -> 0.78325942 | L16: ='BS Intergrated'!L18/'BS Intergrated'!L54 -> 0.72580308 | ... Q16: ='BS Intergrated'!Q18/'BS Intergrated'!Q54 -> 0.74253799 | T16: Target Price | U16: - | V16: 108.26452
D17: Quick Ratio | E17: =('BS Intergrated'!E11+'BS Intergrated'!E12+'BS Intergrated'!E13)/'BS Intergrated'!E54 -> 0.75131701 | F17: =('BS Intergrated'!F11+'BS Intergrated'!F12+'BS Intergrated'!F13)/'BS Intergrated'!F54 -> 0.60852567 | G17: =('BS Intergrated'!G11+'BS Intergrated'!G12+'BS Intergrated'!G13)/'BS Intergrated'!G54 -> 1.1082961 | H17: =('BS Intergrated'!H11+'BS Intergrated'!H12+'BS Intergrated'!H13)/'BS Intergrated'!H54 -> 1.277491 | I17: =('BS Intergrated'!I11+'BS Intergrated'!I12+'BS Intergrated'!I13)/'BS Intergrated'!I54 -> 1.1367083 | J17: =('BS Intergrated'!J11+'BS Intergrated'!J12+'BS Intergrated'!J13)/'BS Intergrated'!J54 -> 1.168062 | K17: =('BS Intergrated'!K11+'BS Intergrated'!K12+'BS Intergrated'!K13)/'BS Intergrated'!K54 -> 0.70270707 | L17: =('BS Intergrated'!L11+'BS Intergrated'!L12+'BS Intergrated'!L13)/'BS Intergrated'!L54 -> 0.63779783 | ... Q17: =('BS Intergrated'!Q11+'BS Intergrated'!Q12+'BS Intergrated'!Q13)/'BS Intergrated'!Q54 -> 0.6684718 | T17: Implied Downside | U17: - | V17: -0.36850966
D18: Debt Ratio
D19: Interest Coverage Ratio | E19: =-('IS Intergrated'!E29/'IS Intergrated'!E34) -> 0.28393469 | F19: =-('IS Intergrated'!F29/'IS Intergrated'!F34) -> 0.82822521 | G19: =-('IS Intergrated'!G29/'IS Intergrated'!G34) -> -4.1224055 | H19: =-('IS Intergrated'!H29/'IS Intergrated'!H34) -> -11.451289 | I19: =-('IS Intergrated'!I29/'IS Intergrated'!I34) -> -3.4356604 | J19: =-('IS Intergrated'!J29/'IS Intergrated'!J34) -> -4.2681506 | K19: =-('IS Intergrated'!K29/'IS Intergrated'!K34) -> 0.20936299 | L19: =-('IS Intergrated'!L29/'IS Intergrated'!L34) -> 0.91585891 | ... Q19: =-('IS Intergrated'!Q29/'IS Intergrated'!Q34) -> 46.112245
D20: Debt/EBITDA | E20: =('BS Intergrated'!E59+'BS Intergrated'!E48)/'IS Intergrated'!E55 -> 2.5125472 | F20: =('BS Intergrated'!F59+'BS Intergrated'!F48)/'IS Intergrated'!F55 -> 1.3936865 | G20: =('BS Intergrated'!G59+'BS Intergrated'!G48)/'IS Intergrated'!G55 -> -5.8860559 | H20: =('BS Intergrated'!H59+'BS Intergrated'!H48)/'IS Intergrated'!H55 -> -0.81243894 | I20: =('BS Intergrated'!I59+'BS Intergrated'!I48)/'IS Intergrated'!I55 -> -5.594147 | J20: =('BS Intergrated'!J59+'BS Intergrated'!J48)/'IS Intergrated'!J55 -> -3.9006273 | K20: =('BS Intergrated'!K59+'BS Intergrated'!K48)/'IS Intergrated'!K55 -> 1.2901412 | L20: =('BS Intergrated'!L59+'BS Intergrated'!L48)/'IS Intergrated'!L55 -> 1.0314195 | ... Q20: =('BS Intergrated'!Q59+'BS Intergrated'!Q48)/'IS Intergrated'!Q55 -> 0.075349689
T26: 1-Month VWAP | U26: ='VWAP LIVE'!I7 -> 0
T27: Market Cap | U27: $48.833B
T28: Shares Outstanding | U28: 260.16M
T29: 52-Week High | U29: 198.6
T30: 52-Week Low | U30: 56.01

Sheet Altman's Z-Score
A1: Altman's Z-Score
C4: Parameters - Actuals | F4: Calculations
C5: Income statement | H5: Variable | I5: Factor
C6: Net sales | D6: ='DCF FINAL'!J11 -> 6572.308 | F6: Working Cap / Total Assets | H6: =(D10-D12)/D11 -> -0.12681336 | I6: 1.2
C7: Operating income | D7: ='DCF FINAL'!J19 -> 10.353 | F7: Retained Earnings / Total Assets | H7: =D14/D11 -> -1.0003029 | I7: 1.4
F8: EBIT / Total Assets | H8: =D7/D11 -> 0.0016962318 | I8: 3.3
C9: Balance sheet | F9: Net Sales / Total Assets | H9: =D6/D11 -> 1.0768046 | I9: 1
C10: Current assets | D10: ='BS Intergrated'!K18 -> 2797.122 | F10: Market value of equity/Total liabilities | H10: =D16/D13 -> 9.1851964 | I10: 0.6
C11: Total assets | D11: ='BS Intergrated'!K42 -> 6103.529
C12: Current liabilities | D12: ='BS Intergrated'!K54 -> 3571.131 | F12: Z Score | G12: =SUMPRODUCT(H6:H10,I6:I10) -> 5.0409199
C13: Total liabilities | D13: ='BS Intergrated'!K65 -> 5045.09
C14: Retained earnings | D14: ='BS Intergrated'!K70 -> -6105.378
F15: Key
C16: Market value of equity | D16: ='Comp. Multi & Imp. Val'!W9 -> 46340.143 | F16: Z < 1.81 | G16: Bad
C17: Book value of equity | D17: =D11-D13 -> 1058.439 | F17: 1.81 < Z < 2.99 | G17: Moderate
F18: Z > 2.99 | G18: Excellent

Sheet Chaffe-Finnerty DLOM
A1: Chaffe & Finntery Discount for Lack of Marketability
A2: 409A Valuation(s)
A3: NASDAQ:TEAM
B6: TEAM RSU Vesting Schedule | F6: ICAEW Presentation | I6: Finnerty Paper | L6: Precendent(s) | M6: Stout | N6: Precedent 2
B7: 1 | C7: 0.25 | F7: Chaffe Model | I7: Finnerty Model
B8: 2 | C8: 0.25 | F8: Sigma Annualized | G8: =_xlfn.STDEV.S(C15:C540)*SQRT(52) -> 0.50953948 | I8: Sigma Annualized | J8: =_xlfn.STDEV.S(C15:C540)*SQRT(52) -> 0.50953948
B9: 3 | C9: 0.25 | F9: Vesting | G9: =SUMPRODUCT(B7:B10,C7:C10)/SUM(C7:C10) -> 2.5 | I9: q | J9: 0 | K9: No div
B10: 4 | C10: 0.25 | F10: rf | G10: ='DCS Detail'!D5 -> 0.04975 | I10: L (vesting) | J10: =SUMPRODUCT(B7:B10,C7:C10)/SUM(C7:C10) -> 2.5
F11: S | G11: ='VWAP LIVE'!I5 -> 178.1217 | I11: v | J11: =SQRT(J8^2+LN(2*(EXP(J8^2)-J8^2-1))-2*LN(EXP(J8^2)-1)) -> 0.28778985 | K11: Effective volatility, equation 6
F12: K | G12: =G11 -> 178.1217 | I12: p | J12: =_xlfn.NORM.S.DIST(J11/2,TRUE) - _xlfn.NORM.S.DIST(-J11/2,TRUE) -> 0.11441656 | K12: 1y marketability discount, equation 7
B13: Date | C13: TEAM Weekly Returns 10 yr (%) | F13: d1 | G13: =(LN(G11/G12)+(G10+G8^2/2)*G9)/(G8*SQRT(G9)) -> 0.55720427 | I13: Delta | J13: =-LN(1-J12) -> 0.12150859 | K13: Annualised decay rate, equation 8
B14: 42552 | F14: d2 | G14: =G13-(G8*SQRT(G9)) -> -0.24844839 | I14: Delta * | J14: =1-EXP(-J13*J10) -> 0.2619705 | K14: Multi-year discount, equation 9/10
B15: 42559 | C15: 0.053083528 | F15: P | G15: =G12*EXP(-G10*G9)*_xlfn.NORM.S.DIST(-G14,TRUE)-G11*_xlfn.NORM.S.DIST(-G13,TRUE) -> 42.653553 | I15: Adjustment (α) | J15: =1-J14 -> 0.7380295
B16: 42566 | C16: 0.015567087 | F16: Discount | G16: =G15/G11 -> 0.23946297
B17: 42573 | C17: 0.027737226 | F17: Adjustment (α) | G17: =1-G16 -> 0.76053703
B18: 42580 | C18: 0.064275568
B19: 42587 | C19: 0.0667334
B20: 42594 | C20: -0.061620269
B21: 42601 | C21: -0.019333333
B22: 42608 | C22: -0.016315432
B23: 42615 | C23: 0.04008293
B24: 42622 | C24: -0.020598007
B25: 42629 | C25: 0.017639077
B26: 42636 | C26: 0.025
B27: 42643 | C27: -0.025365854
B28: 42650 | C28: -0.05672339
B29: 42657 | C29: 0.0053059781
... B540: 46234 | C540: 0.16269567

Sheet VWAP LIVE
A1: Trailing Monthly VWAP
B2: #VALUE!
B5: Date | C5: High | D5: Low | E5: Close | F5: Volume | H5: 31-Day Trailing VWAP | I5: {=_xlfn.LET(_xlpm.d,_xlfn.ANCHORARRAY(B6),_xlpm.tp,(INDEX(_xlpm.d,,2)+INDEX(_xlpm.d,,3)+INDEX(_xlpm.d,,4))/3,_xlpm.v,INDEX(_xlpm.d,,5),IF(SUM(_xlpm.v)=0,NA(),SUMPRODUCT(_xlpm.tp,_xlpm.v)/SUM(_xlpm.v)))} -> 178.1217
B6: {=_xlfn.STOCKHISTORY($B$2,TODAY()-31,TODAY(),0,0,0,3,4,1,5)} -> 46251 | C6: 161.6 | D6: 156.5501 | E6: 158.34 | F6: 3048946
B7: 46252 | C7: 167.87 | D7: 158.58 | E7: 163 | F7: 4888443 | H7: 31-Day Trailing VWAP
B8: 46253 | C8: 176.15 | D8: 161.5 | E8: 174.23 | F8: 6066916
B9: 46254 | C9: 177.88 | D9: 171.22 | E9: 174.91 | F9: 5458362
B10: 46255 | C10: 176 | D10: 168.01 | E10: 171.81 | F10: 3275677
B11: 46258 | C11: 174.2341 | D11: 169.04 | E11: 171.33 | F11: 2584312
B12: 46259 | C12: 172.1 | D12: 165.1 | E12: 166.49 | F12: 2909953
B13: 46260 | C13: 170 | D13: 160.962 | E13: 168.47 | F13: 4127538
B14: 46261 | C14: 185.73 | D14: 168.73 | E14: 185.62 | F14: 6073950
B15: 46262 | C15: 194.96 | D15: 185 | E15: 190.415 | F15: 5224708
B16: 46265 | C16: 197.3 | D16: 187.67 | E16: 194.17 | F16: 5117290
B17: 46266 | C17: 193.645 | D17: 185.45 | E17: 187.03 | F17: 3891792
B18: 46267 | C18: 192.87 | D18: 184.73 | E18: 186.44 | F18: 3546782
B19: 46268 | C19: 198.5999 | D19: 190.61 | E19: 194.68 | F19: 3359288
B20: 46269 | C20: 193.425 | D20: 186.54 | E20: 189.58 | F20: 2473769

Sheet Charts
Z1: Increases YoY
J2: '20A | K2: '21A | L2: '22A | M2: '23A | N2: '24A | O2: '25A | P2: '26A | Q2: '27E | R2: '28E | S2: '29E | T2: '30E | U2: '31E | V2: '32E | AA2: '20A | AB2: '21A | AC2: '22A | AD2: '23A | AE2: '24A | AF2: '25A | AG2: '26A
C3: Figure XX: Goodwill by Fiscal Year (US$m) - Investment Summary | J3: ='IS Intergrated'!E25/'IS Intergrated'!E$10 -> 0.47280434 | K3: ='IS Intergrated'!F25/'IS Intergrated'!F$10 -> 0.46111304 | L3: ='IS Intergrated'!G25/'IS Intergrated'!G$10 -> 0.49861821 | M3: ='IS Intergrated'!H25/'IS Intergrated'!H$10 -> 0.52901492 | N3: ='IS Intergrated'!I25/'IS Intergrated'!I$10 -> 0.50110345 | O3: ='IS Intergrated'!J25/'IS Intergrated'!J$10 -> 0.5118229 | P3: ='IS Intergrated'!K25/'IS Intergrated'!K$10 -> 0.49742906 | Q3: ='IS Intergrated'!L25/'IS Intergrated'!L$10 -> 0.46260265 | ... V3: ='IS Intergrated'!Q25/'IS Intergrated'!Q$10 -> 0.33760265 | AA3: 25.4 | AB3: =31.3+AA3 -> 56.7 | AC3: =35+AB3 -> 91.7 | AD3: =56.1+AC3 -> 147.8 | AE3: =101.9+AD3 -> 249.7 | AF3: =32.5+AE3 -> 282.2 | AG3: =87+AF3 -> 369.2
A4: '20A | B4: 645.14 | C4: =B4/608.907-1 -> 0.059504982 | J4: ='IS Intergrated'!E26/'IS Intergrated'!E$10 -> 0.1856573 | K4: ='IS Intergrated'!F26/'IS Intergrated'!F$10 -> 0.17849949 | L4: ='IS Intergrated'!G26/'IS Intergrated'!G$10 -> 0.20253832 | M4: ='IS Intergrated'!H26/'IS Intergrated'!H$10 -> 0.21780421 | N4: ='IS Intergrated'!I26/'IS Intergrated'!I$10 -> 0.20132529 | O4: ='IS Intergrated'!J26/'IS Intergrated'!J$10 -> 0.21753957 | P4: ='IS Intergrated'!K26/'IS Intergrated'!K$10 -> 0.23449571 | Q4: ='IS Intergrated'!L26/'IS Intergrated'!L$10 -> 0.23449571 | ... V4: ='IS Intergrated'!Q26/'IS Intergrated'!Q$10 -> 0.22449571 | AB4: =(AB3-AA3)/AA3 -> 1.2322835 | AC4: =(AC3-AB3)/AB3 -> 0.61728395 | AD4: =(AD3-AC3)/AC3 -> 0.61177754 | AE4: =(AE3-AD3)/AD3 -> 0.6894452 | AF4: =(AF3-AE3)/AE3 -> 0.13015619 | AG4: =(AG3-AF3)/AF3 -> 0.30829199
A5: '21A | B5: 725.758 | C5: =B5/B4-1 -> 0.12496202 | J5: ='IS Intergrated'!E27/'IS Intergrated'!E$10 -> 0.16628267 | K5: ='IS Intergrated'!F27/'IS Intergrated'!F$10 -> 0.15089616 | L5: ='IS Intergrated'!G27/'IS Intergrated'!G$10 -> 0.17067183 | M5: ='IS Intergrated'!H27/'IS Intergrated'!H$10 -> 0.17154811 | N5: ='IS Intergrated'!I27/'IS Intergrated'!I$10 -> 0.14008548 | O5: ='IS Intergrated'!J27/'IS Intergrated'!J$10 -> 0.12405758 | P5: ='IS Intergrated'!K27/'IS Intergrated'!K$10 -> 0.11482846 | Q5: ='IS Intergrated'!L27/'IS Intergrated'!L$10 -> 0.11944302 | ... V5: ='IS Intergrated'!Q27/'IS Intergrated'!Q$10 -> 0.09444302
A6: '22A | B6: 732.666 | C6: =B6/B5-1 -> 0.0095183243 | AA6: Figure XX: Inference Costs by Fiscal Year (US$m)
A7: '23A | B7: 727.221 | C7: =B7/B6-1 -> -0.0074317629 | J7: Figure XX: R&D, M&S, G&A Margins by Fiscal Year (%) - Investment Summary
A8: '24A | B8: 1288.756 | C8: =B8/B7-1 -> 0.77216555
A9: '25A | B9: 1304.445 | C9: =B9/B8-1 -> 0.012173755
A10: '26A | B10: 2302.739 | C10: =B10/B9-1 -> 0.76530172
B16: =B10/B9 -> 1.7653017
B17: =B16-1 -> 0.76530172
D22: '20A | E22: '21A | F22: '22A | G22: '23A | H22: '24A | I22: '25A | J22: '26A | K22: '27E | L22: '28E | M22: '29E | N22: '30E | O22: '31E | P22: '32E | S22: '20A | T22: '21A | U22: '22A | V22: '23A | W22: '24A | X22: '25A | Y22: '26A | Z22: '27E | AA22: '28E | AB22: '29E | AC22: '30E | AD22: '31E | AE22: '32E
A23: Cloud | D23: 872.72904 | E23: 1129.5234 | F23: 1515.424 | G23: 2085.5 | H23: 2698.9 | I23: 3447.4 | J23: 4410.627 | K23: 5909.4218 | L23: 7634.3851 | M23: 9463.205 | N23: 12137.566 | O23: 13715.449 | P23: 15086.994 | S23: ='IS Intergrated'!E22/1000 -> 1.345366 | T23: ='IS Intergrated'!F22/1000 -> 1.753111 | U23: ='IS Intergrated'!G22/1000 -> 2.337175 | V23: ='IS Intergrated'!H22/1000 -> 2.900882 | W23: ='IS Intergrated'!I22/1000 -> 3.555108 | X23: ='IS Intergrated'!J22/1000 -> 4.320453 | Y23: ='IS Intergrated'!K22/1000 -> 5.575476 | Z23: ='IS Intergrated'!L22/1000 -> 6.2067684 | ... AE23: ='IS Intergrated'!Q22/1000 -> 13.11227
A24: Data Center | D24: 322.68636 | E24: 417.63455 | F24: 560.319 | G24: 819.251 | H24: 1208.498 | I24: 1467.167 | J24: 1830.941 | K24: 1208.4211 | L24: 1012.6568 | M24: 919.49242 | N24: 0 | O24: - | P24: - | S24: ='IS Intergrated'!E22/'IS Intergrated'!E10 -> 0.83347076 | T24: ='IS Intergrated'!F22/'IS Intergrated'!F10 -> 0.8391576 | U24: ='IS Intergrated'!G22/'IS Intergrated'!G10 -> 0.83384709 | V24: ='IS Intergrated'!H22/'IS Intergrated'!H10 -> 0.82069921 | W24: ='IS Intergrated'!I22/'IS Intergrated'!I10 -> 0.81565309 | X24: ='IS Intergrated'!J22/'IS Intergrated'!J10 -> 0.82841825 | Y24: ='IS Intergrated'!K22/'IS Intergrated'!K10 -> 0.84832847 | Z24: ='IS Intergrated'!L22/'IS Intergrated'!L10 -> 0.82313997 | ... AE24: ='IS Intergrated'!Q22/'IS Intergrated'!Q10 -> 0.81159955
A25: Server | D25: 302.36236 | E25: 391.33035 | F25: 525.028 | G25: 400.517 | H25: 177.645 | I25: - | J25: - | K25: - | L25: - | M25: - | N25: - | O25: - | P25: - | AJ25: Atlassian Corp | AK25: ServiceNow | AL25: HubSpot | AM25: GitLab | AN25: Monday.com | AO25: Freshworks | AP25: Asana
A26: Marketplace & Other | D26: 116.39524 | E26: 150.64372 | F26: 202.111 | G26: 229.379 | H26: 273.56 | I26: 300.737 | J26: 330.74 | K26: 373.7362 | L26: 416.71586 | M26: 460.47103 | N26: 501.91342 | O26: 539.55693 | P26: 571.93034 | S26: Figure XX: Gross Profit & Gross Margin - Investment Summary | AJ26: 22.642684 | AK26: 19.318169 | AL26: 8.4230762 | AM26: 49.291457 | AN26: 9.7332465 | AO26: 11.143876 | AP26: 15.902268
AJ27: =AVERAGE($AJ$26:$AQ$26) -> 19.49354 | AK27: =AVERAGE($AJ$26:$AQ$26) -> 19.49354 | AL27: =AVERAGE($AJ$26:$AQ$26) -> 19.49354 | AM27: =AVERAGE($AJ$26:$AQ$26) -> 19.49354 | AN27: =AVERAGE($AJ$26:$AQ$26) -> 19.49354 | AO27: =AVERAGE($AJ$26:$AQ$26) -> 19.49354 | AP27: =AVERAGE($AJ$26:$AQ$26) -> 19.49354
A28: Figure XX: Revenue Stream Build-Up - Business Model
L48: '20A | M48: '21A | N48: '22A | O48: '23A | P48: '24A | Q48: '25A | R48: '26A | S48: '27E | T48: '28E | U48: '29E | V48: '30E | W48: '31E | X48: '32E
L49: =-'CF Intergrated'!E31 -> 53.972 | M49: =-'CF Intergrated'!F31 -> 91.769 | N49: =-'CF Intergrated'!G31 -> 19.411 | O49: =-'CF Intergrated'!H31 -> 5.775 | P49: =-'CF Intergrated'!I31 -> 847.767 | Q49: =-'CF Intergrated'!J31 -> 14.245 | R49: =-'CF Intergrated'!K31 -> 1228.875 | S49: =-'CF Intergrated'!L31 -> 489.80612 | ... X49: =-'CF Intergrated'!Q31 -> 1857.2704
S50: ='IS Intergrated'!L15 -> 48.776925 | T50: ='IS Intergrated'!M15 -> 68.218476 | U50: ='IS Intergrated'!N15 -> 95.38845 | V50: ='IS Intergrated'!O15 -> 132.53476 | W50: ='IS Intergrated'!P15 -> 181.44584 | X50: ='IS Intergrated'!Q15 -> 242.55276
A51: '17A | B51: 20
A52: '18A | B52: 27
A53: '19A | B53: 58 | L53: Figure XX: Forecasted Acquisitions (US$m)
A54: '20A | B54: 50
A55: '21A | B55: 56 | AJ55: '20A | AK55: '21A | AL55: '22A | AM55: '23A | AN55: '24A | AO55: '25A | AP55: '26A | AQ55: '27E | AR55: '28E | AS55: '29E | AT55: '30E | AU55: '31E | AV55: '32E
A56: '22A | B56: 50 | AJ56: 183.628 | AK56: 253.859 | AL56: 410.354 | AM56: 581.285 | AN56: 724.757 | AO56: 816.113 | AP56: 856.162 | AQ56: 1194.4376 | AR56: 1484.2493 | AS56: 1830.6058 | AT56: 2198.118 | AU56: 2551.7025 | AV56: 2882.8691
A57: '23A | B57: 55 | AJ57: 0.1137598 | AK57: 0.1215141 | AL57: 0.14640431 | AM57: 0.16445348 | AN57: 0.16628195 | AO57: 0.15648426 | AP57: 0.13026809 | AQ57: 0.158406 | AR57: 0.163406 | AS57: 0.168406 | AT57: 0.173406 | AU57: 0.178406 | AV57: 0.183406
A58: '24A | B58: 78
A59: '25A | B59: 88
A60: '26A | B60: 89
A82: https://www.mckinsey.com/capabilities/quantumblack/our-insights/the-state-of-ai#/
Y86: z
X88: Teamwork Graph Reliance | Y88: Switching Cost | Z88: size
W89: Software Collection | X89: 8.9 | Y89: 8.8 | Z89: 28
W90: Service Collection | X90: 6.9 | Y90: 7.4 | Z90: 20
W91: Strategy Collection | X91: 8.3 | Y91: 6.1 | Z91: 6
W92: Teamwork Collection | X92: 5.1 | Y92: 5.3 | Z92: 40
W93: Product Collection | X93: 3.2 | Y93: 3 | Z93: 5

Sheet WACC
A1: WACC Calculations
A2: NASDAQ: TEAM
A6: WACC Summary
B7: CAPM | H7: =H32 -> 0.10959412
B8: French-Fama 3 Factor | H8: =H55 -> 0.098174268
B9: French-Fama 5 Factor | H9: =H78 -> -0.014503252
A12: WACC Calculation - Fama-French 1 Model
B14: Capital Structure
B15: Total Debt | H15: ='BS Intergrated'!I58+'BS Intergrated'!I59+'BS Intergrated'!I51 -> 1249.338
B16: Total Equity | H16: ='Comp. Multi & Imp. Val'!$C$15*'Comp. Multi & Imp. Val'!$W$13 -> 46340.143
B18: %Debt | H18: =H15/(H15+H16) -> 0.026252398
B19: %Equity | H19: =H16/(H15+H16) -> 0.9737476
B20: Total% | H20: =SUM(H18:H19) -> 1
B22: Cost of Debt (%YTM Issued Debt) | H22: =('DCS Detail'!$M$43+'DCS Detail'!$M$44)/2 -> 0.0549
B23: Tax Rate | H23: ='DCS Detail'!$D$57 -> 0.24
B24: After-Tax Cost of Debt | H24: =H22*(1-H23) -> 0.041724
B26: Cost of Equity
B27: Risk Free Rate | H27: ='DCS Detail'!D5 -> 0.04975
B28: Equity Risk Premium | H28: ='DCS Detail'!$D$6 -> 0.0446
B29: Beta Calculation | H29: ='Beta Regression'!$B$10 -> 1.3828231
B30: Cost of Equity | H30: =H27+H29*(H28) -> 0.11142391
B32: WACC | H32: =SUMPRODUCT(H18:H19,_xlfn.VSTACK(H24,H30)) -> 0.10959412
A35: WACC Calculation - Fama-French 3 Model | J35: Figure XX: 3-Factor Fama-French CoE
J36: Risk-Free Rate | K36: ='DCS Detail'!D5 -> 0.04975
B37: Capital Structure | J37: Mkt-RF (β) | K37: 1.2081001
B38: Total Debt | H38: ='BS Intergrated'!I58+'BS Intergrated'!I59+'BS Intergrated'!I51 -> 1249.338 | J38: SMB (β) | K38: 0.73658678
B39: Total Equity | H39: ='Comp. Multi & Imp. Val'!$C$15*'Comp. Multi & Imp. Val'!$W$13 -> 46340.143 | J39: HML (β) | K39: -0.3544557
J40: Market Risk Premium | K40: 0.0446
B41: %Debt | H41: =H38/(H38+H39) -> 0.026252398 | J41: SMB Premium | K41: 0.013976
B42: %Equity | H42: =H39/(H38+H39) -> 0.9737476 | J42: HML Premium | K42: 0.040145
B43: Total% | H43: =SUM(H41:H42) -> 1 | J43: Cost of Equity | K43: =K36+K37*K40+K38*K41+K39*K42 -> 0.099696177
J44: Source: CapitalIQ, Damodaran 2026, MURG
B45: Cost of Debt | H45: =('DCS Detail'!$M$43+'DCS Detail'!$M$44)/2 -> 0.0549
B46: Tax Rate | H46: ='DCS Detail'!$D$57 -> 0.24 | J46: Figure XX: After-Tax Cost of Debt
B47: After-Tax Cost of Debt | H47: =H45*(1-H46) -> 0.041724 | J47: Cost of Debt | K47: =H45 -> 0.0549
J48: Tax Rate | K48: =H46 -> 0.24
B49: Cost of Equity | J49: AT Cost of Debt | K49: =K47*(1-K48) -> 0.041724
B50: Risk Free Rate | H50: ='DCS Detail'!D5 -> 0.04975 | J50: Source: CapitalIQ, Damodaran 2026, MURG
B51: Equity Risk Premium | H51: ='DCS Detail'!$D$6 -> 0.0446
B52: Beta Calculation | H52: ='WACC FF Data'!B19 -> 1.2081001 | J52: Figure XX: WACC
B53: Cost of Equity | H53: ='WACC FF Data'!B7 -> 0.099696177 | J53: Weight of Debt | K53: =H41 -> 0.026252398
J54: Weight of Equity | K54: =H42 -> 0.9737476
B55: WACC | H55: =SUMPRODUCT(H41:H42,_xlfn.VSTACK(H47,H53)) -> 0.098174268 | J55: AT Cost of Debt | K55: =K49 -> 0.041724
J56: Cost of Equity | K56: =K43 -> 0.099696177
J57: WACC | K57: =K53*K55+K54*K56 -> 0.098174268
A58: WACC Calculation - Fama-French 5 Model | J58: Source: CapitalIQ, Damodaran 2026, MURG
B60: Capital Structure
B61: Total Debt | H61: ='BS Intergrated'!I58+'BS Intergrated'!I59+'BS Intergrated'!I51 -> 1249.338
B62: Total Equity | H62: ='Comp. Multi & Imp. Val'!$C$15*'Comp. Multi & Imp. Val'!$W$13 -> 46340.143
B64: %Debt | H64: =H61/(H61+H62) -> 0.026252398
B65: %Equity | H65: =H62/(H61+H62) -> 0.9737476
B66: Total% | H66: =SUM(H64:H65) -> 1
B68: Cost of Debt | H68: =('DCS Detail'!$M$43+'DCS Detail'!$M$44)/2 -> 0.0549
B69: Tax Rate | H69: ='DCS Detail'!$D$57 -> 0.24
B70: After-Tax Cost of Debt | H70: =H68*(1-H69) -> 0.041724
B72: Cost of Equity
B73: Risk Free Rate | H73: ='DCS Detail'!D5 -> 0.04975
B74: Equity Risk Premium | H74: ='DCS Detail'!$D$6 -> 0.0446
B75: Beta Calculation | H75: ='WACC FF Data'!B189 -> 0.85013041
B76: Cost of Equity | H76: ='WACC FF Data'!B209 -> -0.016019148
B78: WACC | H78: =SUMPRODUCT(H64:H65,_xlfn.VSTACK(H70,H76)) -> -0.014503252

Sheet WACC FF Data
A1: Atlassian (TEAM) — Cost of Equity: CAPM vs. Fama-French Models
A2: Full regression outputs, premiums, and headline comparison
A4: Headline Comparison
A5: Model | B5: Cost of Equity | C5: R² | D5: vs. CAPM (bps) | E5: Reliability
A6: CAPM (S&P 500 Beta) | B6: =WACC!H30 -> 0.11142391 | C6: ='Beta Regression'!B13 -> 0.13581336 | D6: 0 | E6: Reliable
A7: Fama-French 3-Factor | B7: =B33 -> 0.099696177 | C7: =B27 -> 0.17491658 | D7: =(B7-B6)*10000 -> -117.27734 | E7: Reliable
A8: Fama-French 5-Factor | B8: =B209 -> -0.016019148 | C8: =B201 -> 0.3246688 | D8: =(B8-B6)*10000 -> -1274.4306 | E8: Unreliable
A11: CAPM Inputs
A12: Risk-Free Rate (Rf) | B12: ='DCS Detail'!D5 -> 0.04975
A13: Market Risk Premium (MRP) | B13: 0.0446
A14: Beta (own regression vs. S&P 500) | B14: 1.3828
A15: Cost of Equity (CAPM) | B15: =B12+B14*B13 -> 0.11142288
A17: Fama-French 3-Factor — Live Regression (LINEST)
A18: Intercept (alpha) | B18: =INDEX(LINEST(D36:D184,E36:G184,TRUE,TRUE),1,4) -> -0.0036377356
A19: Mkt-RF (coefficient) | B19: =INDEX(LINEST(D36:D184,E36:G184,TRUE,TRUE),1,3) -> 1.2081001
A20: SMB (coefficient) | B20: =INDEX(LINEST(D36:D184,E36:G184,TRUE,TRUE),1,2) -> 0.73658678
A21: HML (coefficient) | B21: =INDEX(LINEST(D36:D184,E36:G184,TRUE,TRUE),1,1) -> -0.3544557
A22: Std Error (Intercept) | B22: =INDEX(LINEST(D36:D184,E36:G184,TRUE,TRUE),2,4) -> 0.0058379356
A23: Std Error (Mkt-RF) | B23: =INDEX(LINEST(D36:D184,E36:G184,TRUE,TRUE),2,3) -> 0.30012176
A24: Std Error (SMB) | B24: =INDEX(LINEST(D36:D184,E36:G184,TRUE,TRUE),2,2) -> 0.41701968
A25: Std Error (HML) | B25: =INDEX(LINEST(D36:D184,E36:G184,TRUE,TRUE),2,1) -> 0.36817547
A26: French-Fama 3-Factor Standard Deviation | B26: =2.1436% -> 0.021436 | C26: =B26*WACC!H42 -> 0.020873254
A27: R-Squared | B27: =INDEX(LINEST(D36:D184,E36:G184,TRUE,TRUE),3,1) -> 0.17491658
A29: Fama-French 3-Factor — Premiums & Cost of Equity
A30: Market Risk Premium (MRP) | B30: =B13 -> 0.0446 | C30: Same as CAPM
A31: SMB Premium (Annualised) | B31: 0.013976 | C31: Mean of three factor SMB * 52 (full history range is from 1926 to 2026)
A32: HML Premium (Annualised) | B32: 0.040145 | C32: Mean of three factor HML * 52 (full history range is from 1926 to 2026)
A33: Cost of Equity | B33: =B12+B19*B30+B20*B31+B21*B32 -> 0.099696177
A35: Date | B35: TEAM Return | C35: RF | D35: TEAM Excess Return | E35: Mkt-RF | F35: SMB | G35: HML
A36: 45135 | B36: -0.0012039904 | C36: 0.0011 | D36: -0.0023039904 | E36: 0.0097 | F36: -0.0003 | G36: 0.0095
A37: 45142 | B37: 0.14138109 | C37: 0.0011 | D37: 0.14028109 | E37: -0.0226 | F37: 0.0077 | G37: 0.0153
A38: 45149 | B38: -0.0059344196 | C38: 0.0011 | D38: -0.0070344196 | E38: -0.006 | F38: -0.0134 | G38: 0.0043
A39: 45156 | B39: -0.057472427 | C39: 0.0011 | D39: -0.058572427 | E39: -0.023 | F39: -0.0074 | G39: -0.0164
A40: 45163 | B40: 0.02533548 | C40: 0.0011 | D40: 0.02423548 | E40: 0.0059 | F40: -0.0081 | G40: -0.017
A41: 45170 | B41: 0.070306774 | C41: 0.0011 | D41: 0.069206774 | E41: 0.0273 | F41: 0.0071 | G41: 0.0063
A42: 45177 | B42: 0.010516019 | C42: 0.0011 | D42: 0.0094160186 | E42: -0.0155 | F42: -0.0255 | G42: -0.006
A43: 45184 | B43: -0.017279768 | C43: 0.0011 | D43: -0.018379768 | E43: -0.0029 | F43: -0.0092 | G43: 0.0137
A44: 45191 | B44: -0.03728513 | C44: 0.0011 | D44: -0.03838513 | E44: -0.0316 | F44: -0.0082 | G44: -0.0003
A45: 45198 | B45: 0.030952625 | C45: 0.0011 | D45: 0.029852625 | E45: -0.0058 | F45: 0.0112 | G45: 0.0026
A46: 45205 | B46: -0.011413826 | C46: 0.0012 | D46: -0.012613826 | E46: 0.0018 | F46: -0.0152 | G46: -0.0201
A47: 45212 | B47: -0.054716129 | C47: 0.0012 | D47: -0.055916129 | E47: 0.0011 | F47: -0.0273 | G47: 0.0138
... A184: 46171 | B184: 0.25977523 | C184: 0.0008 | D184: 0.25897523 | E184: 0.0152 | F184: 0.0053 | G184: -0.0095
A187: Fama-French 5-Factor Live Regression (LINEST)
A188: Intercept (alpha) | B188: =INDEX(LINEST(D212:D360,E212:I360,TRUE,TRUE),1,6) -> -0.0087970286
A189: Mkt-RF (coefficient) | B189: =INDEX(LINEST(D212:D360,E212:I360,TRUE,TRUE),1,5) -> 0.85013041
A190: SMB (coefficient) | B190: =INDEX(LINEST(D212:D360,E212:I360,TRUE,TRUE),1,4) -> -0.12841844
A191: HML (coefficient) | B191: =INDEX(LINEST(D212:D360,E212:I360,TRUE,TRUE),1,3) -> 0.42811867
A192: RMW (coefficient) | B192: =INDEX(LINEST(D212:D360,E212:I360,TRUE,TRUE),1,2) -> -2.6659629 | C192: =B192*B207 -> -0.080509413
A193: CMA (coefficient) | B193: =INDEX(LINEST(D212:D360,E212:I360,TRUE,TRUE),1,1) -> -1.2588684 | C193: =B193*B208 -> -0.037118992
A194: Std Error (Intercept) | B194: =INDEX(LINEST(D212:D360,E212:I360,TRUE,TRUE),2,6) -> 0.0054165785 | C194: =C192+C193 -> -0.11762841
A195: Std Error (Mkt-RF) | B195: =INDEX(LINEST(D212:D360,E212:I360,TRUE,TRUE),2,5) -> 0.28563238
A196: Std Error (SMB) | B196: =INDEX(LINEST(D212:D360,E212:I360,TRUE,TRUE),2,4) -> 0.43739257
A197: Std Error (HML) | B197: =INDEX(LINEST(D212:D360,E212:I360,TRUE,TRUE),2,3) -> 0.4218998
A198: Std Error (RMW) | B198: =INDEX(LINEST(D212:D360,E212:I360,TRUE,TRUE),2,2) -> 0.51711156
A199: Std Error (CMA) | B199: =INDEX(LINEST(D212:D360,E212:I360,TRUE,TRUE),2,1) -> 0.56467017
A200: French-Fama 5-Factor Standard Deviation | B200: =2.7664% -> 0.027664
A201: R-Squared | B201: =INDEX(LINEST(D212:D360,E212:I360,TRUE,TRUE),3,1) -> 0.3246688
A203: Fama-French 5-Factor Premiums & Cost of Equity
A204: Market Risk Premium (MRP) | B204: =B13 -> 0.0446 | C204: Same as CAPM
A205: SMB Premium (Annualised) | B205: 0.015095 | C205: Mean of five factor SMB * 252, historical range of 1963 to 2026
A206: HML Premium (Annualised) | B206: 0.037097 | C206: Mean of five factor HML * 252, historical range of 1963 to 2026
A207: RMW Premium (annualised) | B207: 0.030199 | C207: Mean of five factor RMW * 252, historical range of 1963 to 2026
A208: CMA Premium (annualised) | B208: 0.029486 | C208: Mean of five factor CMA * 252, historical range of 1963 to 2026
A209: Cost of Equity | B209: =B12+B13*B189+B190*B205+B191*B206+B192*B207+B193*B208 -> -0.016019148
A211: Date | B211: TEAM Return | C211: RF | D211: TEAM Excess Return | E211: Mkt-RF | F211: SMB | G211: HML | H211: RMW | I211: CMA
A212: 45135 | B212: -0.0012039904 | C212: 0.0010004001 | D212: -0.0022043904 | E212: 0.0095464759 | F212: 0.0020184543 | G212: 0.0093224979 | H212: 0.0068305459 | I212: -0.0022365554
A213: 45142 | B213: 0.14138109 | C213: 0.0010004001 | D213: 0.14038069 | E213: -0.022380161 | F213: 0.0092922428 | G213: 0.016382304 | H213: 0.0004235508 | I213: -0.0053382316
A214: 45149 | B214: -0.0059344196 | C214: 0.0010004001 | D214: -0.0069348197 | E214: -0.0058545579 | F214: -0.01209958 | G214: 0.0047596635 | H214: 0.017377711 | I214: 0.0025959001
A215: 45156 | B215: -0.057472427 | C215: 0.0010004001 | D215: -0.058472827 | E215: -0.022985966 | F215: -0.011095475 | G215: -0.016658271 | H215: 0.012555768 | I215: -0.0050101388
A216: 45163 | B216: 0.02533548 | C216: 0.0010004001 | D216: 0.02433508 | E216: 0.0061123586 | F216: -0.013255642 | G216: -0.016962588 | H216: -0.0037284565 | I216: -0.01099132
A217: 45170 | B217: 0.070306774 | C217: 0.0010004001 | D217: 0.069306374 | E217: 0.027426132 | F217: 0.0074888483 | G217: 0.0062807548 | H217: -0.0016100487 | I217: -0.0085770677
A218: 45177 | B218: 0.010516019 | C218: 0.00080024003 | D218: 0.0097157786 | E218: -0.015231508 | F218: -0.02737971 | G218: -0.0063275826 | H218: -0.0064994552 | I218: -0.003605551
A219: 45184 | B219: -0.017279768 | C219: 0.0010004001 | D219: -0.018280168 | E219: -0.002942921 | F219: -0.0043562872 | G219: 0.014092448 | H219: 0.0046533623 | I219: 7.3895845e-05
A220: 45191 | B220: -0.03728513 | C220: 0.0010004001 | D220: -0.03828553 | E220: -0.031488314 | F220: -0.0074131884 | G220: -0.0004246495 | H220: 0.01548997 | I220: 0.0069054746
A221: 45198 | B221: 0.030952625 | C221: 0.0010004001 | D221: 0.029952224 | E221: -0.0057242973 | F221: 0.012539235 | G221: 0.0026802809 | H221: 0.0065876083 | I221: -0.0095693096
A222: 45205 | B222: -0.011413826 | C222: 0.0010004001 | D222: -0.012414226 | E222: 0.001785251 | F222: -0.02226316 | G222: -0.020075347 | H222: 3.3777901e-05 | I222: -0.013443313
A223: 45212 | B223: -0.054716129 | C223: 0.0010004001 | D223: -0.055716529 | E223: 0.0011094598 | F223: -0.022977928 | G223: 0.014371422 | H223: 0.025183548 | I223: -0.0018229105
... A360: 46171 | B360: 0.25977523 | C360: 0.00080024003 | D360: 0.25897499 | E360: 0.015371746 | F360: 0.00010340007 | G360: -0.0093860466 | H360: -0.029621191 | I360: -0.0036036005

Sheet Beta Regression
A1: Beta Regression
A2: NASDAQ: TEAM
A5: Atlassian (TEAM) - Beta Regression vs. S&P500
A7: Weekly Returns, July 2023 - July 2026 (n=157 weeks)
A9: Regression Summary
A10: Beta (Slope) | B10: =SLOPE(F24:F179,E24:E179) -> 1.3828231
A11: Standard Error | B11: =INDEX(LINEST(F24:F179,E24:E179,TRUE(),TRUE()),2,1) -> 0.28108573
A12: Intercept | B12: =INTERCEPT(F24:F179,E24:E179) -> -0.0058823767
A13: R-Squared | B13: =RSQ(F24:F179,E24:E179) -> 0.13581336
A14: t-Statistic | B14: =B10/B11 -> 4.9195777
A15: Observations (n) | B15: =COUNT(F24:F179) -> 156
A16: Standard Deviation | B16: 0.011961
A18: Inputs used Elsewhere
A19: Risk-Free Rate | B19: ='DCS Detail'!D5 -> 0.04975
A20: Market-Risk Premium | B20: ='DCS Detail'!D6 -> 0.0446
A22: Date | B22: S&P 500 | C22: TEAM | E22: S&P 500 Return | F22: TEAM Return
A23: 45128 | B23: 4536.3385 | C23: 174.42
A24: 45135 | B24: 4582.2313 | C24: 174.21 | E24: 0.010116703 | F24: -0.0012039904
A25: 45142 | B25: 4478.0338 | C25: 198.84 | E25: -0.022739464 | F25: 0.14138109
A26: 45149 | B26: 4464.0546 | C26: 197.66 | E26: -0.0031217452 | F26: -0.0059344196
A27: 45156 | B27: 4369.7115 | C27: 186.3 | E27: -0.02113394 | F27: -0.057472427
A28: 45163 | B28: 4405.7057 | C28: 191.02 | E28: 0.0082372098 | F28: 0.02533548
A29: 45170 | B29: 4515.7674 | C29: 204.45 | E29: 0.02498162 | F29: 0.070306774
A30: 45177 | B30: 4457.4893 | C30: 206.6 | E30: -0.012905467 | F30: 0.010516019
A31: 45184 | B31: 4450.3163 | C31: 203.03 | E31: -0.0016092075 | F31: -0.017279768
A32: 45191 | B32: 4320.0571 | C32: 195.46 | E32: -0.02926964 | F32: -0.03728513
A33: 45198 | B33: 4288.0541 | C33: 201.51 | E33: -0.0074080048 | F33: 0.030952625
A34: 45205 | B34: 4308.5023 | C34: 199.21 | E34: 0.0047686284 | F34: -0.011413826
A35: 45212 | B35: 4327.783 | C35: 188.31 | E35: 0.0044750511 | F35: -0.054716129
... A179: 46220 | B179: 7457.6858 | C179: 93.29 | E179: -0.015538071 | F179: 0.049853702

Sheet IS Intergrated
A1: IS Intergrated
A2: NASDAQ: TEAM | L2: =L22/L10 -> 0.82313997 | M2: =M22/M10 -> 0.82048585 | N2: =N22/N10 -> 0.81738618 | O2: =O22/O10 -> 0.81377869 | P2: =P22/P10 -> 0.81480665 | Q2: =Q22/Q10 -> 0.81159955
E3: =E24/E10 -> 0.82474431 | F3: =F24/F10 -> 0.79050869 | G3: =G24/G10 -> 0.87182835 | H3: =H24/H10 -> 0.91836724 | I3: =I24/I10 -> 0.84251422 | J3: =J24/J10 -> 0.85342005 | K3: =K24/K10 -> 0.84675323 | L3: =L24/L10 -> 0.81654138 | ... Q3: =Q24/Q10 -> 0.65654138
E4: 0 | F4: 1 | G4: 2 | H4: 3 | I4: 4 | J4: 5 | K4: 6 | L4: 7 | M4: 8 | N4: 9 | O4: 10 | P4: 11 | Q4: 12
E5: 43983 | F5: 44377 | G5: =EDATE(F5,12) -> 44742 | H5: =EDATE(G5,12) -> 45107 | I5: =EDATE(H5,12) -> 45473 | J5: =EDATE(I5,12) -> 45838 | K5: 46174 | L5: =EDATE(K5,12) -> 46539 | M5: =EDATE(L5,12) -> 46905 | N5: =EDATE(M5,12) -> 47270 | O5: =EDATE(N5,12) -> 47635 | P5: =EDATE(O5,12) -> 48000 | Q5: =EDATE(P5,12) -> 48366
E6: Actuals | F6: Actuals | G6: Actuals | H6: Actuals | I6: Actuals | J6: Actuals | K6: Actuals | L6: Forecast | M6: Forecast | N6: Forecast | O6: Forecast | P6: Forecast | Q6: Forecast
K7: 0 | L7: 1 | M7: 2 | N7: 3 | O7: 4 | P7: 5 | Q7: 6
E9: 0.3339 | F9: =F10/E10-1 -> 0.29424293 | G9: =G10/F10-1 -> 0.34164907 | H9: =H10/G10-1 -> 0.26107592 | I9: =I10/H10-1 -> 0.23310843 | J9: =J10/I10-1 -> 0.19655403 | K9: =K10/J10-1 -> 0.26019653 | L9: =L10/K10-1 -> 0.14729193 | M9: =M10/L10-1 -> 0.21108027 | ... Q9: =Q10/P10-1 -> 0.10145761
B10: Sales | E10: 1614.173 | F10: 2089.132 | G10: =SUM(G11:G14) -> 2802.882 | H10: =SUM(H11:H14) -> 3534.647 | I10: =SUM(I11:I14) -> 4358.603 | J10: =SUM(J11:J14) -> 5215.304 | K10: =SUM(K11:K14) -> 6572.308 | L10: =SUM(L11:L15) -> 7540.3559 | M10: =SUM(M11:M15) -> 9131.9763 | N10: =SUM(N11:N15) -> 11015.519 | O10: =SUM(O11:O15) -> 12976.846 | P10: =SUM(P11:P15) -> 14667.912 | Q10: =SUM(Q11:Q15) -> 16156.084 | R10: =_xlfn.RRI(Q7,K10,Q10) -> 0.16172419
B11: Cloud | E11: =E10*(F11/F10) -> 872.72904 | F11: =F10*(G11/G10) -> 1129.5234 | G11: ='IS Historical'!G11 -> 1515.424 | H11: ='IS Historical'!H11 -> 2085.5 | I11: ='IS Historical'!I11 -> 2698.9 | J11: ='IS Historical'!J11 -> 3447.4 | K11: ='IS Historical'!K11 -> 4410.627 | L11: =K11*(1+'Revenue Assumptions'!F7)+'Revenue Assumptions'!Q8 -> 5909.4218 | M11: =L11*(1+'Revenue Assumptions'!G7)+'Revenue Assumptions'!R8 -> 7634.3851 | N11: =M11*(1+'Revenue Assumptions'!H7)+'Revenue Assumptions'!S8 -> 10459.659 | O11: =N11*(1+'Revenue Assumptions'!I7) -> 12342.398 | P11: =O11*(1+'Revenue Assumptions'!J7) -> 13946.91 | Q11: =P11*(1+'Revenue Assumptions'!K7) -> 15341.601
B12: Data Center | E12: =E10*($G$12/$G$10) -> 322.68636 | F12: =F10*($G$12/$G$10) -> 417.63455 | G12: ='IS Historical'!G12 -> 560.319 | H12: ='IS Historical'!H12 -> 819.251 | I12: ='IS Historical'!I12 -> 1208.498 | J12: ='IS Historical'!J12 -> 1467.167 | K12: ='IS Historical'!K12 -> 1830.941 | L12: =K12*(1+'Revenue Assumptions'!F16) -> 1208.4211 | M12: =L12*(1+'Revenue Assumptions'!G16) -> 1012.6568 | N12: =M12*(1+'Revenue Assumptions'!H16) -> 0 | O12: =N12*(1+'Revenue Assumptions'!I16) -> 0 | P12: - | Q12: -
B13: Server | E13: =E10*($G$13/$G$10) -> 302.36236 | F13: =F10*($G$13/$G$10) -> 391.33035 | G13: ='IS Historical'!G13 -> 525.028 | H13: ='IS Historical'!H13 -> 400.517 | I13: ='IS Historical'!I13 -> 177.645 | J13: ='IS Historical'!J13 -> - | K13: ='IS Historical'!K13 -> - | L13: - | M13: - | N13: - | O13: - | P13: - | Q13: -
B14: Marketplace & Other | E14: =E10*(G14/G10) -> 116.39524 | F14: =F10*(G14/G10) -> 150.64372 | G14: ='IS Historical'!G14 -> 202.111 | H14: ='IS Historical'!H14 -> 229.379 | I14: ='IS Historical'!I14 -> 273.56 | J14: ='IS Historical'!J14 -> 300.737 | K14: ='IS Historical'!K14 -> 330.74 | L14: =K14*(1+'Revenue Assumptions'!F25) -> 373.7362 | M14: =L14*(1+'Revenue Assumptions'!G25) -> 416.71586 | N14: =M14*(1+'Revenue Assumptions'!H25) -> 460.47103 | O14: =N14*(1+'Revenue Assumptions'!I25) -> 501.91342 | P14: =O14*(1+'Revenue Assumptions'!J25) -> 539.55693 | Q14: =P14*(1+'Revenue Assumptions'!K25) -> 571.93034 | R14: =_xlfn.RRI(Q7,K14,Q14) -> 0.09557657
B15: Acquistions | L15: =-'CF Intergrated'!K31/'Acquistion Multiples'!$C$6 -> 48.776925 | M15: =-'CF Intergrated'!L31/'Acquistion Multiples'!$C$6+L15 -> 68.218476 | N15: =-'CF Intergrated'!M31/'Acquistion Multiples'!$C$6+M15 -> 95.38845 | O15: =-'CF Intergrated'!N31/'Acquistion Multiples'!$C$6+N15 -> 132.53476 | P15: =-'CF Intergrated'!O31/'Acquistion Multiples'!$C$6+O15 -> 181.44584 | Q15: =-'CF Intergrated'!P31/'Acquistion Multiples'!$C$6+P15 -> 242.55276 | R15: =L15/L10 -> 0.0064687828 | S15: =M15/M10 -> 0.0074702861 | T15: =N15/N10 -> 0.0086594605 | U15: =O15/O10 -> 0.010213172 | V15: =P15/P10 -> 0.012370257 | W15: =Q15/Q10 -> 0.015013091
B17: Cost of Goods Sold (COGS) Excl. D&A | E17: ='IS Historical'!E16 -> 183.628 | F17: ='IS Historical'!F16 -> 253.859 | G17: ='IS Historical'!G16 -> 410.354 | H17: ='IS Historical'!H16 -> 581.285 | I17: ='IS Historical'!I16 -> 724.757 | J17: ='IS Historical'!J16 -> 816.113 | K17: ='IS Historical'!K16 -> 856.162 | L17: ='IS Assumption'!G10*'IS Intergrated'!L10 -> 1194.4376 | M17: ='IS Assumption'!H10*'IS Intergrated'!M10 -> 1492.2197 | N17: ='IS Assumption'!I10*'IS Intergrated'!N10 -> 1855.0795 | O17: ='IS Assumption'!J10*'IS Intergrated'!O10 -> 2250.263 | P17: ='IS Assumption'!K10*'IS Intergrated'!P10 -> 2616.8436 | Q17: ='IS Assumption'!L10*'IS Intergrated'!Q10 -> 2963.1227 | R17: COGS based upon historical %of revenue, with weighting towards recent trends
B18: D&A | E18: ='IS Historical'!E17 -> 85.179 | F18: ='IS Historical'!F17 -> 82.162 | G18: ='IS Historical'!G17 -> 55.353 | H18: ='IS Historical'!H17 -> 52.48 | I18: ='IS Historical'!I17 -> 78.738 | J18: ='IS Historical'!J17 -> 78.738 | K18: ='IS Historical'!K17 -> 140.67 | L18: =SUM(L19:L20) -> 139.14995 | M18: =SUM(M19:M20) -> 147.09922 | N18: =SUM(N19:N20) -> 156.50649 | O18: =SUM(O19:O20) -> 166.30225 | P18: =SUM(P19:P20) -> 99.556197 | Q18: =SUM(Q19:Q20) -> 80.690798
B19: Depreciation | E19: ='IS Historical'!E18 -> 42.644 | F19: ='IS Historical'!F18 -> 50.408 | G19: ='IS Historical'!G18 -> 22.955 | H19: ='IS Historical'!H18 -> 19.353 | I19: ='IS Historical'!I18 -> 28.99 | J19: ='IS Historical'!J18 -> 23.221 | K19: ='IS Historical'!K18 -> 39.18 | L19: ='IS Assumption'!F20*'BS Intergrated'!L21 -> 37.659952 | M19: ='IS Assumption'!G20*'BS Intergrated'!M21 -> 45.609225 | N19: ='IS Assumption'!H20*'BS Intergrated'!N21 -> 55.016489 | O19: ='IS Assumption'!I20*'BS Intergrated'!O21 -> 64.812246 | P19: ='IS Assumption'!J20*'BS Intergrated'!P21 -> 73.258197 | Q19: ='IS Assumption'!K20*'BS Intergrated'!Q21 -> 80.690798 | R19: Depr based upon historical %of revenue, with weighting towards recent trends
B20: Amortization | E20: ='IS Historical'!E19 -> 42.535 | F20: ='IS Historical'!F19 -> 31.754 | G20: ='IS Historical'!G19 -> 32.398 | H20: ='IS Historical'!H19 -> 33.127 | I20: ='IS Historical'!I19 -> 49.748 | J20: ='IS Historical'!J19 -> 55.517 | K20: ='IS Historical'!K19 -> 101.49 | L20: ='BS Intergrated'!K36-'BS Intergrated'!L36 -> 101.49 | M20: ='BS Intergrated'!L36-'BS Intergrated'!M36 -> 101.49 | N20: ='BS Intergrated'!M36-'BS Intergrated'!N36 -> 101.49 | O20: ='BS Intergrated'!N36-'BS Intergrated'!O36 -> 101.49 | P20: ='BS Intergrated'!O36-'BS Intergrated'!P36 -> 26.298 | Q20: ='BS Intergrated'!P36-'BS Intergrated'!Q36 -> 0 | R20: Acquired developed technology and customer relationships typically disclosed at 3-5 years, Atlassian 10-K FY25. Intangibles fully amortise by 2030
B22: Gross Income | E22: =E10-SUM(E17:E18) -> 1345.366 | F22: =F10-SUM(F17:F18) -> 1753.111 | G22: =G10-SUM(G17:G18) -> 2337.175 | H22: =H10-SUM(H17:H18) -> 2900.882 | I22: =I10-SUM(I17:I18) -> 3555.108 | J22: =J10-SUM(J17:J18) -> 4320.453 | K22: =K10-SUM(K17:K18) -> 5575.476 | L22: =L10-SUM(L17:L18) -> 6206.7684 | ... Q22: =Q10-SUM(Q17:Q18) -> 13112.27 | R22: =L22/L10 -> 0.82313997 | S22: =M22/M10 -> 0.82048585 | T22: =N22/N10 -> 0.81738618 | U22: =O22/O10 -> 0.81377869 | V22: =P22/P10 -> 0.81480665 | W22: =Q22/Q10 -> 0.81159955
B24: Operating Expenses | E24: =SUM(E25:E27) -> 1331.28 | F24: =SUM(F25:F27) -> 1651.477 | G24: =SUM(G25:G27) -> 2443.632 | H24: =SUM(H25:H27) -> 3246.104 | I24: =SUM(I25:I27) -> 3672.185 | J24: =SUM(J25:J27) -> 4450.845 | K24: =SUM(K25:K27) -> 5565.123 | L24: =SUM(L25:L27) -> 6157.0126 | ... Q24: =SUM(Q25:Q27) -> 10607.138
B25: R&D Expense | E25: ='IS Historical'!E24 -> 763.188 | F25: ='IS Historical'!F24 -> 963.326 | G25: ='IS Historical'!G24 -> 1397.568 | H25: ='IS Historical'!H24 -> 1869.881 | I25: ='IS Historical'!I24 -> 2184.111 | J25: ='IS Historical'!J24 -> 2669.312 | K25: ='IS Historical'!K24 -> 3269.257 | L25: ='IS Assumption'!G40*'IS Intergrated'!L10 -> 3488.1887 | M25: ='IS Assumption'!H40*'IS Intergrated'!M10 -> 3996.1771 | N25: ='IS Assumption'!I40*'IS Intergrated'!N10 -> 4545.0323 | O25: ='IS Assumption'!J40*'IS Intergrated'!O10 -> 5029.86 | P25: ='IS Assumption'!K40*'IS Intergrated'!P10 -> 5318.624 | Q25: ='IS Assumption'!L40*'IS Intergrated'!Q10 -> 5454.3368
B26: ='IS Historical'!B25 -> M&S Expense | E26: ='IS Historical'!E25 -> 299.683 | F26: ='IS Historical'!F25 -> 372.909 | G26: ='IS Historical'!G25 -> 567.691 | H26: ='IS Historical'!H25 -> 769.861 | I26: ='IS Historical'!I25 -> 877.497 | J26: ='IS Historical'!J25 -> 1134.535 | K26: ='IS Historical'!K25 -> 1541.178 | L26: ='IS Assumption'!F50*'IS Intergrated'!L10 -> 1768.1811 | M26: ='IS Assumption'!G50*'IS Intergrated'!M10 -> 2232.729 | N26: ='IS Assumption'!H50*'IS Intergrated'!N10 -> 2803.4022 | O26: ='IS Assumption'!I50*'IS Intergrated'!O10 -> 3172.7832 | P26: ='IS Assumption'!J50*'IS Intergrated'!P10 -> 3439.5625 | Q26: ='IS Assumption'!K50*'IS Intergrated'!Q10 -> 3626.9714
B27: ='IS Historical'!B26 -> G&A Expense | E27: ='IS Historical'!E26 -> 268.409 | F27: ='IS Historical'!F26 -> 315.242 | G27: ='IS Historical'!G26 -> 478.373 | H27: ='IS Historical'!H26 -> 606.362 | I27: ='IS Historical'!I26 -> 610.577 | J27: ='IS Historical'!J26 -> 646.998 | K27: ='IS Historical'!K26 -> 754.688 | L27: ='IS Assumption'!F60*'IS Intergrated'!L10 -> 900.64289 | M27: ='IS Assumption'!G60*'IS Intergrated'!M10 -> 1045.0909 | N27: ='IS Assumption'!H60*'IS Intergrated'!N10 -> 1205.5716 | O27: ='IS Assumption'!I60*'IS Intergrated'!O10 -> 1355.341 | P27: ='IS Assumption'!J60*'IS Intergrated'!P10 -> 1458.6215 | Q27: ='IS Assumption'!K60*'IS Intergrated'!Q10 -> 1525.8293
B29: EBIT | E29: =E22-E24 -> 14.086 | F29: =F22-F24 -> 101.634 | G29: =G22-G24 -> -106.457 | H29: =H22-H24 -> -345.222 | I29: =I22-I24 -> -117.077 | J29: =J22-J24 -> -130.392 | K29: =K22-K24 -> 10.353 | L29: =L22-L24 -> 49.755724 | ... Q29: =Q22-Q24 -> 2505.1327
B31: Non-Operating Income - Net | E31: =SUM(E32:E34) -> -360.295 | F31: =SUM(F32:F34) -> -736.298 | G31: =SUM(G32:G34) -> -458.085 | H31: =SUM(H32:H34) -> 34.086 | I31: =SUM(I32:I34) -> 31.67 | J31: =SUM(J32:J34) -> 31.497 | K31: =SUM(K32:K34) -> 11.695 | L31: =SUM(L32:L34) -> 12.104538 | ... Q31: =SUM(Q32:Q34) -> 132.86386
B32: Nonoperating Int. Inc | E32: ='IS Historical'!E31 -> 27.801 | F32: ='IS Historical'!F31 -> 7.174 | G32: ='IS Historical'!G31 -> 2.297 | H32: ='IS Historical'!H31 -> 49.732 | I32: ='IS Historical'!I31 -> 96.663 | J32: ='IS Historical'!J31 -> 112.324 | K32: ='IS Historical'!K31 -> 69.71 | L32: ='IS Assumption'!G70*'Additional Assumptions'!F43 -> 80.028116 | M32: ='IS Assumption'!H70*'Additional Assumptions'!G43 -> 93.734958 | N32: ='IS Assumption'!I70*'Additional Assumptions'!H43 -> 109.95038 | O32: ='IS Assumption'!J70*'Additional Assumptions'!I43 -> 135.33711 | P32: ='IS Assumption'!K70*'Additional Assumptions'!J43 -> 169.74787 | Q32: ='IS Assumption'!L70*'Additional Assumptions'!K43 -> 216.32327 | R32: Forecast as a %of cash? Need guidance
B33: Other Income (Expense) | E33: ='IS Historical'!E32 -> -338.486 | F33: ='IS Historical'!F32 -> -620.759 | G33: ='IS Historical'!G32 -> -434.558 | H33: ='IS Historical'!H32 -> 14.501 | I33: ='IS Historical'!I32 -> -30.916 | J33: ='IS Historical'!J32 -> -50.277 | K33: ='IS Historical'!K32 -> -8.565 | L33: ='IS Assumption'!G80*'IS Intergrated'!L10 -> -13.596733 | M33: ='IS Assumption'!H80*'IS Intergrated'!M10 -> -16.466735 | N33: ='IS Assumption'!I80*'IS Intergrated'!N10 -> -19.86313 | O33: ='IS Assumption'!J80*'IS Intergrated'!O10 -> -23.399786 | P33: ='IS Assumption'!K80*'IS Intergrated'!P10 -> -26.449109 | Q33: ='IS Assumption'!L80*'IS Intergrated'!Q10 -> -29.132572 | R33: Forecast as a %of revenue
B34: Gross Interest Expense | E34: ='IS Historical'!E33 -> -49.61 | F34: ='IS Historical'!F33 -> -122.713 | G34: ='IS Historical'!G33 -> -25.824 | H34: ='IS Historical'!H33 -> -30.147 | I34: ='IS Historical'!I33 -> -34.077 | J34: ='IS Historical'!J33 -> -30.55 | K34: ='IS Historical'!K33 -> -49.45 | L34: =-(WACC!$H$22*'BS Historical Updated'!$J$54) -> -54.326844 | M34: =-(WACC!$H$22*'BS Historical Updated'!$J$54) -> -54.326844 | N34: =-(WACC!$H$22*'BS Historical Updated'!$J$54) -> -54.326844 | O34: =-(WACC!$H$22*'BS Historical Updated'!$J$54) -> -54.326844 | P34: =-(WACC!$H$22*'BS Historical Updated'!$J$54) -> -54.326844 | Q34: =-(WACC!$H$22*'BS Historical Updated'!$J$54) -> -54.326844 | R34: Interest expense forecast as current yield on corp.notes * long-term debt
B36: Pretax Income | E36: =E29+E31 -> -346.209 | F36: =F29+F31 -> -634.664 | G36: =G29+G31 -> -564.542 | H36: =H29+H31 -> -311.136 | I36: =I29+I31 -> -85.407 | J36: =J29+J31 -> -98.895 | K36: =K29+K31 -> 22.048 | L36: =L29+L31 -> 61.860262 | ... Q36: =Q29+Q31 -> 2637.9966
B38: Income Taxes | E38: ='IS Historical'!E37 -> 4.445 | F38: ='IS Historical'!F37 -> 61.651 | G38: ='IS Historical'!G37 -> 49.582 | H38: ='IS Historical'!H37 -> 175.625 | I38: ='IS Historical'!I37 -> 215.112 | J38: ='IS Historical'!J37 -> 157.792 | K38: ='IS Historical'!K37 -> 75.878 | L38: =IF(L36<0,L36*-'DCS Detail'!$D$4,L36*'DCS Detail'!$D$4) -> 14.846463 | M38: =IF(M36<0,M36*-'DCS Detail'!$D$4,M36*'DCS Detail'!$D$4) -> 57.984416 | N38: =IF(N36<0,N36*-'DCS Detail'!$D$4,N36*'DCS Detail'!$D$4) -> 116.5649 | O38: =IF(O36<0,O36*-'DCS Detail'!$D$4,O36*'DCS Detail'!$D$4) -> 254.37774 | P38: =IF(P36<0,P36*-'DCS Detail'!$D$4,P36*'DCS Detail'!$D$4) -> 437.68239 | Q38: =IF(Q36<0,Q36*-'DCS Detail'!$D$4,Q36*'DCS Detail'!$D$4) -> 633.11919 | R38: Pretax income * 24% tax rate
B41: Net Income | E41: =E36-E38+E39 -> -350.654 | F41: =F36-F38+F39 -> -696.315 | G41: =G36-G38+G39 -> -614.124 | H41: =H36-H38+H39 -> -486.761 | I41: =I36-I38+I39 -> -300.519 | J41: =J36-J38+J39 -> -256.687 | K41: =K36-K38 -> -53.83 | L41: =L36-L38 -> 47.013799 | M41: =M36-M38 -> 183.61732 | N41: =N36-N38 -> 369.12219 | O41: =O36-O38 -> 805.5295 | P41: =P36-P38 -> 1385.9942 | Q41: =Q36-Q38 -> 2004.8774 | R41: '20A | S41: '21A | T41: '22A | U41: '23A | V41: '24A | W41: '25A | X41: '26A | Y41: '27E | Z41: '28E | AA41: '29E | AB41: '30E | AC41: '31E | AD41: '32E
R42: -350.654 | S42: -696.315 | T42: -614.124 | U42: -486.761 | V42: -300.519 | W42: -256.687 | X42: -53.83 | Y42: 47.013799 | Z42: 183.61732 | AA42: 369.12219 | AB42: 805.5295 | AC42: 1385.9942 | AD42: 2004.8774
B44: Per Share
B45: EPS (basic) | E45: =E41/E46 -> -1.4321527 | F45: =F41/F46 -> -2.7888409 | G45: =G41/G46 -> -2.4243778 | H45: =H41/H46 -> -1.8991327 | I45: =I41/I46 -> -1.1597095 | J45: =J41/J46 -> -0.98051851 | K45: -0.20684579 | L45: =L41/L46 -> 0.1807111 | M45: =M41/M46 -> 0.70578612 | N45: =N41/N46 -> 1.4188276 | O45: =O41/O46 -> 3.096285 | P45: =P41/P46 -> 5.3274686 | Q45: =Q41/Q46 -> 7.7063246
B46: Basic Shares Outstanding | E46: 244.844 | F46: 249.679 | G46: 253.312 | H46: 256.307 | I46: 259.133 | J46: 261.787 | K46: 260.16 | L46: 260.16 | M46: 260.16 | N46: 260.16 | O46: 260.16 | P46: 260.16 | Q46: 260.16
B47: EPS (diluted) | E47: =E41/E48 -> -1.4321527 | F47: =F41/F48 -> -2.7888409 | G47: =G41/G48 -> -2.4243778 | H47: =H41/H48 -> -1.8991327 | I47: =I41/I48 -> -1.1597095 | J47: =J41/J48 -> -0.98051851 | K47: -0.20684579 | L47: =L41/L48 -> 0.1807111 | M47: =M41/M48 -> 0.70578612 | N47: =N41/N48 -> 1.4188276 | O47: =O41/O48 -> 3.096285 | P47: =P41/P48 -> 5.3274686 | Q47: =Q41/Q48 -> 7.7063246
B48: Diluted Shares Outstanding | E48: 244.844 | F48: 249.679 | G48: 253.312 | H48: 256.307 | I48: 259.133 | J48: 261.787 | K48: 260.16 | L48: ='Comp. Multi & Imp. Val'!$W$13 -> 260.16 | M48: ='Comp. Multi & Imp. Val'!$W$13 -> 260.16 | N48: ='Comp. Multi & Imp. Val'!$W$13 -> 260.16 | O48: ='Comp. Multi & Imp. Val'!$W$13 -> 260.16 | P48: ='Comp. Multi & Imp. Val'!$W$13 -> 260.16 | Q48: ='Comp. Multi & Imp. Val'!$W$13 -> 260.16
B49: Total Shares Outstanding | E49: 244.844 | F49: 249.679 | G49: 253.312 | H49: 256.307 | I49: 259.133 | J49: 261.787 | K49: 253.4 | L49: 253.4 | M49: 253.4 | N49: 253.4 | O49: 253.4 | P49: 253.4 | Q49: 253.4
B52: EBIT | E52: =E29 -> 14.086 | F52: =F29 -> 101.634 | G52: =G29 -> -106.457 | H52: =H29 -> -345.222 | I52: =I29 -> -117.077 | J52: =J29 -> -130.392 | K52: =K29 -> 10.353 | L52: =L29 -> 49.755724 | ... Q52: =Q29 -> 2505.1327
B53: D&A | E53: =E18 -> 85.179 | F53: =F18 -> 82.162 | G53: =G18 -> 55.353 | H53: =H18 -> 52.48 | I53: =I18 -> 78.738 | J53: =J18 -> 78.738 | K53: =K18 -> 140.67 | L53: =L18 -> 139.14995 | ... Q53: =Q18 -> 80.690798
B55: EBITDA | E55: =SUM(E52:E53) -> 99.265 | F55: =SUM(F52:F53) -> 183.796 | G55: =SUM(G52:G53) -> -51.104 | H55: =SUM(H52:H53) -> -292.742 | I55: =SUM(I52:I53) -> -38.339 | J55: =SUM(J52:J53) -> -51.654 | K55: =SUM(K52:K53) -> 151.023 | L55: =SUM(L52:L53) -> 188.90568 | ... Q55: =SUM(Q52:Q53) -> 2585.8235
B57: Trailing 12-Year Revenue CAGR | E57: =_xlfn.RRI(Q4,E10,Q10) -> 0.2116174
B59: Year | C59: Revenue ($M) | D59: Type | E59: YoY Growth (%) | F59: Total CAGR | H59: '20A | I59: '21A | J59: '22A | K59: '23A | L59: '24A | M59: '25A | N59: '26A | O59: '27E | P59: '28E | Q59: '29E | R59: '30E | S59: '31E | T59: '32E
B60: 43983 | C60: =E10 -> 1614.173 | D60: Actual | H60: =E9 -> 0.3339 | I60: =F9 -> 0.29424293 | J60: =G9 -> 0.34164907 | K60: =H9 -> 0.26107592 | L60: =I9 -> 0.23310843 | M60: =J9 -> 0.19655403 | N60: =K9 -> 0.26019653 | O60: =L9 -> 0.14729193 | ... T60: =Q9 -> 0.10145761
B61: 44377 | C61: =F10 -> 2089.132 | D61: Actual | E61: =C61/C60-1 -> 0.29424293 | F61: =$E$57 -> 0.2116174 | H61: =_xlfn.RRI($K$4,$E$10,$K$10) -> 0.2636534 | I61: =_xlfn.RRI($K$4,$E$10,$K$10) -> 0.2636534 | J61: =_xlfn.RRI($K$4,$E$10,$K$10) -> 0.2636534 | K61: =_xlfn.RRI($K$4,$E$10,$K$10) -> 0.2636534 | L61: =_xlfn.RRI($K$4,$E$10,$K$10) -> 0.2636534 | M61: =_xlfn.RRI($K$4,$E$10,$K$10) -> 0.2636534 | N61: =_xlfn.RRI($K$4,$E$10,$K$10) -> 0.2636534
B62: =EDATE(B61,12) -> 44742 | C62: =G10 -> 2802.882 | D62: Actual | E62: =C62/C61-1 -> 0.34164907 | F62: =$E$57 -> 0.2116174 | O62: =_xlfn.RRI($Q$7,$K$10,$Q$10) -> 0.16172419 | P62: =_xlfn.RRI($Q$7,$K$10,$Q$10) -> 0.16172419 | Q62: =_xlfn.RRI($Q$7,$K$10,$Q$10) -> 0.16172419 | R62: =_xlfn.RRI($Q$7,$K$10,$Q$10) -> 0.16172419 | S62: =_xlfn.RRI($Q$7,$K$10,$Q$10) -> 0.16172419 | T62: =_xlfn.RRI($Q$7,$K$10,$Q$10) -> 0.16172419
B63: =EDATE(B62,12) -> 45107 | C63: =H10 -> 3534.647 | D63: Actual | E63: =C63/C62-1 -> 0.26107592 | F63: =$E$57 -> 0.2116174
B64: =EDATE(B63,12) -> 45473 | C64: =I10 -> 4358.603 | D64: Actual | E64: =C64/C63-1 -> 0.23310843 | F64: =$E$57 -> 0.2116174
B65: =EDATE(B64,12) -> 45838 | C65: =J10 -> 5215.304 | D65: Actual | E65: =C65/C64-1 -> 0.19655403 | F65: =$E$57 -> 0.2116174
B66: =EDATE(B65,12) -> 46203 | C66: =K10 -> 6572.308 | D66: Actual | E66: =C66/C65-1 -> 0.26019653 | F66: =$E$57 -> 0.2116174
B67: =EDATE(B66,12) -> 46568 | C67: =L10 -> 7540.3559 | D67: Forecast | E67: =C67/C66-1 -> 0.14729193 | F67: =$E$57 -> 0.2116174
B68: =EDATE(B67,12) -> 46934 | C68: =M10 -> 9131.9763 | D68: Forecast | E68: =C68/C67-1 -> 0.21108027 | F68: =$E$57 -> 0.2116174
B69: =EDATE(B68,12) -> 47299 | C69: =N10 -> 11015.519 | D69: Forecast | E69: =C69/C68-1 -> 0.20625793 | F69: =$E$57 -> 0.2116174
B70: =EDATE(B69,12) -> 47664 | C70: =O10 -> 12976.846 | D70: Forecast | E70: =C70/C69-1 -> 0.17805129 | F70: =$E$57 -> 0.2116174
B71: =EDATE(B70,12) -> 48029 | C71: =P10 -> 14667.912 | D71: Forecast | E71: =C71/C70-1 -> 0.13031412 | F71: =$E$57 -> 0.2116174
B72: =EDATE(B71,12) -> 48395 | C72: =Q10 -> 16156.084 | D72: Forecast | E72: =C72/C71-1 -> 0.10145761 | F72: =$E$57 -> 0.2116174

Sheet Graphs for report 
A1: FY | B1: Cloud Sales | C1: Growth (%)
A2: FY25 | B2: ='IS Intergrated'!J11/1000 -> 3.4474 | E2: '26A | F2: '27E | G2: '28E | H2: '29E | I2: '30E | J2: '31E | K2: '32E | S2: COLOUR CODE
A3: FY26 | B3: ='IS Intergrated'!K11 -> 4410.627 | C3: =(B3/B2)-1 -> 1278.4068 | E3: ='IS Intergrated'!K11/1000 -> 4.410627 | F3: ='IS Intergrated'!L11/1000 -> 5.9094218 | G3: ='IS Intergrated'!M11/1000 -> 7.6343851 | H3: ='IS Intergrated'!N11/1000 -> 10.459659 | I3: ='IS Intergrated'!O11/1000 -> 12.342398 | J3: ='IS Intergrated'!P11/1000 -> 13.94691 | K3: ='IS Intergrated'!Q11/1000 -> 15.341601
A4: FY27 | B4: ='IS Intergrated'!L11 -> 5909.4218 | C4: =(B4/B3)-1 -> 0.33981444 | E4: =E3/B2-1 -> 0.2794068 | F4: ='Revenue Assumptions'!F7 -> 0.29 | G4: ='Revenue Assumptions'!G7 -> 0.26 | H4: ='Revenue Assumptions'!H7 -> 0.23 | I4: ='Revenue Assumptions'!I7 -> 0.18 | J4: ='Revenue Assumptions'!J7 -> 0.13 | K4: ='Revenue Assumptions'!K7 -> 0.1 | N4: Company | O4: MSCI | P4: Sustainalytics Score
A5: FY28 | B5: ='IS Intergrated'!M11 -> 7634.3851 | C5: =(B5/B4)-1 -> 0.29190053 | N5: Atlassian | P5: 17.19 (Low)
A6: FY29 | B6: ='IS Intergrated'!N11 -> 10459.659 | C6: =(B6/B5)-1 -> 0.37007227 | N6: ServiceNow | P6: 16.18 (Low)
A7: FY30 | B7: ='IS Intergrated'!O11 -> 12342.398 | C7: =(B7/B6)-1 -> 0.18 | N7: HubSpot | P7: 17.25 (Low)
N8: GitLab | P8: 13.63 (Low)
N9: Monday.com | P9: 18.89 (Low)
N10: Freshworks | P10: 24.77 (Medium)
N11: Asana | P11: 10.57 (Low)
K16: AI Pricing & Monetisation Comparison
K17: Company | L17: AI Offering | M17: Included in core plan? | N17: Separate add-on/ Premium Plan? | O17: Usage Based Pricing?
K18: Atlassian | L18: Rovo | M18: ✅ (included credits in paid plans) | N18: ❌ | O18: ✅ (excess usage fees from Dec2026)
K19: ServiceNow | L19: Now Assist | M19: ❌ | N19: ✅ (premium SKU) | O19: Varies
K20: GitHub | L20: Copilot | M20: ❌ | N20: ✅ (add-on) | O20: ✅
K21: Monday.com | L21: monday AI | M21: ❌ | N21: ✅ (premium plan) | O21: ✅
K22: Asana | L22: Asana AI | M22: ❌ | N22: ✅ (premium plan) | O22: ✅
D23: Luca fix this up to standard chart template (use our references) when you're free | K23: GitLab | L23: GitLab Duo | M23: ❌ | N23: ✅ (add-on) | O23: ✅
A28: Collections vc Atlassion Platform Graph
A29: Teamwork | B29: 67
A30: Service | B30: 28
A31: Platform | B31: 22
A32: Software | B32: 11
A33: Product | B33: 9
A34: Strategy | B34: 3
B55: Jira | C55: Jira Service Management | D55: Confluence
A56: Knowledge workers | B56: 65 | C56: 77 | D56: 68
A57: Developers and engineers | B57: 35 | C57: 23 | D57: 32
B77: 2025 | C77: 2026
A78: North America | B78: 148.2 | C78: 172.7
A79: EMEA | B79: 60 | C79: 70.8
A80: Asia Pacific | B80: 69.4 | C80: 86.1
B99: Americas | C99: 0.48
B100: EMEA | C100: 0.41
B101: Asia Pacific | C101: 0.11
A121: 2025 | B121: 2032
A122: 104.2 | B122: 368

Sheet BS Intergrated
A1: BS Intergrated
A2: NASDAQ: TEAM
E5: 43983 | F5: 44377 | G5: =EDATE(F5,12) -> 44742 | H5: =EDATE(G5,12) -> 45107 | I5: =EDATE(H5,12) -> 45473 | J5: =EDATE(I5,12) -> 45838 | K5: 46174 | L5: =EDATE(K5,12) -> 46539 | M5: =EDATE(L5,12) -> 46905 | N5: =EDATE(M5,12) -> 47270 | O5: =EDATE(N5,12) -> 47635 | P5: =EDATE(O5,12) -> 48000 | Q5: =EDATE(P5,12) -> 48366
E6: Actuals | F6: Actuals | G6: Actuals | H6: Actuals | I6: Actuals | J6: Actuals | K6: Actuals | L6: Forecast | M6: Forecast | N6: Forecast | O6: Forecast | P6: Forecast | Q6: Forecast
B10: Assets
B11: Cash & Cash Equivalents | E11: ='BS Historical Updated'!D7 -> 1479.969 | F11: ='BS Historical Updated'!E7 -> 919.227 | G11: ='BS Historical Updated'!F7 -> 1385.265 | H11: ='BS Historical Updated'!G7 -> 2102.55 | I11: ='BS Historical Updated'!H7 -> 2176.93 | J11: ='BS Historical Updated'!I7 -> 2512.874 | K11: ='BS Historical Updated'!J7 -> 1239.512 | L11: =K11+'CF Intergrated'!L49 -> 1290.192 | M11: =L11+'CF Intergrated'!M49 -> 1385.8473 | N11: =M11+'CF Intergrated'!N49 -> 1504.8372 | O11: =N11+'CF Intergrated'!O49 -> 1774.4938 | P11: =O11+'CF Intergrated'!P49 -> 2164.3669 | Q11: =P11+'CF Intergrated'!Q49 -> 2771.1576
B12: Short-Term Investments | E12: ='BS Historical Updated'!D8 -> 676.072 | F12: ='BS Historical Updated'!E8 -> 313.001 | G12: ='BS Historical Updated'!F8 -> 73.294 | H12: ='BS Historical Updated'!G8 -> 10 | I12: ='BS Historical Updated'!H8 -> 161.973 | J12: ='BS Historical Updated'!I8 -> 424.268 | K12: ='BS Historical Updated'!J8 -> 0 | L12: 0 | M12: 0 | N12: 0 | O12: 0 | P12: 0 | Q12: 0
B13: Trade Receivables | E13: ='BS Historical Updated'!D9 -> 112.019 | F13: ='BS Historical Updated'!E9 -> 173.473 | G13: ='BS Historical Updated'!F9 -> 308.127 | H13: ='BS Historical Updated'!G9 -> 477.678 | I13: ='BS Historical Updated'!H9 -> 628.049 | J13: ='BS Historical Updated'!I9 -> 778.302 | K13: ='BS Historical Updated'!J9 -> 1269.947 | L13: ='BS Assumptions'!E9*'IS Intergrated'!L10 -> 1105.9001 | M13: ='BS Assumptions'!F9*'IS Intergrated'!M10 -> 1339.3338 | N13: ='BS Assumptions'!G9*'IS Intergrated'!N10 -> 1615.582 | O13: ='BS Assumptions'!H9*'IS Intergrated'!O10 -> 1903.2385 | P13: ='BS Assumptions'!I9*'IS Intergrated'!P10 -> 2151.2573 | Q13: ='BS Assumptions'!J9*'IS Intergrated'!Q10 -> 2369.5188
B14: Tax Receivables | E14: ='BS Historical Updated'!D10 -> 1.509 | F14: ='BS Historical Updated'!E10 -> 2.322 | G14: ='BS Historical Updated'!F10 -> 0.541 | H14: ='BS Historical Updated'!G10 -> 0 | I14: ='BS Historical Updated'!H10 -> 0 | J14: ='BS Historical Updated'!I10 -> 0 | K14: ='BS Historical Updated'!J10 -> 0 | L14: 0 | M14: 0 | N14: 0 | O14: 0 | P14: 0 | Q14: 0
B15: Derivative Assets | E15: ='BS Historical Updated'!D11 -> 327.487 | F15: ='BS Historical Updated'!E11 -> 127.486 | G15: ='BS Historical Updated'!F11 -> 13.685 | H15: ='BS Historical Updated'!G11 -> 0 | I15: ='BS Historical Updated'!H11 -> 0 | J15: ='BS Historical Updated'!I11 -> 0 | K15: ='BS Historical Updated'!J11 -> 0 | L15: 0 | M15: 0 | N15: 0 | O15: 0 | P15: 0 | Q15: 0
B16: Prepaid Expenses & Other Current Assets | E16: ='BS Historical Updated'!D12 -> 46.73 | F16: ='BS Historical Updated'!E12 -> 91.997 | G16: ='BS Historical Updated'!F12 -> 118.342 | H16: ='BS Historical Updated'!G12 -> 146.136 | I16: ='BS Historical Updated'!H12 -> 109.312 | J16: ='BS Historical Updated'!I12 -> 175.793 | K16: ='BS Historical Updated'!J12 -> 287.663 | L16: ='BS Assumptions'!E19*'IS Intergrated'!L24 -> 330.61992 | M16: ='BS Assumptions'!F19*'IS Intergrated'!M24 -> 390.59987 | N16: ='BS Assumptions'!G19*'IS Intergrated'!N24 -> 459.33394 | O16: ='BS Assumptions'!H19*'IS Intergrated'!O24 -> 513.24566 | P16: ='BS Assumptions'!I19*'IS Intergrated'!P24 -> 548.62325 | Q16: ='BS Assumptions'!J19*'IS Intergrated'!Q24 -> 569.58321
B18: Total Current Assets | E18: =SUM(E11:E16) -> 2643.786 | F18: =SUM(F11:F16) -> 1627.506 | G18: =SUM(G11:G16) -> 1899.254 | H18: =SUM(H11:H16) -> 2736.364 | I18: =SUM(I11:I16) -> 3076.264 | J18: =SUM(J11:J16) -> 3891.237 | K18: =SUM(K11:K16) -> 2797.122 | L18: =SUM(L11:L16) -> 2726.7121 | ... Q18: =SUM(Q11:Q16) -> 5710.2595
B20: Net Property, Plant & Equipment | E20: ='BS Historical Updated'!D16 -> 97.648 | F20: ='BS Historical Updated'!E16 -> 66.221 | G20: ='BS Historical Updated'!F16 -> 98.554 | H20: ='BS Historical Updated'!G16 -> 81.402 | I20: ='BS Historical Updated'!H16 -> 86.315 | J20: ='BS Historical Updated'!I16 -> 105.118 | K20: ='BS Historical Updated'!J16 -> 86.302 | L20: =L21+L27 -> 107.3517 | M20: =M21+M27 -> 125.36368 | N20: =N21+N27 -> 145.63729 | O20: =O21+O27 -> 159.22441 | P20: =P21+P27 -> 153.56253 | Q20: =Q21+Q27 -> 132.35781
B21: Property, Plant & Equipment - Gross | E21: ='BS Historical Updated'!D17 -> 155.765 | F21: ='BS Historical Updated'!E17 -> 148.151 | G21: ='BS Historical Updated'!F17 -> 172.288 | H21: ='BS Historical Updated'!G17 -> 186.997 | I21: ='BS Historical Updated'!H17 -> 215.14 | J21: ='BS Historical Updated'!I17 -> 252.897 | K21: ='BS Historical Updated'!J17 -> 242.698 | L21: =SUM(L22:L26) -> 301.40765 | M21: =SUM(M22:M26) -> 365.02886 | N21: =SUM(N22:N26) -> 440.31896 | O21: =SUM(O22:O26) -> 518.71832 | P21: =SUM(P22:P26) -> 586.31464 | Q21: =SUM(Q22:Q26) -> 645.80072
B22: Machinery & Equipment | E22: ='BS Historical Updated'!D18 -> 9.652 | F22: ='BS Historical Updated'!E18 -> 10.43 | G22: ='BS Historical Updated'!F18 -> 9.14 | H22: ='BS Historical Updated'!G18 -> 9.298 | I22: ='BS Historical Updated'!H18 -> 11.2 | J22: ='BS Historical Updated'!I18 -> 15.008 | K22: ='BS Historical Updated'!J18 -> 16.27 | L22: ='BS Assumptions'!E29*'IS Intergrated'!L10 -> 35.773876 | M22: ='BS Assumptions'!F29*'IS Intergrated'!M10 -> 43.325036 | N22: ='BS Assumptions'!G29*'IS Intergrated'!N10 -> 52.261168 | O22: ='BS Assumptions'!H29*'IS Intergrated'!O10 -> 61.566336 | P22: ='BS Assumptions'!I29*'IS Intergrated'!P10 -> 69.589299 | Q22: ='BS Assumptions'!J29*'IS Intergrated'!Q10 -> 76.649663
B23: Computer Software & Equipment | E23: ='BS Historical Updated'!D19 -> 12.065 | F23: ='BS Historical Updated'!E19 -> 9.537 | G23: ='BS Historical Updated'!F19 -> 18.324 | H23: ='BS Historical Updated'!G19 -> 29.801 | I23: ='BS Historical Updated'!H19 -> 40.824 | J23: ='BS Historical Updated'!I19 -> 58.559 | K23: ='BS Historical Updated'!J19 -> 73.057 | L23: ='BS Assumptions'!E39*'IS Intergrated'!L10 -> 84.241544 | M23: ='BS Assumptions'!F39*'IS Intergrated'!M10 -> 102.02327 | N23: ='BS Assumptions'!G39*'IS Intergrated'!N10 -> 123.06638 | O23: ='BS Assumptions'!H39*'IS Intergrated'!O10 -> 144.97851 | P23: ='BS Assumptions'!I39*'IS Intergrated'!P10 -> 163.87126 | Q23: ='BS Assumptions'!J39*'IS Intergrated'!Q10 -> 180.49724
B24: Furniture & Fittings | E24: ='BS Historical Updated'!D20 -> 19.687 | F24: ='BS Historical Updated'!E20 -> 21.188 | G24: ='BS Historical Updated'!F20 -> 25.157 | H24: ='BS Historical Updated'!G20 -> 24.773 | I24: ='BS Historical Updated'!H20 -> 25.172 | J24: ='BS Historical Updated'!I20 -> 25.217 | K24: ='BS Historical Updated'!J20 -> 27.767 | L24: ='BS Assumptions'!E49*'IS Intergrated'!L10 -> 37.287777 | M24: ='BS Assumptions'!F49*'IS Intergrated'!M10 -> 45.158491 | N24: ='BS Assumptions'!G49*'IS Intergrated'!N10 -> 54.472788 | O24: ='BS Assumptions'!H49*'IS Intergrated'!O10 -> 64.171738 | P24: ='BS Assumptions'!I49*'IS Intergrated'!P10 -> 72.534222 | Q24: ='BS Assumptions'!J49*'IS Intergrated'!Q10 -> 79.893371
B25: Leasehold Improvements | E25: ='BS Historical Updated'!D21 -> 103.1 | F25: ='BS Historical Updated'!E21 -> 106.996 | G25: ='BS Historical Updated'!F21 -> 119.667 | H25: ='BS Historical Updated'!G21 -> 123.125 | I25: ='BS Historical Updated'!H21 -> 137.944 | J25: ='BS Historical Updated'!I21 -> 154.113 | K25: ='BS Historical Updated'!J21 -> 125.604 | L25: ='BS Assumptions'!E59*'IS Intergrated'!L10 -> 144.10446 | M25: ='BS Assumptions'!F59*'IS Intergrated'!M10 -> 174.52206 | N25: ='BS Assumptions'!G59*'IS Intergrated'!N10 -> 210.51862 | O25: ='BS Assumptions'!H59*'IS Intergrated'!O10 -> 248.00173 | P25: ='BS Assumptions'!I59*'IS Intergrated'!P10 -> 280.31986 | Q25: ='BS Assumptions'!J59*'IS Intergrated'!Q10 -> 308.76045
B26: Constructions in Progress | E26: ='BS Historical Updated'!D22 -> 11.261 | F26: ='BS Historical Updated'!E22 -> 0 | G26: ='BS Historical Updated'!F22 -> 0 | H26: ='BS Historical Updated'!G22 -> 0 | I26: ='BS Historical Updated'!H22 -> 0 | J26: ='BS Historical Updated'!I22 -> 0 | K26: ='BS Historical Updated'!J22 -> 0 | L26: 0 | M26: 0 | N26: 0 | O26: 0 | P26: 0 | Q26: 0
B27: Accumulated Depreciation | E27: ='BS Historical Updated'!D23 -> -58.117 | F27: ='BS Historical Updated'!E23 -> -81.93 | G27: ='BS Historical Updated'!F23 -> -73.734 | H27: ='BS Historical Updated'!G23 -> -105.595 | I27: ='BS Historical Updated'!H23 -> -128.825 | J27: ='BS Historical Updated'!I23 -> -147.779 | K27: ='BS Historical Updated'!J23 -> -156.396 | L27: =K27-'IS Intergrated'!L19 -> -194.05595 | M27: =L27-'IS Intergrated'!M19 -> -239.66518 | N27: =M27-'IS Intergrated'!N19 -> -294.68167 | O27: =N27-'IS Intergrated'!O19 -> -359.49391 | P27: =O27-'IS Intergrated'!P19 -> -432.75211 | Q27: =P27-'IS Intergrated'!Q19 -> -513.44291
B28: Machinery & Equipment | E28: ='BS Historical Updated'!D24 -> -5.618 | F28: ='BS Historical Updated'!E24 -> -7.545 | G28: ='BS Historical Updated'!F24 -> -7.903 | H28: ='BS Historical Updated'!G24 -> - | I28: ='BS Historical Updated'!H24 -> - | J28: ='BS Historical Updated'!I24 -> - | K28: ='BS Historical Updated'!J24 -> - | L28: - | M28: - | N28: - | O28: - | P28: - | Q28: -
B29: Computer Software & Equipment | E29: ='BS Historical Updated'!D25 -> -8.611 | F29: ='BS Historical Updated'!E25 -> -9.062 | G29: ='BS Historical Updated'!F25 -> -2.902 | H29: ='BS Historical Updated'!G25 -> - | I29: ='BS Historical Updated'!H25 -> - | J29: ='BS Historical Updated'!I25 -> - | K29: ='BS Historical Updated'!J25 -> - | L29: - | M29: - | N29: - | O29: - | P29: - | Q29: -
B30: Furniture & Fittings | E30: ='BS Historical Updated'!D26 -> -8.388 | F30: ='BS Historical Updated'!E26 -> -11.259 | G30: ='BS Historical Updated'!F26 -> -12.171 | H30: ='BS Historical Updated'!G26 -> - | I30: ='BS Historical Updated'!H26 -> - | J30: ='BS Historical Updated'!I26 -> - | K30: ='BS Historical Updated'!J26 -> - | L30: - | M30: - | N30: - | O30: - | P30: - | Q30: -
B31: Leasehold Improvements | E31: ='BS Historical Updated'!D27 -> -35.5 | F31: ='BS Historical Updated'!E27 -> -54.064 | G31: ='BS Historical Updated'!F27 -> -50.758 | H31: ='BS Historical Updated'!G27 -> - | I31: ='BS Historical Updated'!H27 -> - | J31: ='BS Historical Updated'!I27 -> - | K31: ='BS Historical Updated'!J27 -> - | L31: - | M31: - | N31: - | O31: - | P31: - | Q31: -
B32: Constructions in Progress | E32: ='BS Historical Updated'!D28 -> 0 | F32: ='BS Historical Updated'!E28 -> 0 | G32: ='BS Historical Updated'!F28 -> 0 | H32: ='BS Historical Updated'!G28 -> - | I32: ='BS Historical Updated'!H28 -> - | J32: ='BS Historical Updated'!I28 -> - | K32: ='BS Historical Updated'!J28 -> - | L32: - | M32: - | N32: - | O32: - | P32: - | Q32: -
B33: Operating Lease Right-of-Use Assets | E33: ='BS Historical Updated'!D29 -> 217.683 | F33: ='BS Historical Updated'!E29 -> 205.3 | G33: ='BS Historical Updated'!F29 -> 267.328 | H33: ='BS Historical Updated'!G29 -> 184.195 | I33: ='BS Historical Updated'!H29 -> 172.468 | J33: ='BS Historical Updated'!I29 -> 169.127 | K33: ='BS Historical Updated'!J29 -> 114.059 | L33: ='BS Assumptions'!E69 -> 114.059 | M33: ='BS Assumptions'!F69 -> 114.059 | N33: ='BS Assumptions'!G69 -> 114.059 | O33: ='BS Assumptions'!H69 -> 114.059 | P33: ='BS Assumptions'!I69 -> 114.059 | Q33: ='BS Assumptions'!J69 -> 114.059
B34: Deferred Tax Assets | E34: ='BS Historical Updated'!D30 -> 35.351 | F34: ='BS Historical Updated'!E30 -> 36.174 | G34: ='BS Historical Updated'!F30 -> 42.76 | H34: ='BS Historical Updated'!G30 -> 9.945 | I34: ='BS Historical Updated'!H30 -> 3.934 | J34: ='BS Historical Updated'!I30 -> 3.762 | K34: ='BS Historical Updated'!J30 -> 4.088 | L34: ='BS Assumptions'!E79 -> 4.088 | M34: ='BS Assumptions'!F79 -> 4.088 | N34: ='BS Assumptions'!G79 -> 4.088 | O34: ='BS Assumptions'!H79 -> 4.088 | P34: ='BS Assumptions'!I79 -> 4.088 | Q34: ='BS Assumptions'!J79 -> 4.088
B35: Goodwill | E35: ='BS Historical Updated'!D31 -> 645.14 | F35: ='BS Historical Updated'!E31 -> 725.758 | G35: ='BS Historical Updated'!F31 -> 732.666 | H35: ='BS Historical Updated'!G31 -> 727.221 | I35: ='BS Historical Updated'!H31 -> 1288.756 | J35: ='BS Historical Updated'!I31 -> 1304.445 | K35: ='BS Historical Updated'!J31 -> 2302.739 | L35: ='BS Assumptions'!E113 -> 2792.5451 | M35: ='BS Assumptions'!F113 -> 3477.0594 | N35: ='BS Assumptions'!G113 -> 4412.9154 | O35: ='BS Assumptions'!H113 -> 5645.1702 | P35: ='BS Assumptions'!I113 -> 7184.6843 | Q35: ='BS Assumptions'!J113 -> 9041.9547
B36: Intangible Assets, Net | E36: ='BS Historical Updated'!D32 -> 129.69 | F36: ='BS Historical Updated'!E32 -> 124.59 | G36: ='BS Historical Updated'!F32 -> 100.84 | H36: ='BS Historical Updated'!G32 -> 69.072 | I36: ='BS Historical Updated'!H32 -> 299.057 | J36: ='BS Historical Updated'!I32 -> 244.84 | K36: ='BS Historical Updated'!J32 -> 432.258 | L36: =MAX(K36-'BS Assumptions'!E119,0) -> 330.768 | M36: =MAX(L36-'BS Assumptions'!F119,0) -> 229.278 | N36: =MAX(M36-'BS Assumptions'!G119,0) -> 127.788 | O36: =MAX(N36-'BS Assumptions'!H119,0) -> 26.298 | P36: =MAX(O36-'BS Assumptions'!I119,0) -> 0 | Q36: =MAX(P36-'BS Assumptions'!J119,0) -> 0
B37: Strategic Investments | E37: ='BS Historical Updated'!D33 -> 0 | F37: ='BS Historical Updated'!E33 -> 122.159 | G37: ='BS Historical Updated'!F33 -> 159.064 | H37: ='BS Historical Updated'!G33 -> 225.538 | I37: ='BS Historical Updated'!H33 -> 223.221 | J37: ='BS Historical Updated'!I33 -> 221.942 | K37: ='BS Historical Updated'!J33 -> 213.147 | L37: 213.147 | M37: 213.147 | N37: 213.147 | O37: 213.147 | P37: 213.147 | Q37: 213.147
B38: Other Non-Current Assets | E38: ='BS Historical Updated'!D34 -> 124.774 | F38: ='BS Historical Updated'!E34 -> 37.636 | G38: ='BS Historical Updated'!F34 -> 60.74 | H38: ='BS Historical Updated'!G34 -> 73.052 | I38: ='BS Historical Updated'!H34 -> 62.118 | J38: ='BS Historical Updated'!I34 -> 101.499 | K38: ='BS Historical Updated'!J34 -> 153.814 | L38: ='BS Assumptions'!E89*'IS Intergrated'!L10 -> 209.80399 | M38: ='BS Assumptions'!F89*'IS Intergrated'!M10 -> 254.08947 | N38: ='BS Assumptions'!G89*'IS Intergrated'!N10 -> 306.49744 | O38: ='BS Assumptions'!H89*'IS Intergrated'!O10 -> 361.06971 | P38: ='BS Assumptions'!I89*'IS Intergrated'!P10 -> 408.12219 | Q38: ='BS Assumptions'!J89*'IS Intergrated'!Q10 -> 449.52929
B40: Total Non-Current Assets | E40: =E20+E33+E34+E35+E36+E38+E37 -> 1250.286 | F40: =F20+F33+F34+F35+F36+F38+F37 -> 1317.838 | G40: =G20+G33+G34+G35+G36+G38+G37 -> 1461.952 | H40: =H20+H33+H34+H35+H36+H38+H37 -> 1370.425 | I40: =I20+I33+I34+I35+I36+I38+I37 -> 2135.869 | J40: =J20+J33+J34+J35+J36+J38+J37 -> 2150.733 | K40: =K20+K33+K34+K35+K36+K38+K37 -> 3306.407 | L40: =L20+L33+L34+L35+L36+L38+L37 -> 3771.7628 | ... Q40: =Q20+Q33+Q34+Q35+Q36+Q38+Q37 -> 9955.1358
B42: Total Assets | E42: =E40+E18 -> 3894.072 | F42: =F40+F18 -> 2945.344 | G42: =G40+G18 -> 3361.206 | H42: =H40+H18 -> 4106.789 | I42: =I40+I18 -> 5212.133 | J42: =J40+J18 -> 6041.97 | K42: =K40+K18 -> 6103.529 | L42: =L40+L18 -> 6498.4749 | ... Q42: =Q40+Q18 -> 15665.395
B44: Liabilities & Shareholders' Equity
B45: Current
B46: ST Debt | E46: ='BS Historical Updated'!D42 -> 889.183 | F46: ='BS Historical Updated'!E42 -> 348.799 | G46: ='BS Historical Updated'!F42 -> 0 | H46: ='BS Historical Updated'!G42 -> 37.5 | I46: ='BS Historical Updated'!H42 -> 0 | J46: ='BS Historical Updated'!I42 -> 0 | K46: ='BS Historical Updated'!J42 -> 0 | L46: 0 | M46: 0 | N46: 0 | O46: 0 | P46: 0 | Q46: 0
B47: Accounts Payable | E47: ='BS Historical Updated'!D43 -> 202.57 | F47: ='BS Historical Updated'!E43 -> 266.497 | G47: ='BS Historical Updated'!F43 -> 404.908 | H47: ='BS Historical Updated'!G43 -> 159.293 | I47: ='BS Historical Updated'!H43 -> 177.545 | J47: ='BS Historical Updated'!I43 -> 222.092 | K47: ='BS Historical Updated'!J43 -> 262.609 | L47: ='BS Assumptions'!E139*'IS Intergrated'!L10 -> 304.22046 | M47: ='BS Assumptions'!F139*'IS Intergrated'!M10 -> 368.4354 | N47: ='BS Assumptions'!G139*'IS Intergrated'!N10 -> 444.42812 | O47: ='BS Assumptions'!H139*'IS Intergrated'!O10 -> 523.55912 | P47: ='BS Assumptions'!I139*'IS Intergrated'!P10 -> 591.78627 | Q47: ='BS Assumptions'!J139*'IS Intergrated'!Q10 -> 651.82749
B48: Tax Liabilities | E48: ='BS Historical Updated'!D44 -> 19.583 | F48: ='BS Historical Updated'!E44 -> 42.051 | G48: ='BS Historical Updated'!F44 -> 26.367 | H48: ='BS Historical Updated'!G44 -> 0 | I48: ='BS Historical Updated'!H44 -> 0 | J48: ='BS Historical Updated'!I44 -> 0 | K48: ='BS Historical Updated'!J44 -> 0 | L48: 0 | M48: 0 | N48: 0 | O48: 0 | P48: 0 | Q48: 0
B49: Provisions | E49: ='BS Historical Updated'!D45 -> 14.291 | F49: ='BS Historical Updated'!E45 -> 25.148 | G49: ='BS Historical Updated'!F45 -> 32.796 | H49: ='BS Historical Updated'!G45 -> 0 | I49: ='BS Historical Updated'!H45 -> 0 | J49: ='BS Historical Updated'!I45 -> 0 | K49: ='BS Historical Updated'!J45 -> 0 | L49: 0 | M49: 0 | N49: 0 | O49: 0 | P49: 0 | Q49: 0
B50: Deferred Revenue, Current | E50: ='BS Historical Updated'!D46 -> 573.813 | F50: ='BS Historical Updated'!E46 -> 812.943 | G50: ='BS Historical Updated'!F46 -> 1066.059 | H50: ='BS Historical Updated'!G46 -> 1362.736 | I50: ='BS Historical Updated'!H46 -> 1806.269 | J50: ='BS Historical Updated'!I46 -> 2227.002 | K50: ='BS Historical Updated'!J46 -> 2495.431 | L50: ='BS Assumptions'!E149*'IS Intergrated'!L10 -> 2680.4774 | M50: ='BS Assumptions'!F149*'IS Intergrated'!M10 -> 3246.2733 | N50: ='BS Assumptions'!G149*'IS Intergrated'!N10 -> 3915.8429 | O50: ='BS Assumptions'!H149*'IS Intergrated'!O10 -> 4613.0638 | P50: ='BS Assumptions'!I149*'IS Intergrated'!P10 -> 5214.2112 | Q50: ='BS Assumptions'!J149*'IS Intergrated'!Q10 -> 5743.2325
B51: Lease Obligations, Current | E51: ='BS Historical Updated'!D47 -> 34.743 | F51: ='BS Historical Updated'!E47 -> 42.446 | G51: ='BS Historical Updated'!F47 -> 40.638 | H51: ='BS Historical Updated'!G47 -> 44.93 | I51: ='BS Historical Updated'!H47 -> 48.953 | J51: ='BS Historical Updated'!I47 -> 50.164 | K51: ='BS Historical Updated'!J47 -> 48.509 | L51: 48.509 | M51: 48.509 | N51: 48.509 | O51: 48.509 | P51: 48.509 | Q51: 48.509
B52: Accrued Expenses & Other Curr. Liabilities | E52: ='BS Historical Updated'!D48 -> 1284.596 | F52: ='BS Historical Updated'!E48 -> 772.127 | G52: ='BS Historical Updated'!F48 -> 23.288 | H52: ='BS Historical Updated'!G48 -> 423.131 | I52: ='BS Historical Updated'!H48 -> 577.359 | J52: ='BS Historical Updated'!I48 -> 681.604 | K52: ='BS Historical Updated'!J48 -> 764.582 | L52: ='BS Assumptions'!E159*'IS Intergrated'!L24 -> 723.61391 | M52: ='BS Assumptions'!F159*'IS Intergrated'!M24 -> 854.88949 | N52: ='BS Assumptions'!G159*'IS Intergrated'!N24 -> 1005.3248 | O52: ='BS Assumptions'!H159*'IS Intergrated'!O24 -> 1123.3192 | P52: ='BS Assumptions'!I159*'IS Intergrated'!P24 -> 1200.7486 | Q52: ='BS Assumptions'!J159*'IS Intergrated'!Q24 -> 1246.6228
B54: Total Current Liabilities | E54: =SUM(E46:E52) -> 3018.779 | F54: =SUM(F46:F52) -> 2310.011 | G54: =SUM(G46:G52) -> 1594.056 | H54: =SUM(H46:H52) -> 2027.59 | I54: =SUM(I46:I52) -> 2610.126 | J54: =SUM(J46:J52) -> 3180.862 | K54: =SUM(K46:K52) -> 3571.131 | L54: =SUM(L46:L52) -> 3756.8208 | ... Q54: =SUM(Q46:Q52) -> 7690.1918
B56: Deferred Revenue, Net of Current | E56: ='BS Historical Updated'!D52 -> 27.192 | F56: ='BS Historical Updated'!E52 -> 84.652 | G56: ='BS Historical Updated'!F52 -> 116.621 | H56: ='BS Historical Updated'!G52 -> 182.743 | I56: ='BS Historical Updated'!H52 -> 308.467 | J56: ='BS Historical Updated'!I52 -> 254.252 | K56: ='BS Historical Updated'!J52 -> 166.26 | L56: ='BS Assumptions'!E169*'IS Intergrated'!L10 -> 318.30445 | M56: ='BS Assumptions'!F169*'IS Intergrated'!M10 -> 385.49223 | N56: ='BS Assumptions'!G169*'IS Intergrated'!N10 -> 465.00306 | O56: ='BS Assumptions'!H169*'IS Intergrated'!O10 -> 547.79746 | P56: ='BS Assumptions'!I169*'IS Intergrated'!P10 -> 619.1832 | Q56: ='BS Assumptions'!J169*'IS Intergrated'!Q10 -> 682.00405
B57: Deferred Tax Liabilities | E57: ='BS Historical Updated'!D53 -> 31.304 | F57: ='BS Historical Updated'!E53 -> 26.625 | G57: ='BS Historical Updated'!F53 -> 26.457 | H57: ='BS Historical Updated'!G53 -> 10.669 | I57: ='BS Historical Updated'!H53 -> 20.387 | J57: ='BS Historical Updated'!I53 -> 23.881 | K57: ='BS Historical Updated'!J53 -> 27.853 | L57: ='BS Assumptions'!E189 -> 27.853 | M57: ='BS Assumptions'!F189 -> 27.853 | N57: ='BS Assumptions'!G189 -> 27.853 | O57: ='BS Assumptions'!H189 -> 27.853 | P57: ='BS Assumptions'!I189 -> 27.853 | Q57: ='BS Assumptions'!J189 -> 27.853
B58: Long-Term Debt | E58: ='BS Historical Updated'!D54 -> 0 | F58: ='BS Historical Updated'!E54 -> 0 | G58: ='BS Historical Updated'!F54 -> 999.419 | H58: ='BS Historical Updated'!G54 -> 962.093 | I58: ='BS Historical Updated'!H54 -> 985.911 | J58: ='BS Historical Updated'!I54 -> 987.684 | K58: ='BS Historical Updated'!J54 -> 989.56 | L58: 989.56 | M58: 989.56 | N58: 989.56 | O58: 989.56 | P58: 989.56 | Q58: 989.56
B59: Lease Obligations, Net of Current | E59: ='BS Historical Updated'!D55 -> 229.825 | F59: ='BS Historical Updated'!E55 -> 214.103 | G59: ='BS Historical Updated'!F55 -> 274.434 | H59: ='BS Historical Updated'!G55 -> 237.835 | I59: ='BS Historical Updated'!H55 -> 214.474 | J59: ='BS Historical Updated'!I55 -> 201.483 | K59: ='BS Historical Updated'!J55 -> 194.841 | L59: 194.841 | M59: 194.841 | N59: 194.841 | O59: 194.841 | P59: 194.841 | Q59: 194.841
B60: Provisions | E60: ='BS Historical Updated'!D56 -> 9.493 | F60: ='BS Historical Updated'!E56 -> 12.435 | G60: ='BS Historical Updated'!F56 -> 13.804 | H60: ='BS Historical Updated'!G56 -> 0 | I60: ='BS Historical Updated'!H56 -> 0 | J60: ='BS Historical Updated'!I56 -> 0 | K60: ='BS Historical Updated'!J56 -> 0 | L60: 0 | M60: 0 | N60: 0 | O60: 0 | P60: 0 | Q60: 0
B61: Other Non-Current Liabilities | E61: ='BS Historical Updated'!D57 -> 2.173 | F61: ='BS Historical Updated'!E57 -> 2.604 | G61: ='BS Historical Updated'!F57 -> 0.812 | H61: ='BS Historical Updated'!G57 -> 31.177 | I61: ='BS Historical Updated'!H57 -> 39.917 | J61: ='BS Historical Updated'!I57 -> 48.157 | K61: ='BS Historical Updated'!J57 -> 95.445 | L61: ='BS Assumptions'!E179*'IS Intergrated'!L10 -> 105.64287 | M61: ='BS Assumptions'!F179*'IS Intergrated'!M10 -> 127.942 | N61: ='BS Assumptions'!G179*'IS Intergrated'!N10 -> 154.33105 | O61: ='BS Assumptions'!H179*'IS Intergrated'!O10 -> 181.80989 | P61: ='BS Assumptions'!I179*'IS Intergrated'!P10 -> 205.50229 | Q61: ='BS Assumptions'!J179*'IS Intergrated'!Q10 -> 226.35206
B63: Total Non-Current Liabilities | E63: =SUM(E56:E61) -> 299.987 | F63: =SUM(F56:F61) -> 340.419 | G63: =SUM(G56:G61) -> 1431.547 | H63: =SUM(H56:H61) -> 1424.517 | I63: =SUM(I56:I61) -> 1569.156 | J63: =SUM(J56:J61) -> 1515.457 | K63: =SUM(K56:K61) -> 1473.959 | L63: =SUM(L56:L61) -> 1636.2013 | ... Q63: =SUM(Q56:Q61) -> 2120.6101
B65: Total Liabilities | E65: =E63+E54 -> 3318.766 | F65: =F63+F54 -> 2650.43 | G65: =G63+G54 -> 3025.603 | H65: =H63+H54 -> 3452.107 | I65: =I63+I54 -> 4179.282 | J65: =J63+J54 -> 4696.319 | K65: =K63+K54 -> 5045.09 | L65: =L63+L54 -> 5393.0221 | ... Q65: =Q63+Q54 -> 9810.8019
B67: Equity
B68: APIC | E68: ='BS Historical Updated'!D64 -> 1691.698 | F68: ='BS Historical Updated'!E64 -> 2107.621 | G68: ='BS Historical Updated'!F64 -> 2764.178 | H68: ='BS Historical Updated'!G64 -> 3130.631 | I68: ='BS Historical Updated'!H64 -> 4212.064 | J68: ='BS Historical Updated'!I64 -> 5574.29 | K68: ='BS Historical Updated'!J64 -> 7180.851 | L68: =K68+'CF Assumptions'!F38 -> 8961.4988 | M68: =L68+'CF Assumptions'!G38 -> 11072.346 | N68: =M68+'CF Assumptions'!H38 -> 13563.495 | O68: =N68+'CF Assumptions'!I38 -> 16433.313 | P68: =O68+'CF Assumptions'!J38 -> 19603.768 | Q68: =P68+'CF Assumptions'!K38 -> 23015.109
B69: Accum. Other Comp. Income | E69: ='BS Historical Updated'!D65 -> - | F69: ='BS Historical Updated'!E65 -> - | G69: ='BS Historical Updated'!F65 -> - | H69: ='BS Historical Updated'!G65 -> 34.015 | I69: ='BS Historical Updated'!H65 -> 25.303 | J69: ='BS Historical Updated'!I65 -> 13.226 | K69: ='BS Historical Updated'!J65 -> -17.034 | L69: -17.034 | M69: -17.034 | N69: -17.034 | O69: -17.034 | P69: -17.034 | Q69: -17.034
B70: Accumulated Deficit | E70: ='BS Historical Updated'!D66 -> -1116.392 | F70: ='BS Historical Updated'!E66 -> -1812.707 | G70: ='BS Historical Updated'!F66 -> -2428.575 | H70: ='BS Historical Updated'!G66 -> -2509.964 | I70: ='BS Historical Updated'!H66 -> -3204.516 | J70: ='BS Historical Updated'!I66 -> -4241.865 | K70: ='BS Historical Updated'!J66 -> -6105.378 | L70: =K70+'IS Intergrated'!L41+'CF Intergrated'!L37 -> -7839.012 | M70: =L70+'IS Intergrated'!M41+'CF Intergrated'!M37 -> -9766.2423 | N70: =M70+'IS Intergrated'!N41+'CF Intergrated'!N37 -> -11888.269 | O70: =N70+'IS Intergrated'!O41+'CF Intergrated'!O37 -> -13952.557 | P70: =O70+'IS Intergrated'!P41+'CF Intergrated'!P37 -> -15737.018 | Q70: =P70+'IS Intergrated'!Q41+'CF Intergrated'!Q37 -> -17143.482
B72: Total Equity | E72: =SUM(E68:E70) -> 575.306 | F72: =SUM(F68:F70) -> 294.914 | G72: =SUM(G68:G70) -> 335.603 | H72: =SUM(H68:H70) -> 654.682 | I72: =SUM(I68:I70) -> 1032.851 | J72: =SUM(J68:J70) -> 1345.651 | K72: =SUM(K68:K70) -> 1058.439 | L72: =SUM(L68:L70) -> 1105.4528 | ... Q72: =SUM(Q68:Q70) -> 5854.5934
B74: Total Liabilities & Shareholders' Equity | E74: =E72+E65 -> 3894.072 | F74: =F72+F65 -> 2945.344 | G74: =G72+G65 -> 3361.206 | H74: =H72+H65 -> 4106.789 | I74: =I72+I65 -> 5212.133 | J74: =J72+J65 -> 6041.97 | K74: =K72+K65 -> 6103.529 | L74: =L72+L65 -> 6498.4749 | ... Q74: =Q72+Q65 -> 15665.395
E75: =E74-E42 -> 0 | F75: =F74-F42 -> 0 | G75: =G74-G42 -> 0 | H75: =H74-H42 -> 0 | I75: =I74-I42 -> 0 | J75: =J74-J42 -> 0 | K75: =K74-K42 -> 0 | L75: =L74-L42 -> 0 | ... Q75: =Q74-Q42 -> 0

Sheet CF Intergrated
A1: CF Intergrated
A2: NASDAQ: TEAM
E5: 43983 | F5: 44377 | G5: =EDATE(F5,12) -> 44742 | H5: =EDATE(G5,12) -> 45107 | I5: =EDATE(H5,12) -> 45473 | J5: =EDATE(I5,12) -> 45838 | K5: 46203 | L5: =EDATE(K5,12) -> 46568 | M5: =EDATE(L5,12) -> 46934 | N5: =EDATE(M5,12) -> 47299 | O5: =EDATE(N5,12) -> 47664 | P5: =EDATE(O5,12) -> 48029 | Q5: =EDATE(P5,12) -> 48395
D6: ` | E6: Actuals | F6: Actuals | G6: Actuals | H6: Actuals | I6: Actuals | J6: Actuals | K6: Forecast | L6: Forecast | M6: Forecast | N6: Forecast | O6: Forecast | P6: Forecast | Q6: Forecast
B10: Operating Activities
B11: Net Income | E11: ='CF Historical'!D11 -> -350.654 | F11: ='CF Historical'!E11 -> -696.315 | G11: ='CF Historical'!F11 -> -614.124 | H11: ='CF Historical'!G11 -> -486.761 | I11: ='CF Historical'!H11 -> -300.519 | J11: ='CF Historical'!I11 -> -256.687 | K11: ='CF Historical'!J11 -> -53.83 | L11: ='IS Intergrated'!L41 -> 47.013799 | M11: ='IS Intergrated'!M41 -> 183.61732 | N11: ='IS Intergrated'!N41 -> 369.12219 | O11: ='IS Intergrated'!O41 -> 805.5295 | P11: ='IS Intergrated'!P41 -> 1385.9942 | Q11: ='IS Intergrated'!Q41 -> 2004.8774
B12: Depreciation & Amortization | E12: ='CF Historical'!D12 -> 97.398 | F12: ='CF Historical'!E12 -> 92.848 | G12: ='CF Historical'!F12 -> 51.739 | H12: ='CF Historical'!G12 -> 60.923 | I12: ='CF Historical'!H12 -> 78.738 | J12: ='CF Historical'!I12 -> 92.375 | K12: ='CF Historical'!J12 -> 140.668 | L12: ='IS Intergrated'!L18 -> 139.14995 | M12: ='IS Intergrated'!M18 -> 147.09922 | N12: ='IS Intergrated'!N18 -> 156.50649 | O12: ='IS Intergrated'!O18 -> 166.30225 | P12: ='IS Intergrated'!P18 -> 99.556197 | Q12: ='IS Intergrated'!Q18 -> 80.690798
B13: Deferred Taxes | E13: ='CF Historical'!D13 -> 0 | F13: ='CF Historical'!E13 -> 0 | G13: ='CF Historical'!F13 -> 0 | H13: ='CF Historical'!G13 -> 0 | I13: ='CF Historical'!H13 -> 0.119 | J13: ='CF Historical'!I13 -> 4.05 | K13: ='CF Historical'!J13 -> -23.08 | L13: =-('BS Intergrated'!L34-'BS Intergrated'!K34)+('BS Intergrated'!L57-'BS Intergrated'!K57) -> 0 | M13: =-('BS Intergrated'!M34-'BS Intergrated'!L34)+('BS Intergrated'!M57-'BS Intergrated'!L57) -> 0 | N13: =-('BS Intergrated'!N34-'BS Intergrated'!M34)+('BS Intergrated'!N57-'BS Intergrated'!M57) -> 0 | O13: =-('BS Intergrated'!O34-'BS Intergrated'!N34)+('BS Intergrated'!O57-'BS Intergrated'!N57) -> 0 | P13: =-('BS Intergrated'!P34-'BS Intergrated'!O34)+('BS Intergrated'!P57-'BS Intergrated'!O57) -> 0 | Q13: =-('BS Intergrated'!Q34-'BS Intergrated'!P34)+('BS Intergrated'!Q57-'BS Intergrated'!P57) -> 0
B14: Other Funds | E14: ='CF Historical'!D14 -> 673.752 | F14: ='CF Historical'!E14 -> 1091.688 | G14: ='CF Historical'!F14 -> 1035.578 | H14: ='CF Historical'!G14 -> 985.393 | I14: ='CF Historical'!H14 -> 1092.832 | J14: ='CF Historical'!I14 -> 1355.846 | K14: ='CF Historical'!J14 -> 1665.37 | L14: ='CF Assumptions'!F38 -> 1780.6478 | M14: ='CF Assumptions'!G38 -> 2110.8476 | N14: ='CF Assumptions'!H38 -> 2491.149 | O14: ='CF Assumptions'!I38 -> 2869.8171 | P14: ='CF Assumptions'!J38 -> 3170.4552 | Q14: ='CF Assumptions'!K38 -> 3411.3416 | R14: Stock based compensation
B16: Funds from Operations | E16: =SUM(E11:E14) -> 420.496 | F16: =SUM(F11:F14) -> 488.221 | G16: =SUM(G11:G14) -> 473.193 | H16: =SUM(H11:H14) -> 559.555 | I16: =SUM(I11:I14) -> 871.17 | J16: =SUM(J11:J14) -> 1195.584 | K16: =SUM(K11:K14) -> 1729.128 | L16: =SUM(L11:L14) -> 1966.8116 | ... Q16: =SUM(Q11:Q14) -> 5496.9098
B18: Changes in Working Capital | E18: =SUM(E19:E25) -> 143.019 | F18: =SUM(F19:F25) -> 233.502 | G18: =SUM(G19:G25) -> 253.237 | H18: =SUM(H19:H25) -> 308.556 | I18: =SUM(I19:I25) -> 576.989 | J18: =SUM(J19:J25) -> 264.809 | K18: =SUM(K19:K25) -> -375.999 | L18: =SUM(L19:L25) -> 413.03206 | ... Q18: =SUM(Q19:Q25) -> 437.97892
B19: Receivables | E19: ='CF Historical'!D19 -> -29.44 | F19: ='CF Historical'!E19 -> -61.256 | G19: ='CF Historical'!F19 -> -134.764 | H19: ='CF Historical'!G19 -> -169.526 | I19: ='CF Historical'!H19 -> -148.469 | J19: ='CF Historical'!I19 -> -150.035 | K19: ='CF Historical'!J19 -> -484.465 | L19: ='BS Intergrated'!K13-'BS Intergrated'!L13 -> 164.04688 | M19: ='BS Intergrated'!L13-'BS Intergrated'!M13 -> -233.43369 | N19: ='BS Intergrated'!M13-'BS Intergrated'!N13 -> -276.24821 | O19: ='BS Intergrated'!N13-'BS Intergrated'!O13 -> -287.65647 | P19: ='BS Intergrated'!O13-'BS Intergrated'!P13 -> -248.01885 | Q19: ='BS Intergrated'!P13-'BS Intergrated'!Q13 -> -218.26142
B20: Other Accruals | E20: ='CF Historical'!D20 -> 0 | F20: ='CF Historical'!E20 -> 0 | G20: ='CF Historical'!F20 -> 93.25 | H20: ='CF Historical'!G20 -> 74.611 | I20: ='CF Historical'!H20 -> 158.123 | J20: ='CF Historical'!I20 -> 90.988 | K20: ='CF Historical'!J20 -> 69.077 | L20: ='BS Intergrated'!L52-'BS Intergrated'!K52 -> -40.968094 | M20: ='BS Intergrated'!M52-'BS Intergrated'!L52 -> 131.27558 | N20: ='BS Intergrated'!N52-'BS Intergrated'!M52 -> 150.43536 | O20: ='BS Intergrated'!O52-'BS Intergrated'!N52 -> 117.99431 | P20: ='BS Intergrated'!P52-'BS Intergrated'!O52 -> 77.429446 | Q20: ='BS Intergrated'!Q52-'BS Intergrated'!P52 -> 45.874177
B21: Accounts Payable | E21: ='CF Historical'!D21 -> 51.532 | F21: ='CF Historical'!E21 -> 10.441 | G21: ='CF Historical'!F21 -> 31.741 | H21: ='CF Historical'!G21 -> 78.902 | I21: ='CF Historical'!H21 -> 18.15 | J21: ='CF Historical'!I21 -> 42.873 | K21: ='CF Historical'!J21 -> 41.907 | L21: ='BS Intergrated'!L47-'BS Intergrated'!K47 -> 41.611463 | M21: ='BS Intergrated'!M47-'BS Intergrated'!L47 -> 64.214937 | N21: ='BS Intergrated'!N47-'BS Intergrated'!M47 -> 75.992722 | O21: ='BS Intergrated'!O47-'BS Intergrated'!N47 -> 79.131002 | P21: ='BS Intergrated'!P47-'BS Intergrated'!O47 -> 68.227148 | Q21: ='BS Intergrated'!Q47-'BS Intergrated'!P47 -> 60.041219
B22: Prepaid Expenses | E22: ='CF Historical'!D22 -> -10.608 | F22: ='CF Historical'!E22 -> -10.054 | G22: ='CF Historical'!F22 -> -21.927 | H22: ='CF Historical'!G22 -> -38.23 | I22: ='CF Historical'!H22 -> -3.122 | J22: ='CF Historical'!I22 -> -85.385 | K22: ='CF Historical'!J22 -> -155.832 | L22: =-('BS Intergrated'!L16-'BS Intergrated'!K16) -> -42.956925 | M22: =-('BS Intergrated'!M16-'BS Intergrated'!L16) -> -59.979945 | N22: =-('BS Intergrated'!N16-'BS Intergrated'!M16) -> -68.734069 | O22: =-('BS Intergrated'!O16-'BS Intergrated'!N16) -> -53.911719 | P22: =-('BS Intergrated'!P16-'BS Intergrated'!O16) -> -35.377592 | Q22: =-('BS Intergrated'!Q16-'BS Intergrated'!P16) -> -20.959958
B23: Deferred Revenue | E23: 131.535 | F23: 294.371 | G23: 284.937 | H23: 362.799 | I23: 552.307 | J23: 366.368 | K23: 153.314 | L23: =('BS Intergrated'!L50+'BS Intergrated'!L56)-('BS Intergrated'!K50+'BS Intergrated'!K56) -> 337.09085 | M23: =('BS Intergrated'!M50+'BS Intergrated'!M56)-('BS Intergrated'!L50+'BS Intergrated'!L56) -> 632.98367 | N23: =('BS Intergrated'!N50+'BS Intergrated'!N56)-('BS Intergrated'!M50+'BS Intergrated'!M56) -> 749.08043 | O23: =('BS Intergrated'!O50+'BS Intergrated'!O56)-('BS Intergrated'!N50+'BS Intergrated'!N56) -> 780.01529 | P23: =('BS Intergrated'!P50+'BS Intergrated'!P56)-('BS Intergrated'!O50+'BS Intergrated'!O56) -> 672.53311 | Q23: =('BS Intergrated'!Q50+'BS Intergrated'!Q56)-('BS Intergrated'!P50+'BS Intergrated'!P56) -> 591.84223
B24: Other Non-Current Assets | E24: - | F24: - | G24: - | H24: - | I24: - | J24: - | K24: - | L24: =-('BS Intergrated'!L38-'BS Intergrated'!K38) -> -55.989991 | M24: =-('BS Intergrated'!M38-'BS Intergrated'!L38) -> -44.285482 | N24: =-('BS Intergrated'!N38-'BS Intergrated'!M38) -> -52.407968 | O24: =-('BS Intergrated'!O38-'BS Intergrated'!N38) -> -54.572266 | P24: =-('BS Intergrated'!P38-'BS Intergrated'!O38) -> -47.052482 | Q24: =-('BS Intergrated'!Q38-'BS Intergrated'!P38) -> -41.407101
B25: Other Non-Current Liabilities | E25: - | F25: - | G25: - | H25: - | I25: - | J25: - | K25: - | L25: =('BS Intergrated'!L61-'BS Intergrated'!K61) -> 10.197873 | M25: =('BS Intergrated'!M61-'BS Intergrated'!L61) -> 22.299126 | N25: =('BS Intergrated'!N61-'BS Intergrated'!M61) -> 26.389051 | O25: =('BS Intergrated'!O61-'BS Intergrated'!N61) -> 27.478843 | P25: =('BS Intergrated'!P61-'BS Intergrated'!O61) -> 23.692397 | Q25: =('BS Intergrated'!Q61-'BS Intergrated'!P61) -> 20.849771 | R25: (Δmisc. Current assets + Δ deferred charges + Δtangible other assets) + (Δincome tax payable + Δmisc. Current liab. + Δprovisions for R&C + Δother liab. Exlc DI)
B27: Net Operating Cash Flow | E27: =SUM(E16,E18) -> 563.515 | F27: =SUM(F16,F18) -> 721.723 | G27: =SUM(G16,G18) -> 726.43 | H27: =SUM(H16,H18) -> 868.111 | I27: =SUM(I16,I18) -> 1448.159 | J27: =SUM(J16,J18) -> 1460.393 | K27: =SUM(K16,K18) -> 1353.129 | L27: =SUM(L16,L18) -> 2379.8436 | ... Q27: =SUM(Q16,Q18) -> 5934.8887
B29: Investing Activities
B30: Capital Expenditures | E30: ='CF Historical'!D28 -> -35.709 | F30: ='CF Historical'!E28 -> -33.32 | G30: ='CF Historical'!F28 -> -74.601 | H30: ='CF Historical'!G28 -> -25.812 | I30: ='CF Historical'!H28 -> -33.112 | J30: ='CF Historical'!I28 -> -44.85 | K30: ='CF Historical'!J28 -> -34.06 | L30: =-('BS Intergrated'!L21-'BS Intergrated'!K21) -> -58.709653 | M30: =-('BS Intergrated'!M21-'BS Intergrated'!L21) -> -63.621208 | N30: =-('BS Intergrated'!N21-'BS Intergrated'!M21) -> -75.290096 | O30: =-('BS Intergrated'!O21-'BS Intergrated'!N21) -> -78.39936 | P30: =-('BS Intergrated'!P21-'BS Intergrated'!O21) -> -67.596322 | Q30: =-('BS Intergrated'!Q21-'BS Intergrated'!P21) -> -59.486081
B31: Net Assets from Acquisitions | E31: ='CF Historical'!D29 -> -53.972 | F31: ='CF Historical'!E29 -> -91.769 | G31: ='CF Historical'!F29 -> -19.411 | H31: ='CF Historical'!G29 -> -5.775 | I31: ='CF Historical'!H29 -> -847.767 | J31: ='CF Historical'!I29 -> -14.245 | K31: ='CF Historical'!J29 -> -1228.875 | L31: =-('BS Assumptions'!E199*'IS Intergrated'!L10) -> -489.80612 | M31: =-('BS Assumptions'!F199*'IS Intergrated'!M10) -> -684.51429 | N31: =-('BS Assumptions'!G199*'IS Intergrated'!N10) -> -935.85598 | O31: =-('BS Assumptions'!H199*'IS Intergrated'!O10) -> -1232.2548 | P31: =-('BS Assumptions'!I199*'IS Intergrated'!P10) -> -1539.5141 | Q31: =-('BS Assumptions'!J199*'IS Intergrated'!Q10) -> -1857.2704
B32: Purchase/Sale of Investments | E32: ='CF Historical'!D30 -> -229.25 | F32: ='CF Historical'!E30 -> 381.733 | G32: ='CF Historical'!F30 -> 130.528 | H32: ='CF Historical'!G30 -> 30.329 | I32: ='CF Historical'!H30 -> -82.867 | J32: ='CF Historical'!I30 -> -283.227 | K32: ='CF Historical'!J30 -> 456.042 | L32: ='Additional Assumptions'!F19 -> 0 | M32: ='Additional Assumptions'!G19 -> 0 | N32: ='Additional Assumptions'!H19 -> 0 | O32: ='Additional Assumptions'!I19 -> 0 | P32: ='Additional Assumptions'!J19 -> 0 | Q32: ='Additional Assumptions'!K19 -> 0 | R32: Can't forecast purchase/sale investments
B34: Net Investing Cash Flow | E34: =SUM(E30:E32) -> -318.931 | F34: =SUM(F30:F32) -> 256.644 | G34: =SUM(G30:G32) -> 36.516 | H34: =SUM(H30:H32) -> -1.258 | I34: =SUM(I30:I32) -> -963.746 | J34: =SUM(J30:J32) -> -342.322 | K34: =SUM(K30:K32) -> -806.893 | L34: =SUM(L30:L32) -> -548.51577 | ... Q34: =SUM(Q30:Q32) -> -1916.7565
B36: Financing Activities
B37: Change In Capital Stock | E37: ='CF Historical'!D35 -> 1.802 | F37: ='CF Historical'!E35 -> 1.163 | G37: ='CF Historical'!F35 -> 0 | H37: ='CF Historical'!G35 -> -150.006 | I37: ='CF Historical'!H35 -> -395.256 | J37: ='CF Historical'!I35 -> -779.439 | K37: ='CF Historical'!J35 -> -1800.485 | L37: ='CF Assumptions'!F18 -> -1780.6478 | M37: ='CF Assumptions'!G18 -> -2110.8476 | N37: ='CF Assumptions'!H18 -> -2491.149 | O37: ='CF Assumptions'!I18 -> -2869.8171 | P37: ='CF Assumptions'!J18 -> -3170.4552 | Q37: ='CF Assumptions'!K18 -> -3411.3416
B38: Issuance/Reduction of Debt, Net | E38: ='CF Historical'!D36 -> -0.002 | F38: ='CF Historical'!E36 -> -1803.244 | G38: ='CF Historical'!F36 -> -548.686 | H38: ='CF Historical'!G36 -> 0 | I38: ='CF Historical'!H36 -> -12.961 | J38: ='CF Historical'!I36 -> 0 | K38: ='CF Historical'!J36 -> 0.222 | L38: 0 | M38: 0 | N38: 0 | O38: 0 | P38: 0 | Q38: 0
B39: Change in Current Debt | E39: ='CF Historical'!D37 -> -0.002 | F39: ='CF Historical'!E37 -> -1803.244 | G39: ='CF Historical'!F37 -> 0 | H39: ='CF Historical'!G37 -> 0 | I39: ='CF Historical'!H37 -> 0 | J39: ='CF Historical'!I37 -> 0 | K39: ='CF Historical'!J37 -> -1.654 | L39: 0 | M39: 0 | N39: 0 | O39: 0 | P39: 0 | Q39: 0
B40: Change in Long-Term Debt | E40: ='CF Historical'!D38 -> 0 | F40: ='CF Historical'!E38 -> 0 | G40: ='CF Historical'!F38 -> -548.686 | H40: ='CF Historical'!G38 -> 0 | I40: ='CF Historical'!H38 -> -12.961 | J40: ='CF Historical'!I38 -> 0 | K40: ='CF Historical'!J38 -> 1.876 | L40: 0 | M40: 0 | N40: 0 | O40: 0 | P40: 0 | Q40: 0
B41: Issuance of Long-Term Debt | E41: ='CF Historical'!D39 -> 0 | F41: ='CF Historical'!E39 -> 0 | G41: ='CF Historical'!F39 -> 1000 | H41: ='CF Historical'!G39 -> 0 | I41: ='CF Historical'!H39 -> 987.039 | J41: ='CF Historical'!I39 -> 0 | K41: ='CF Historical'!J39 -> 1.876 | L41: 0 | M41: 0 | N41: 0 | O41: 0 | P41: 0 | Q41: 0
B42: Reduction in Long-Term Debt | E42: ='CF Historical'!D40 -> 0 | F42: ='CF Historical'!E40 -> 0 | G42: ='CF Historical'!F40 -> -1548.686 | H42: ='CF Historical'!G40 -> 0 | I42: ='CF Historical'!H40 -> -1000 | J42: ='CF Historical'!I40 -> 0 | K42: ='CF Historical'!J40 -> 0 | L42: 0 | M42: 0 | N42: 0 | O42: ='BS Assumptions'!I214-'BS Assumptions'!H214 -> 0 | P42: ='BS Assumptions'!J214-'BS Assumptions'!I214 -> 0 | Q42: ='BS Assumptions'!K214-'BS Assumptions'!J214 -> 0
B43: Repayments of Operating Lease Liabilities | E43: -38.125 | F43: -44.874
B44: Other Funds | E44: 0 | F44: 203.093 | G44: 149.406 | H44: 1.585 | I44: 0 | J44: -3.143 | K44: 0
B45: Exchange Rate Effect | E45: -1.18 | F45: 5.41 | G45: -9.19 | H45: -1.81 | I45: -1.99 | J45: 0.15 | K45: -10.233
B47: Net Financing Cash Flow | E47: =E37+E38+E43+E44 -> -36.325 | F47: =F37+F38+F43+F44 -> -1643.862 | G47: =G37+G38+G43+G44 -> -399.28 | H47: =H37+H38+H43+H44 -> -148.421 | I47: =I37+I38+I43+I44 -> -408.217 | J47: =J37+J38+J43+J44 -> -782.582 | K47: =K37+K38+K43+K44 -> -1800.263 | L47: =L37+L38+L43 -> -1780.6478 | M47: =M37+M38+M43 -> -2110.8476 | N47: =N37+N38+N43 -> -2491.149 | O47: =O37+O38+O43 -> -2869.8171 | P47: =P37+P38+P43 -> -3170.4552 | Q47: =Q37+Q38+Q43 -> -3411.3416
B49: Net Change in Cash | E49: =SUM(E27,E34,E47,E45) -> 207.079 | F49: =SUM(F27,F34,F47,F45) -> -660.085 | G49: =SUM(G27,G34,G47,G45) -> 354.476 | H49: =SUM(H27,H34,H47,H45) -> 716.622 | I49: =SUM(I27,I34,I47,I45) -> 74.206 | J49: =SUM(J27,J34,J47,J45) -> 335.639 | K49: =SUM(K27,K34,K47,K45) -> -1264.26 | L49: =SUM(L27,L34,L47,L44) -> 50.68004 | M49: =SUM(M27,M34,M47,M44) -> 95.655241 | N49: =SUM(N27,N34,N47,N44) -> 118.98991 | O49: =SUM(O27,O34,O47,O44) -> 269.65657 | P49: =SUM(P27,P34,P47,P44) -> 389.87313 | Q49: =SUM(Q27,Q34,Q47,Q44) -> 606.79066
B51: Total Cash | L51: ='BS Intergrated'!K11+'CF Intergrated'!L49 -> 1290.192 | M51: ='BS Intergrated'!L11+'CF Intergrated'!M49 -> 1385.8473 | N51: ='BS Intergrated'!M11+'CF Intergrated'!N49 -> 1504.8372 | O51: ='BS Intergrated'!N11+'CF Intergrated'!O49 -> 1774.4938 | P51: ='BS Intergrated'!O11+'CF Intergrated'!P49 -> 2164.3669 | Q51: ='BS Intergrated'!P11+'CF Intergrated'!Q49 -> 2771.1576
B53: Free Cash Flow | E53: =E27+E30 -> 527.806 | F53: =F27+F30 -> 688.403 | G53: =G27+G30 -> 651.829 | H53: =H27+H30 -> 842.299 | I53: =I27+I30 -> 1415.047 | J53: =J27+J30 -> 1415.543 | K53: =K27+K30 -> 1319.069 | L53: =L27+L30 -> 2321.134 | ... Q53: =Q27+Q30 -> 5875.4027

Sheet IS Assumption
A1: IS Assumptions
A2: NASDAQ: TEAM
A3: Currently Running | B3: =Cover!E5 -> Base Case
E5: 45809 | F5: 46174 | G5: 46539 | H5: 46905 | I5: 47270 | J5: 47635 | K5: 48000 | L5: 48366
E6: Actual | F6: Actual | G6: Forecast | H6: Forecast | I6: Forecast | J6: Forecast | K6: Forecast | L6: Forecast
F8: 2026 FORECASTS ARE NOT ANCHORED
F9: COGS (Excl. D&A)/Revenue
D10: Selected Case | F10: =_xlfn.XLOOKUP($B$3,$D$12:$D$16,F12:F16) -> 0.158406 | G10: =_xlfn.XLOOKUP($B$3,$D$12:$D$16,G12:G16) -> 0.158406 | H10: =_xlfn.XLOOKUP($B$3,$D$12:$D$16,H12:H16) -> 0.163406 | I10: =_xlfn.XLOOKUP($B$3,$D$12:$D$16,I12:I16) -> 0.168406 | J10: =_xlfn.XLOOKUP($B$3,$D$12:$D$16,J12:J16) -> 0.173406 | K10: =_xlfn.XLOOKUP($B$3,$D$12:$D$16,K12:K16) -> 0.178406 | L10: =_xlfn.XLOOKUP($B$3,$D$12:$D$16,L12:L16) -> 0.183406
D12: Pessimistic Case 2 | F12: {=AVERAGE(LARGE('IS Ratio'!$E$12:$K$12,_xlfn.SEQUENCE(2)))} -> 0.16536771 | G12: =F12 -> 0.16536771 | H12: =G12+0.005 -> 0.17036771 | I12: =H12+0.005 -> 0.17536771 | J12: =I12+0.005 -> 0.18036771 | K12: =J12+0.005 -> 0.18536771 | L12: =K12+0.005 -> 0.19036771
D13: Pessimistic Case 1 | F13: {=AVERAGE(LARGE('IS Ratio'!$E$12:$K$12,_xlfn.SEQUENCE(3)))} -> 0.16240656 | G13: =F13 -> 0.16240656 | H13: =G13+0.005 -> 0.16740656 | I13: =H13+0.005 -> 0.17240656 | J13: =I13+0.005 -> 0.17740656 | K13: =J13+0.005 -> 0.18240656 | L13: =K13+0.005 -> 0.18740656
D14: Base Case | F14: {=AVERAGE(LARGE('IS Ratio'!$E$12:$K$12,_xlfn.SEQUENCE(4)))} -> 0.158406 | G14: =F14 -> 0.158406 | H14: =G14+0.005 -> 0.163406 | I14: =H14+0.005 -> 0.168406 | J14: =I14+0.005 -> 0.173406 | K14: =J14+0.005 -> 0.178406 | L14: =K14+0.005 -> 0.183406
D15: Optimistic Case 1 | F15: {=AVERAGE(LARGE('IS Ratio'!$E$12:$K$12,_xlfn.SEQUENCE(5)))} -> 0.15277842 | G15: =F15 -> 0.15277842 | H15: =G15+0.005 -> 0.15777842 | I15: =H15+0.005 -> 0.16277842 | J15: =I15+0.005 -> 0.16777842 | K15: =J15+0.005 -> 0.17277842 | L15: =K15+0.005 -> 0.17777842
D16: Optimistic Case 2 | F16: {=AVERAGE(LARGE('IS Ratio'!$E$12:$K$12,_xlfn.SEQUENCE(6)))} -> 0.1475677 | G16: =F16 -> 0.1475677 | H16: =G16+0.005 -> 0.1525677 | I16: =H16+0.005 -> 0.1575677 | J16: =I16+0.005 -> 0.1625677 | K16: =J16+0.005 -> 0.1675677 | L16: =K16+0.005 -> 0.1725677
F19: Depreciation/PPE
D20: Selected Case | F20: =_xlfn.XLOOKUP($B$3,$D$12:$D$16,F22:F26) -> 0.1249469 | G20: =_xlfn.XLOOKUP($B$3,$D$12:$D$16,G22:G26) -> 0.1249469 | H20: =_xlfn.XLOOKUP($B$3,$D$12:$D$16,H22:H26) -> 0.1249469 | I20: =_xlfn.XLOOKUP($B$3,$D$12:$D$16,I22:I26) -> 0.1249469 | J20: =_xlfn.XLOOKUP($B$3,$D$12:$D$16,J22:J26) -> 0.1249469 | K20: =_xlfn.XLOOKUP($B$3,$D$12:$D$16,K22:K26) -> 0.1249469 | L20: =_xlfn.XLOOKUP($B$3,$D$12:$D$16,L22:L26) -> 0.1249469
D22: Pessimistic Case 2 | F22: {=AVERAGE(SMALL('IS Ratio'!$E$13:$K$13,_xlfn.SEQUENCE(5)))} -> 0.1249469 | G22: {=AVERAGE(SMALL('IS Ratio'!$E$13:$K$13,_xlfn.SEQUENCE(5)))} -> 0.1249469 | H22: {=AVERAGE(SMALL('IS Ratio'!$E$13:$K$13,_xlfn.SEQUENCE(5)))} -> 0.1249469 | I22: {=AVERAGE(SMALL('IS Ratio'!$E$13:$K$13,_xlfn.SEQUENCE(5)))} -> 0.1249469 | J22: {=AVERAGE(SMALL('IS Ratio'!$E$13:$K$13,_xlfn.SEQUENCE(5)))} -> 0.1249469 | K22: {=AVERAGE(SMALL('IS Ratio'!$E$13:$K$13,_xlfn.SEQUENCE(5)))} -> 0.1249469 | L22: {=AVERAGE(SMALL('IS Ratio'!$E$13:$K$13,_xlfn.SEQUENCE(5)))} -> 0.1249469
D23: Pessimistic Case 1 | F23: {=AVERAGE(SMALL('IS Ratio'!$E$13:$K$13,_xlfn.SEQUENCE(5)))} -> 0.1249469 | G23: {=AVERAGE(SMALL('IS Ratio'!$E$13:$K$13,_xlfn.SEQUENCE(5)))} -> 0.1249469 | H23: {=AVERAGE(SMALL('IS Ratio'!$E$13:$K$13,_xlfn.SEQUENCE(5)))} -> 0.1249469 | I23: {=AVERAGE(SMALL('IS Ratio'!$E$13:$K$13,_xlfn.SEQUENCE(5)))} -> 0.1249469 | J23: {=AVERAGE(SMALL('IS Ratio'!$E$13:$K$13,_xlfn.SEQUENCE(5)))} -> 0.1249469 | K23: {=AVERAGE(SMALL('IS Ratio'!$E$13:$K$13,_xlfn.SEQUENCE(5)))} -> 0.1249469 | L23: {=AVERAGE(SMALL('IS Ratio'!$E$13:$K$13,_xlfn.SEQUENCE(5)))} -> 0.1249469
D24: Base Case | F24: {=AVERAGE(SMALL('IS Ratio'!$E$13:$K$13,_xlfn.SEQUENCE(5)))} -> 0.1249469 | G24: {=AVERAGE(SMALL('IS Ratio'!$E$13:$K$13,_xlfn.SEQUENCE(5)))} -> 0.1249469 | H24: {=AVERAGE(SMALL('IS Ratio'!$E$13:$K$13,_xlfn.SEQUENCE(5)))} -> 0.1249469 | I24: {=AVERAGE(SMALL('IS Ratio'!$E$13:$K$13,_xlfn.SEQUENCE(5)))} -> 0.1249469 | J24: {=AVERAGE(SMALL('IS Ratio'!$E$13:$K$13,_xlfn.SEQUENCE(5)))} -> 0.1249469 | K24: {=AVERAGE(SMALL('IS Ratio'!$E$13:$K$13,_xlfn.SEQUENCE(5)))} -> 0.1249469 | L24: {=AVERAGE(SMALL('IS Ratio'!$E$13:$K$13,_xlfn.SEQUENCE(5)))} -> 0.1249469
D25: Optimistic Case 1 | F25: {=AVERAGE(SMALL('IS Ratio'!$E$13:$K$13,_xlfn.SEQUENCE(5)))} -> 0.1249469 | G25: {=AVERAGE(SMALL('IS Ratio'!$E$13:$K$13,_xlfn.SEQUENCE(5)))} -> 0.1249469 | H25: {=AVERAGE(SMALL('IS Ratio'!$E$13:$K$13,_xlfn.SEQUENCE(5)))} -> 0.1249469 | I25: {=AVERAGE(SMALL('IS Ratio'!$E$13:$K$13,_xlfn.SEQUENCE(5)))} -> 0.1249469 | J25: {=AVERAGE(SMALL('IS Ratio'!$E$13:$K$13,_xlfn.SEQUENCE(5)))} -> 0.1249469 | K25: {=AVERAGE(SMALL('IS Ratio'!$E$13:$K$13,_xlfn.SEQUENCE(5)))} -> 0.1249469 | L25: {=AVERAGE(SMALL('IS Ratio'!$E$13:$K$13,_xlfn.SEQUENCE(5)))} -> 0.1249469
D26: Optimistic Case 2 | F26: {=AVERAGE(SMALL('IS Ratio'!$E$13:$K$13,_xlfn.SEQUENCE(5)))} -> 0.1249469 | G26: {=AVERAGE(SMALL('IS Ratio'!$E$13:$K$13,_xlfn.SEQUENCE(5)))} -> 0.1249469 | H26: {=AVERAGE(SMALL('IS Ratio'!$E$13:$K$13,_xlfn.SEQUENCE(5)))} -> 0.1249469 | I26: {=AVERAGE(SMALL('IS Ratio'!$E$13:$K$13,_xlfn.SEQUENCE(5)))} -> 0.1249469 | J26: {=AVERAGE(SMALL('IS Ratio'!$E$13:$K$13,_xlfn.SEQUENCE(5)))} -> 0.1249469 | K26: {=AVERAGE(SMALL('IS Ratio'!$E$13:$K$13,_xlfn.SEQUENCE(5)))} -> 0.1249469 | L26: {=AVERAGE(SMALL('IS Ratio'!$E$13:$K$13,_xlfn.SEQUENCE(5)))} -> 0.1249469
F29: Acquired Intangibles Useful Life (Years)
D30: Selected Case | F30: =_xlfn.XLOOKUP($B$3,$D$12:$D$16,F32:F36) -> 4 | G30: =_xlfn.XLOOKUP($B$3,$D$12:$D$16,G32:G36) -> 4 | H30: =_xlfn.XLOOKUP($B$3,$D$12:$D$16,H32:H36) -> 4 | I30: =_xlfn.XLOOKUP($B$3,$D$12:$D$16,I32:I36) -> 4 | J30: =_xlfn.XLOOKUP($B$3,$D$12:$D$16,J32:J36) -> 4 | K30: =_xlfn.XLOOKUP($B$3,$D$12:$D$16,K32:K36) -> 4 | L30: =_xlfn.XLOOKUP($B$3,$D$12:$D$16,L32:L36) -> 4
D32: Pessimistic Case 2 | F32: 4 | G32: 4 | H32: 4 | I32: 4 | J32: 4 | K32: 4 | L32: 4
D33: Pessimistic Case 1 | F33: 4 | G33: 4 | H33: 4 | I33: 4 | J33: 4 | K33: 4 | L33: 4
D34: Base Case | F34: 4 | G34: 4 | H34: 4 | I34: 4 | J34: 4 | K34: 4 | L34: 4
D35: Optimistic Case 1 | F35: 4 | G35: 4 | H35: 4 | I35: 4 | J35: 4 | K35: 4 | L35: 4
D36: Optimistic Case 2 | F36: 4 | G36: 4 | H36: 4 | I36: 4 | J36: 4 | K36: 4 | L36: 4
F39: R&D Expense/Revenue
D40: Selected Case | F40: =_xlfn.XLOOKUP($B$3,$D$12:$D$16,F42:F46) -> 0.49598656 | G40: =_xlfn.XLOOKUP($B$3,$D$12:$D$16,G42:G46) -> 0.46260265 | H40: =_xlfn.XLOOKUP($B$3,$D$12:$D$16,H42:H46) -> 0.43760265 | I40: =_xlfn.XLOOKUP($B$3,$D$12:$D$16,I42:I46) -> 0.41260265 | J40: =_xlfn.XLOOKUP($B$3,$D$12:$D$16,J42:J46) -> 0.38760265 | K40: =_xlfn.XLOOKUP($B$3,$D$12:$D$16,K42:K46) -> 0.36260265 | L40: =_xlfn.XLOOKUP($B$3,$D$12:$D$16,L42:L46) -> 0.33760265
D42: Pessimistic Case 2 | F42: {=AVERAGE(LARGE('IS Ratio'!$E$15:$K$15,_xlfn.SEQUENCE(4)))} -> 0.51013987 | G42: =G43 -> 0.46260265 | H42: =G42-0.025 -> 0.43760265 | I42: =H42-0.025 -> 0.41260265 | J42: =I42-0.025 -> 0.38760265 | K42: =J42-0.025 -> 0.36260265 | L42: =K42-0.025 -> 0.33760265
D43: Pessimistic Case 1 | F43: {=AVERAGE(LARGE('IS Ratio'!$E$15:$K$15,_xlfn.SEQUENCE(6)))} -> 0.50179881 | G43: =G44 -> 0.46260265 | H43: =G43-0.025 -> 0.43760265 | I43: =H43-0.025 -> 0.41260265 | J43: =I43-0.025 -> 0.38760265 | K43: =J43-0.025 -> 0.36260265 | L43: =K43-0.025 -> 0.33760265
D44: Base Case | F44: ='IS Ratio'!$C$15 -> 0.49598656 | G44: ='Additional Assumptions'!O25 -> 0.46260265 | H44: =G44-0.025 -> 0.43760265 | I44: =H44-0.025 -> 0.41260265 | J44: =I44-0.025 -> 0.38760265 | K44: =J44-0.025 -> 0.36260265 | L44: =K44-0.025 -> 0.33760265
D45: Optimistic Case 1 | F45: {=AVERAGE(SMALL('IS Ratio'!$E$15:$K$15,_xlfn.SEQUENCE(2)))} -> 0.46695869 | G45: ='Additional Assumptions'!O25-0.02 -> 0.44260265 | H45: =G45-0.025 -> 0.41760265 | I45: =H45-0.025 -> 0.39260265 | J45: =I45-0.025 -> 0.36760265 | K45: =J45-0.025 -> 0.34260265 | L45: =K45-0.025 -> 0.31760265
D46: Optimistic Case 2 | F46: {=AVERAGE(SMALL('IS Ratio'!$E$15:$K$15,_xlfn.SEQUENCE(1)))} -> 0.46111304 | G46: =G45-0.02 -> 0.42260265 | H46: =G46-0.025 -> 0.39760265 | I46: =H46-0.025 -> 0.37260265 | J46: =I46-0.025 -> 0.34760265 | K46: =J46-0.025 -> 0.32260265 | L46: =K46-0.025 -> 0.29760265
F49: M&S Expense
D50: Selected Case | F50: =_xlfn.XLOOKUP($B$3,$D$12:$D$16,F52:F56) -> 0.23449571 | G50: =_xlfn.XLOOKUP($B$3,$D$12:$D$16,G52:G56) -> 0.24449571 | H50: =_xlfn.XLOOKUP($B$3,$D$12:$D$16,H52:H56) -> 0.25449571 | I50: =_xlfn.XLOOKUP($B$3,$D$12:$D$16,I52:I56) -> 0.24449571 | J50: =_xlfn.XLOOKUP($B$3,$D$12:$D$16,J52:J56) -> 0.23449571 | K50: =_xlfn.XLOOKUP($B$3,$D$12:$D$16,K52:K56) -> 0.22449571 | L50: =_xlfn.XLOOKUP($B$3,$D$12:$D$16,L52:L56) -> 0.21449571
D52: Pessimistic Case 2 | F52: =F53+0.01 -> 0.25449571 | G52: =G53 -> 0.25449571 | H52: =G52+0.01 -> 0.26449571 | I52: =H52-0.01 -> 0.25449571 | J52: =I52-0.01 -> 0.24449571 | K52: =J52-0.01 -> 0.23449571 | L52: =K52-0.01 -> 0.22449571
D53: Pessimistic Case 1 | F53: =F54+0.01 -> 0.24449571 | G53: =F53+0.01 -> 0.25449571 | H53: =G53+0.01 -> 0.26449571 | I53: =H53-0.01 -> 0.25449571 | J53: =I53-0.01 -> 0.24449571 | K53: =J53-0.01 -> 0.23449571 | L53: =K53-0.01 -> 0.22449571
D54: Base Case | F54: {=AVERAGE(LARGE('IS Ratio'!$E$16:$K$16,_xlfn.SEQUENCE(1)))} -> 0.23449571 | G54: {=AVERAGE(LARGE('IS Ratio'!$E$16:$K$16,_xlfn.SEQUENCE(1)))+0.01} -> 0.24449571 | H54: =G54+0.01 -> 0.25449571 | I54: =H54-0.01 -> 0.24449571 | J54: =I54-0.01 -> 0.23449571 | K54: =J54-0.01 -> 0.22449571 | L54: =K54-0.01 -> 0.21449571
D55: Optimistic Case 1 | F55: ='IS Ratio'!$C$16 -> 0.20540855 | G55: {=AVERAGE(LARGE('IS Ratio'!$E$16:$K$16,_xlfn.SEQUENCE(1)))} -> 0.23449571 | H55: =G55+0.01 -> 0.24449571 | I55: =H55-0.01 -> 0.23449571 | J55: =I55-0.01 -> 0.22449571 | K55: =J55-0.01 -> 0.21449571 | L55: =K55-0.01 -> 0.20449571
D56: Optimistic Case 2 | F56: {=AVERAGE(SMALL('IS Ratio'!$E$16:$K$16,_xlfn.SEQUENCE(2)))} -> 0.1820784 | G56: =G55-0.01 -> 0.22449571 | H56: =G56+0.01 -> 0.23449571 | I56: =H56-0.01 -> 0.22449571 | J56: =I56-0.01 -> 0.21449571 | K56: =J56-0.01 -> 0.20449571 | L56: =K56-0.01 -> 0.19449571
F59: G&A Expense/Revenue
D60: Selected Case | F60: =_xlfn.XLOOKUP($B$3,$D$12:$D$16,F62:F66) -> 0.11944302 | G60: =_xlfn.XLOOKUP($B$3,$D$12:$D$16,G62:G66) -> 0.11444302 | H60: =_xlfn.XLOOKUP($B$3,$D$12:$D$16,H62:H66) -> 0.10944302 | I60: =_xlfn.XLOOKUP($B$3,$D$12:$D$16,I62:I66) -> 0.10444302 | J60: =_xlfn.XLOOKUP($B$3,$D$12:$D$16,J62:J66) -> 0.09944302 | K60: =_xlfn.XLOOKUP($B$3,$D$12:$D$16,K62:K66) -> 0.09444302 | L60: =_xlfn.XLOOKUP($B$3,$D$12:$D$16,L62:L66) -> 0.08944302
D62: Pessimistic Case 2 | F62: {=AVERAGE(SMALL('IS Ratio'!$E$17:$K$17,_xlfn.SEQUENCE(3)))} -> 0.12632384 | G62: =F62-0.005 -> 0.12132384 | H62: =G62-0.005 -> 0.11632384 | I62: =H62-0.005 -> 0.11132384 | J62: =I62-0.005 -> 0.10632384 | K62: =J62-0.005 -> 0.10132384 | L62: =K62-0.005 -> 0.096323841
D63: Pessimistic Case 1 | F63: {=AVERAGE(SMALL('IS Ratio'!$E$17:$K$17,_xlfn.SEQUENCE(3)))} -> 0.12632384 | G63: =F63-0.005 -> 0.12132384 | H63: =G63-0.005 -> 0.11632384 | I63: =H63-0.005 -> 0.11132384 | J63: =I63-0.005 -> 0.10632384 | K63: =J63-0.005 -> 0.10132384 | L63: =K63-0.005 -> 0.096323841
D64: Base Case | F64: {=AVERAGE(SMALL('IS Ratio'!$E$17:$K$17,_xlfn.SEQUENCE(2)))} -> 0.11944302 | G64: =F64-0.005 -> 0.11444302 | H64: =G64-0.005 -> 0.10944302 | I64: =H64-0.005 -> 0.10444302 | J64: =I64-0.005 -> 0.09944302 | K64: =J64-0.005 -> 0.09444302 | L64: =K64-0.005 -> 0.08944302
D65: Optimistic Case 1 | F65: {=AVERAGE(SMALL('IS Ratio'!$E$17:$K$17,_xlfn.SEQUENCE(1)))} -> 0.11482846 | G65: =F65-0.005 -> 0.10982846 | H65: =G65-0.005 -> 0.10482846 | I65: =H65-0.005 -> 0.099828459 | J65: =I65-0.005 -> 0.094828459 | K65: =J65-0.005 -> 0.089828459 | L65: =K65-0.005 -> 0.084828459
D66: Optimistic Case 2 | F66: =F65-0.005 -> 0.10982846 | G66: =F66-0.005 -> 0.10482846 | H66: =G66-0.005 -> 0.099828459 | I66: =H66-0.005 -> 0.094828459 | J66: =I66-0.005 -> 0.089828459 | K66: =J66-0.005 -> 0.084828459 | L66: =K66-0.005 -> 0.079828459
F69: Non-Operating Interest Income/Cash
D70: Selected Case | F70: =_xlfn.XLOOKUP($B$3,$D$12:$D$16,F72:F76) -> 0.056239875 | G70: =_xlfn.XLOOKUP($B$3,$D$12:$D$16,G72:G76) -> 0.056239875 | H70: =_xlfn.XLOOKUP($B$3,$D$12:$D$16,H72:H76) -> 0.056239875 | I70: =_xlfn.XLOOKUP($B$3,$D$12:$D$16,I72:I76) -> 0.056239875 | J70: =_xlfn.XLOOKUP($B$3,$D$12:$D$16,J72:J76) -> 0.056239875 | K70: =_xlfn.XLOOKUP($B$3,$D$12:$D$16,K72:K76) -> 0.056239875 | L70: =_xlfn.XLOOKUP($B$3,$D$12:$D$16,L72:L76) -> 0.056239875
D72: Pessimistic Case 2 | F72: {=AVERAGE(LARGE('IS Ratio'!$E$19:$K$19,_xlfn.SEQUENCE(4)))} -> 0.039838015 | G72: {=AVERAGE(LARGE('IS Ratio'!$E$19:$K$19,_xlfn.SEQUENCE(4)))} -> 0.039838015 | H72: {=AVERAGE(LARGE('IS Ratio'!$E$19:$K$19,_xlfn.SEQUENCE(4)))} -> 0.039838015 | I72: {=AVERAGE(LARGE('IS Ratio'!$E$19:$K$19,_xlfn.SEQUENCE(4)))} -> 0.039838015 | J72: {=AVERAGE(LARGE('IS Ratio'!$E$19:$K$19,_xlfn.SEQUENCE(4)))} -> 0.039838015 | K72: {=AVERAGE(LARGE('IS Ratio'!$E$19:$K$19,_xlfn.SEQUENCE(4)))} -> 0.039838015 | L72: {=AVERAGE(LARGE('IS Ratio'!$E$19:$K$19,_xlfn.SEQUENCE(4)))} -> 0.039838015
D73: Pessimistic Case 1 | F73: {=AVERAGE(LARGE('IS Ratio'!$E$19:$K$19,_xlfn.SEQUENCE(3)))} -> 0.045270281 | G73: {=AVERAGE(LARGE('IS Ratio'!$E$19:$K$19,_xlfn.SEQUENCE(2)))} -> 0.048784112 | H73: {=AVERAGE(LARGE('IS Ratio'!$E$19:$K$19,_xlfn.SEQUENCE(2)))} -> 0.048784112 | I73: {=AVERAGE(LARGE('IS Ratio'!$E$19:$K$19,_xlfn.SEQUENCE(2)))} -> 0.048784112 | J73: {=AVERAGE(LARGE('IS Ratio'!$E$19:$K$19,_xlfn.SEQUENCE(2)))} -> 0.048784112 | K73: {=AVERAGE(LARGE('IS Ratio'!$E$19:$K$19,_xlfn.SEQUENCE(2)))} -> 0.048784112 | L73: {=AVERAGE(LARGE('IS Ratio'!$E$19:$K$19,_xlfn.SEQUENCE(2)))} -> 0.048784112
D74: Base Case | F74: {=AVERAGE(LARGE('IS Ratio'!$E$19:$K$19,_xlfn.SEQUENCE(1)))} -> 0.056239875 | G74: {=AVERAGE(LARGE('IS Ratio'!$E$19:$K$19,_xlfn.SEQUENCE(1)))} -> 0.056239875 | H74: {=AVERAGE(LARGE('IS Ratio'!$E$19:$K$19,_xlfn.SEQUENCE(1)))} -> 0.056239875 | I74: {=AVERAGE(LARGE('IS Ratio'!$E$19:$K$19,_xlfn.SEQUENCE(1)))} -> 0.056239875 | J74: {=AVERAGE(LARGE('IS Ratio'!$E$19:$K$19,_xlfn.SEQUENCE(1)))} -> 0.056239875 | K74: {=AVERAGE(LARGE('IS Ratio'!$E$19:$K$19,_xlfn.SEQUENCE(1)))} -> 0.056239875 | L74: {=AVERAGE(LARGE('IS Ratio'!$E$19:$K$19,_xlfn.SEQUENCE(1)))} -> 0.056239875
D75: Optimistic Case 1 | F75: {=AVERAGE(LARGE('IS Ratio'!$E$19:$K$19,_xlfn.SEQUENCE(1)))} -> 0.056239875 | G75: {=AVERAGE(LARGE('IS Ratio'!$E$19:$K$19,_xlfn.SEQUENCE(1)))} -> 0.056239875 | H75: {=AVERAGE(LARGE('IS Ratio'!$E$19:$K$19,_xlfn.SEQUENCE(1)))} -> 0.056239875 | I75: {=AVERAGE(LARGE('IS Ratio'!$E$19:$K$19,_xlfn.SEQUENCE(1)))} -> 0.056239875 | J75: {=AVERAGE(LARGE('IS Ratio'!$E$19:$K$19,_xlfn.SEQUENCE(1)))} -> 0.056239875 | K75: {=AVERAGE(LARGE('IS Ratio'!$E$19:$K$19,_xlfn.SEQUENCE(1)))} -> 0.056239875 | L75: {=AVERAGE(LARGE('IS Ratio'!$E$19:$K$19,_xlfn.SEQUENCE(1)))} -> 0.056239875
D76: Optimistic Case 2 | F76: {=AVERAGE(LARGE('IS Ratio'!$E$19:$K$19,_xlfn.SEQUENCE(1)))} -> 0.056239875 | G76: {=AVERAGE(LARGE('IS Ratio'!$E$19:$K$19,_xlfn.SEQUENCE(1)))} -> 0.056239875 | H76: {=AVERAGE(LARGE('IS Ratio'!$E$19:$K$19,_xlfn.SEQUENCE(1)))} -> 0.056239875 | I76: {=AVERAGE(LARGE('IS Ratio'!$E$19:$K$19,_xlfn.SEQUENCE(1)))} -> 0.056239875 | J76: {=AVERAGE(LARGE('IS Ratio'!$E$19:$K$19,_xlfn.SEQUENCE(1)))} -> 0.056239875 | K76: {=AVERAGE(LARGE('IS Ratio'!$E$19:$K$19,_xlfn.SEQUENCE(1)))} -> 0.056239875 | L76: {=AVERAGE(LARGE('IS Ratio'!$E$19:$K$19,_xlfn.SEQUENCE(1)))} -> 0.056239875
F79: Other Income (Expense) Ex-Outlier/Revenue
D80: Selected Case | F80: =_xlfn.XLOOKUP($B$3,$D$12:$D$16,F82:F86) -> -0.0018031952 | G80: =_xlfn.XLOOKUP($B$3,$D$12:$D$16,G82:G86) -> -0.0018031952 | H80: =_xlfn.XLOOKUP($B$3,$D$12:$D$16,H82:H86) -> -0.0018031952 | I80: =_xlfn.XLOOKUP($B$3,$D$12:$D$16,I82:I86) -> -0.0018031952 | J80: =_xlfn.XLOOKUP($B$3,$D$12:$D$16,J82:J86) -> -0.0018031952 | K80: =_xlfn.XLOOKUP($B$3,$D$12:$D$16,K82:K86) -> -0.0018031952 | L80: =_xlfn.XLOOKUP($B$3,$D$12:$D$16,L82:L86) -> -0.0018031952
D82: Pessimistic Case 2 | F82: =F83-0.0005 -> -0.0028031952 | G82: =G83-0.0005 -> -0.0028031952 | H82: =H83-0.0005 -> -0.0028031952 | I82: =I83-0.0005 -> -0.0028031952 | J82: =J83-0.0005 -> -0.0028031952 | K82: =K83-0.0005 -> -0.0028031952 | L82: =L83-0.0005 -> -0.0028031952
D83: Pessimistic Case 1 | F83: =F84-0.0005 -> -0.0023031952 | G83: =G84-0.0005 -> -0.0023031952 | H83: =H84-0.0005 -> -0.0023031952 | I83: =I84-0.0005 -> -0.0023031952 | J83: =J84-0.0005 -> -0.0023031952 | K83: =K84-0.0005 -> -0.0023031952 | L83: =L84-0.0005 -> -0.0023031952
D84: Base Case | F84: =F85-0.0005 -> -0.0018031952 | G84: =G85-0.0005 -> -0.0018031952 | H84: =H85-0.0005 -> -0.0018031952 | I84: =I85-0.0005 -> -0.0018031952 | J84: =J85-0.0005 -> -0.0018031952 | K84: =K85-0.0005 -> -0.0018031952 | L84: =L85-0.0005 -> -0.0018031952
D85: Optimistic Case 1 | F85: {=AVERAGE(LARGE('IS Ratio'!$E$20:$K$20,_xlfn.SEQUENCE(1)))} -> -0.0013031952 | G85: {=AVERAGE(LARGE('IS Ratio'!$E$20:$K$20,_xlfn.SEQUENCE(1)))} -> -0.0013031952 | H85: {=AVERAGE(LARGE('IS Ratio'!$E$20:$K$20,_xlfn.SEQUENCE(1)))} -> -0.0013031952 | I85: {=AVERAGE(LARGE('IS Ratio'!$E$20:$K$20,_xlfn.SEQUENCE(1)))} -> -0.0013031952 | J85: {=AVERAGE(LARGE('IS Ratio'!$E$20:$K$20,_xlfn.SEQUENCE(1)))} -> -0.0013031952 | K85: {=AVERAGE(LARGE('IS Ratio'!$E$20:$K$20,_xlfn.SEQUENCE(1)))} -> -0.0013031952 | L85: {=AVERAGE(LARGE('IS Ratio'!$E$20:$K$20,_xlfn.SEQUENCE(1)))} -> -0.0013031952
D86: Optimistic Case 2 | F86: {=AVERAGE(LARGE('IS Ratio'!$E$20:$K$20,_xlfn.SEQUENCE(1)))} -> -0.0013031952 | G86: {=AVERAGE(LARGE('IS Ratio'!$E$20:$K$20,_xlfn.SEQUENCE(1)))} -> -0.0013031952 | H86: {=AVERAGE(LARGE('IS Ratio'!$E$20:$K$20,_xlfn.SEQUENCE(1)))} -> -0.0013031952 | I86: {=AVERAGE(LARGE('IS Ratio'!$E$20:$K$20,_xlfn.SEQUENCE(1)))} -> -0.0013031952 | J86: {=AVERAGE(LARGE('IS Ratio'!$E$20:$K$20,_xlfn.SEQUENCE(1)))} -> -0.0013031952 | K86: {=AVERAGE(LARGE('IS Ratio'!$E$20:$K$20,_xlfn.SEQUENCE(1)))} -> -0.0013031952 | L86: {=AVERAGE(LARGE('IS Ratio'!$E$20:$K$20,_xlfn.SEQUENCE(1)))} -> -0.0013031952
F89: Basic Shares Outstanding
D90: Selected Case | F90: =_xlfn.XLOOKUP($B$3,$D$12:$D$16,F92:F96) -> 260.16 | G90: =_xlfn.XLOOKUP($B$3,$D$12:$D$16,G92:G96) -> 260.16 | H90: =_xlfn.XLOOKUP($B$3,$D$12:$D$16,H92:H96) -> 260.16 | I90: =_xlfn.XLOOKUP($B$3,$D$12:$D$16,I92:I96) -> 260.16 | J90: =_xlfn.XLOOKUP($B$3,$D$12:$D$16,J92:J96) -> 260.16 | K90: =_xlfn.XLOOKUP($B$3,$D$12:$D$16,K92:K96) -> 260.16 | L90: =_xlfn.XLOOKUP($B$3,$D$12:$D$16,L92:L96) -> 260.16
D92: Pessimistic Case 2 | F92: ='IS Historical'!$K$43 -> 260.16 | G92: ='IS Historical'!$K$43 -> 260.16 | H92: ='IS Historical'!$K$43 -> 260.16 | I92: ='IS Historical'!$K$43 -> 260.16 | J92: ='IS Historical'!$K$43 -> 260.16 | K92: ='IS Historical'!$K$43 -> 260.16 | L92: ='IS Historical'!$K$43 -> 260.16
D93: Pessimistic Case 1 | F93: ='IS Historical'!$K$43 -> 260.16 | G93: ='IS Historical'!$K$43 -> 260.16 | H93: ='IS Historical'!$K$43 -> 260.16 | I93: ='IS Historical'!$K$43 -> 260.16 | J93: ='IS Historical'!$K$43 -> 260.16 | K93: ='IS Historical'!$K$43 -> 260.16 | L93: ='IS Historical'!$K$43 -> 260.16
D94: Base Case | F94: ='IS Historical'!$K$43 -> 260.16 | G94: ='IS Historical'!$K$43 -> 260.16 | H94: ='IS Historical'!$K$43 -> 260.16 | I94: ='IS Historical'!$K$43 -> 260.16 | J94: ='IS Historical'!$K$43 -> 260.16 | K94: ='IS Historical'!$K$43 -> 260.16 | L94: ='IS Historical'!$K$43 -> 260.16
D95: Optimistic Case 1 | F95: ='IS Historical'!$K$43 -> 260.16 | G95: ='IS Historical'!$K$43 -> 260.16 | H95: ='IS Historical'!$K$43 -> 260.16 | I95: ='IS Historical'!$K$43 -> 260.16 | J95: ='IS Historical'!$K$43 -> 260.16 | K95: ='IS Historical'!$K$43 -> 260.16 | L95: ='IS Historical'!$K$43 -> 260.16
D96: Optimistic Case 2 | F96: ='IS Historical'!$K$43 -> 260.16 | G96: ='IS Historical'!$K$43 -> 260.16 | H96: ='IS Historical'!$K$43 -> 260.16 | I96: ='IS Historical'!$K$43 -> 260.16 | J96: ='IS Historical'!$K$43 -> 260.16 | K96: ='IS Historical'!$K$43 -> 260.16 | L96: ='IS Historical'!$K$43 -> 260.16
F98: Diluted Shares Outstanding
D99: Selected Case | F99: =_xlfn.XLOOKUP($B$3,$D$12:$D$16,F101:F105) -> 260.16 | G99: =_xlfn.XLOOKUP($B$3,$D$12:$D$16,G101:G105) -> 260.16 | H99: =_xlfn.XLOOKUP($B$3,$D$12:$D$16,H101:H105) -> 260.16 | I99: =_xlfn.XLOOKUP($B$3,$D$12:$D$16,I101:I105) -> 260.16 | J99: =_xlfn.XLOOKUP($B$3,$D$12:$D$16,J101:J105) -> 260.16 | K99: =_xlfn.XLOOKUP($B$3,$D$12:$D$16,K101:K105) -> 260.16 | L99: =_xlfn.XLOOKUP($B$3,$D$12:$D$16,L101:L105) -> 260.16
D101: Pessimistic Case 2 | F101: ='IS Historical'!$K$45 -> 260.16 | G101: ='IS Historical'!$K$45 -> 260.16 | H101: ='IS Historical'!$K$45 -> 260.16 | I101: ='IS Historical'!$K$45 -> 260.16 | J101: ='IS Historical'!$K$45 -> 260.16 | K101: ='IS Historical'!$K$45 -> 260.16 | L101: ='IS Historical'!$K$45 -> 260.16
D102: Pessimistic Case 1 | F102: ='IS Historical'!$K$45 -> 260.16 | G102: ='IS Historical'!$K$45 -> 260.16 | H102: ='IS Historical'!$K$45 -> 260.16 | I102: ='IS Historical'!$K$45 -> 260.16 | J102: ='IS Historical'!$K$45 -> 260.16 | K102: ='IS Historical'!$K$45 -> 260.16 | L102: ='IS Historical'!$K$45 -> 260.16
D103: Base Case | F103: ='IS Historical'!$K$45 -> 260.16 | G103: ='IS Historical'!$K$45 -> 260.16 | H103: ='IS Historical'!$K$45 -> 260.16 | I103: ='IS Historical'!$K$45 -> 260.16 | J103: ='IS Historical'!$K$45 -> 260.16 | K103: ='IS Historical'!$K$45 -> 260.16 | L103: ='IS Historical'!$K$45 -> 260.16
D104: Optimistic Case 1 | F104: ='IS Historical'!$K$45 -> 260.16 | G104: ='IS Historical'!$K$45 -> 260.16 | H104: ='IS Historical'!$K$45 -> 260.16 | I104: ='IS Historical'!$K$45 -> 260.16 | J104: ='IS Historical'!$K$45 -> 260.16 | K104: ='IS Historical'!$K$45 -> 260.16 | L104: ='IS Historical'!$K$45 -> 260.16
D105: Optimistic Case 2 | F105: ='IS Historical'!$K$45 -> 260.16 | G105: ='IS Historical'!$K$45 -> 260.16 | H105: ='IS Historical'!$K$45 -> 260.16 | I105: ='IS Historical'!$K$45 -> 260.16 | J105: ='IS Historical'!$K$45 -> 260.16 | K105: ='IS Historical'!$K$45 -> 260.16 | L105: ='IS Historical'!$K$45 -> 260.16

Sheet BS Assumptions
A1: BS Assumptions
A2: NASDAQ: TEAM
A3: Currently Running | B3: =Cover!E5 -> Base Case
D4: 46174 | E4: 46539 | F4: 46905 | G4: 47270 | H4: 47635 | I4: 48000 | J4: 48366
D5: Actual | E5: Forecast | F5: Forecast | G5: Forecast | H5: Forecast | I5: Forecast | J5: Forecast | K5: N/A
E8: Trade Receivables (Excl. Upfront Recognition) /Revenue
C9: Selected Case | E9: {=_xlfn.XLOOKUP($B$3,$C$11:$C$15,E11:K15)} -> 0.14666418 | F9: 0.14666418 | G9: 0.14666418 | H9: 0.14666418 | I9: 0.14666418 | J9: 0.14666418 | K9: 0.14666418
C11: Pessimistic Case 2 | E11: {=AVERAGE(SMALL('BS Ratios'!$E$6:$K$6,_xlfn.SEQUENCE(4)))} -> 0.099376729 | F11: {=AVERAGE(SMALL('BS Ratios'!$E$6:$K$6,_xlfn.SEQUENCE(4)))} -> 0.099376729 | G11: {=AVERAGE(SMALL('BS Ratios'!$E$6:$K$6,_xlfn.SEQUENCE(4)))} -> 0.099376729 | H11: {=AVERAGE(SMALL('BS Ratios'!$E$6:$K$6,_xlfn.SEQUENCE(4)))} -> 0.099376729 | I11: {=AVERAGE(SMALL('BS Ratios'!$E$6:$K$6,_xlfn.SEQUENCE(4)))} -> 0.099376729 | J11: {=AVERAGE(SMALL('BS Ratios'!$E$6:$K$6,_xlfn.SEQUENCE(4)))} -> 0.099376729 | K11: {=AVERAGE(SMALL('BS Ratios'!$E$6:$K$6,_xlfn.SEQUENCE(4)))} -> 0.099376729
C12: Pessimistic Case 1 | E12: ='BS Ratios'!$C$6 -> 0.11513921 | F12: ='BS Ratios'!$C$6 -> 0.11513921 | G12: ='BS Ratios'!$C$6 -> 0.11513921 | H12: ='BS Ratios'!$C$6 -> 0.11513921 | I12: ='BS Ratios'!$C$6 -> 0.11513921 | J12: ='BS Ratios'!$C$6 -> 0.11513921 | K12: ='BS Ratios'!$C$6 -> 0.11513921
C13: Base Case | E13: {=AVERAGE(LARGE('BS Ratios'!$E$6:$K$6,_xlfn.SEQUENCE(2)))} -> 0.14666418 | F13: {=AVERAGE(LARGE('BS Ratios'!$E$6:$K$6,_xlfn.SEQUENCE(2)))} -> 0.14666418 | G13: {=AVERAGE(LARGE('BS Ratios'!$E$6:$K$6,_xlfn.SEQUENCE(2)))} -> 0.14666418 | H13: {=AVERAGE(LARGE('BS Ratios'!$E$6:$K$6,_xlfn.SEQUENCE(2)))} -> 0.14666418 | I13: {=AVERAGE(LARGE('BS Ratios'!$E$6:$K$6,_xlfn.SEQUENCE(2)))} -> 0.14666418 | J13: {=AVERAGE(LARGE('BS Ratios'!$E$6:$K$6,_xlfn.SEQUENCE(2)))} -> 0.14666418 | K13: {=AVERAGE(LARGE('BS Ratios'!$E$6:$K$6,_xlfn.SEQUENCE(2)))} -> 0.14666418
C14: Optimistic Case 1 | E14: {=AVERAGE(LARGE('BS Ratios'!$E$6:$K$6,_xlfn.SEQUENCE(1)))} -> 0.14923425 | F14: {=AVERAGE(LARGE('BS Ratios'!$E$6:$K$6,_xlfn.SEQUENCE(1)))} -> 0.14923425 | G14: {=AVERAGE(LARGE('BS Ratios'!$E$6:$K$6,_xlfn.SEQUENCE(1)))} -> 0.14923425 | H14: {=AVERAGE(LARGE('BS Ratios'!$E$6:$K$6,_xlfn.SEQUENCE(1)))} -> 0.14923425 | I14: {=AVERAGE(LARGE('BS Ratios'!$E$6:$K$6,_xlfn.SEQUENCE(1)))} -> 0.14923425 | J14: {=AVERAGE(LARGE('BS Ratios'!$E$6:$K$6,_xlfn.SEQUENCE(1)))} -> 0.14923425 | K14: {=AVERAGE(LARGE('BS Ratios'!$E$6:$K$6,_xlfn.SEQUENCE(1)))} -> 0.14923425
C15: Optimistic Case 2 | E15: =E14+0.005 -> 0.15423425 | F15: =F14+0.005 -> 0.15423425 | G15: =G14+0.005 -> 0.15423425 | H15: =H14+0.005 -> 0.15423425 | I15: =I14+0.005 -> 0.15423425 | J15: =J14+0.005 -> 0.15423425 | K15: =K14+0.005 -> 0.15423425
E18: Prepaid & Other Current Assets / OpEx
C19: Selected Case | E19: {=_xlfn.XLOOKUP($B$3,$C$11:$C$15,E21:K25)} -> 0.053698107 | F19: 0.053698107 | G19: 0.053698107 | H19: 0.053698107 | I19: 0.053698107 | J19: 0.053698107 | K19: 0.053698107
C21: Pessimistic Case 2 | E21: {=AVERAGE(SMALL('BS Ratios'!$E$7:$K$7,_xlfn.SEQUENCE(2)))} -> 0.03243456 | F21: {=AVERAGE(SMALL('BS Ratios'!$E$7:$K$7,_xlfn.SEQUENCE(2)))} -> 0.03243456 | G21: {=AVERAGE(SMALL('BS Ratios'!$E$7:$K$7,_xlfn.SEQUENCE(2)))} -> 0.03243456 | H21: {=AVERAGE(SMALL('BS Ratios'!$E$7:$K$7,_xlfn.SEQUENCE(2)))} -> 0.03243456 | I21: {=AVERAGE(SMALL('BS Ratios'!$E$7:$K$7,_xlfn.SEQUENCE(2)))} -> 0.03243456 | J21: {=AVERAGE(SMALL('BS Ratios'!$E$7:$K$7,_xlfn.SEQUENCE(2)))} -> 0.03243456 | K21: {=AVERAGE(SMALL('BS Ratios'!$E$7:$K$7,_xlfn.SEQUENCE(2)))} -> 0.03243456
C22: Pessimistic Case 1 | E22: ='BS Ratios'!$C$7 -> 0.043601357 | F22: ='BS Ratios'!$C$7 -> 0.043601357 | G22: ='BS Ratios'!$C$7 -> 0.043601357 | H22: ='BS Ratios'!$C$7 -> 0.043601357 | I22: ='BS Ratios'!$C$7 -> 0.043601357 | J22: ='BS Ratios'!$C$7 -> 0.043601357 | K22: ='BS Ratios'!$C$7 -> 0.043601357
C23: Base Case | E23: {=AVERAGE(LARGE('BS Ratios'!$E$7:$K$7,_xlfn.SEQUENCE(2)))} -> 0.053698107 | F23: {=AVERAGE(LARGE('BS Ratios'!$E$7:$K$7,_xlfn.SEQUENCE(2)))} -> 0.053698107 | G23: {=AVERAGE(LARGE('BS Ratios'!$E$7:$K$7,_xlfn.SEQUENCE(2)))} -> 0.053698107 | H23: {=AVERAGE(LARGE('BS Ratios'!$E$7:$K$7,_xlfn.SEQUENCE(2)))} -> 0.053698107 | I23: {=AVERAGE(LARGE('BS Ratios'!$E$7:$K$7,_xlfn.SEQUENCE(2)))} -> 0.053698107 | J23: {=AVERAGE(LARGE('BS Ratios'!$E$7:$K$7,_xlfn.SEQUENCE(2)))} -> 0.053698107 | K23: {=AVERAGE(LARGE('BS Ratios'!$E$7:$K$7,_xlfn.SEQUENCE(2)))} -> 0.053698107
C24: Optimistic Case 1 | E24: {=AVERAGE(LARGE('BS Ratios'!$E$7:$K$7,_xlfn.SEQUENCE(1)))} -> 0.055705892 | F24: {=AVERAGE(LARGE('BS Ratios'!$E$7:$K$7,_xlfn.SEQUENCE(1)))} -> 0.055705892 | G24: {=AVERAGE(LARGE('BS Ratios'!$E$7:$K$7,_xlfn.SEQUENCE(1)))} -> 0.055705892 | H24: {=AVERAGE(LARGE('BS Ratios'!$E$7:$K$7,_xlfn.SEQUENCE(1)))} -> 0.055705892 | I24: {=AVERAGE(LARGE('BS Ratios'!$E$7:$K$7,_xlfn.SEQUENCE(1)))} -> 0.055705892 | J24: {=AVERAGE(LARGE('BS Ratios'!$E$7:$K$7,_xlfn.SEQUENCE(1)))} -> 0.055705892 | K24: {=AVERAGE(LARGE('BS Ratios'!$E$7:$K$7,_xlfn.SEQUENCE(1)))} -> 0.055705892
C25: Optimistic Case 2 | E25: =E24+0.005 -> 0.060705892 | F25: =F24+0.005 -> 0.060705892 | G25: =G24+0.005 -> 0.060705892 | H25: =H24+0.005 -> 0.060705892 | I25: =I24+0.005 -> 0.060705892 | J25: =J24+0.005 -> 0.060705892 | K25: =K24+0.005 -> 0.060705892
E28: Machinery & Equipment
C29: Selected Case | E29: {=_xlfn.XLOOKUP($B$3,$C$11:$C$15,E31:K35)} -> 0.004744322 | F29: 0.004744322 | G29: 0.004744322 | H29: 0.004744322 | I29: 0.004744322 | J29: 0.004744322 | K29: 0.004744322
C31: Pessimistic Case 2 | E31: {=AVERAGE(SMALL('BS Ratios'!$E$9:$K$9,_xlfn.SEQUENCE(6)))} -> 0.0031344697 | F31: {=AVERAGE(SMALL('BS Ratios'!$E$9:$K$9,_xlfn.SEQUENCE(6)))} -> 0.0031344697 | G31: {=AVERAGE(SMALL('BS Ratios'!$E$9:$K$9,_xlfn.SEQUENCE(6)))} -> 0.0031344697 | H31: {=AVERAGE(SMALL('BS Ratios'!$E$9:$K$9,_xlfn.SEQUENCE(6)))} -> 0.0031344697 | I31: {=AVERAGE(SMALL('BS Ratios'!$E$9:$K$9,_xlfn.SEQUENCE(6)))} -> 0.0031344697 | J31: {=AVERAGE(SMALL('BS Ratios'!$E$9:$K$9,_xlfn.SEQUENCE(6)))} -> 0.0031344697 | K31: {=AVERAGE(SMALL('BS Ratios'!$E$9:$K$9,_xlfn.SEQUENCE(6)))} -> 0.0031344697
C32: Pessimistic Case 1 | E32: ='BS Ratios'!$C$9 -> 0.0035409073 | F32: ='BS Ratios'!$C$9 -> 0.0035409073 | G32: ='BS Ratios'!$C$9 -> 0.0035409073 | H32: ='BS Ratios'!$C$9 -> 0.0035409073 | I32: ='BS Ratios'!$C$9 -> 0.0035409073 | J32: ='BS Ratios'!$C$9 -> 0.0035409073 | K32: ='BS Ratios'!$C$9 -> 0.0035409073
C33: Base Case | E33: {=AVERAGE(LARGE('BS Ratios'!$E$9:$K$9,_xlfn.SEQUENCE(3)))} -> 0.004744322 | F33: {=AVERAGE(LARGE('BS Ratios'!$E$9:$K$9,_xlfn.SEQUENCE(3)))} -> 0.004744322 | G33: {=AVERAGE(LARGE('BS Ratios'!$E$9:$K$9,_xlfn.SEQUENCE(3)))} -> 0.004744322 | H33: {=AVERAGE(LARGE('BS Ratios'!$E$9:$K$9,_xlfn.SEQUENCE(3)))} -> 0.004744322 | I33: {=AVERAGE(LARGE('BS Ratios'!$E$9:$K$9,_xlfn.SEQUENCE(3)))} -> 0.004744322 | J33: {=AVERAGE(LARGE('BS Ratios'!$E$9:$K$9,_xlfn.SEQUENCE(3)))} -> 0.004744322 | K33: {=AVERAGE(LARGE('BS Ratios'!$E$9:$K$9,_xlfn.SEQUENCE(3)))} -> 0.004744322
C34: Optimistic Case 1 | E34: {=AVERAGE(LARGE('BS Ratios'!$E$9:$K$9,_xlfn.SEQUENCE(2)))} -> 0.0054860183 | F34: {=AVERAGE(LARGE('BS Ratios'!$E$9:$K$9,_xlfn.SEQUENCE(2)))} -> 0.0054860183 | G34: {=AVERAGE(LARGE('BS Ratios'!$E$9:$K$9,_xlfn.SEQUENCE(2)))} -> 0.0054860183 | H34: {=AVERAGE(LARGE('BS Ratios'!$E$9:$K$9,_xlfn.SEQUENCE(2)))} -> 0.0054860183 | I34: {=AVERAGE(LARGE('BS Ratios'!$E$9:$K$9,_xlfn.SEQUENCE(2)))} -> 0.0054860183 | J34: {=AVERAGE(LARGE('BS Ratios'!$E$9:$K$9,_xlfn.SEQUENCE(2)))} -> 0.0054860183 | K34: {=AVERAGE(LARGE('BS Ratios'!$E$9:$K$9,_xlfn.SEQUENCE(2)))} -> 0.0054860183
C35: Optimistic Case 2 | E35: {=AVERAGE(LARGE('BS Ratios'!$E$9:$K$9,_xlfn.SEQUENCE(1)))} -> 0.0059795326 | F35: {=AVERAGE(LARGE('BS Ratios'!$E$9:$K$9,_xlfn.SEQUENCE(1)))} -> 0.0059795326 | G35: {=AVERAGE(LARGE('BS Ratios'!$E$9:$K$9,_xlfn.SEQUENCE(1)))} -> 0.0059795326 | H35: {=AVERAGE(LARGE('BS Ratios'!$E$9:$K$9,_xlfn.SEQUENCE(1)))} -> 0.0059795326 | I35: {=AVERAGE(LARGE('BS Ratios'!$E$9:$K$9,_xlfn.SEQUENCE(1)))} -> 0.0059795326 | J35: {=AVERAGE(LARGE('BS Ratios'!$E$9:$K$9,_xlfn.SEQUENCE(1)))} -> 0.0059795326 | K35: {=AVERAGE(LARGE('BS Ratios'!$E$9:$K$9,_xlfn.SEQUENCE(1)))} -> 0.0059795326
E38: Computer Software & Equipment
C39: Selected Case | E39: {=_xlfn.XLOOKUP($B$3,$C$11:$C$15,E41:K45)} -> 0.011172091 | F39: 0.011172091 | G39: 0.011172091 | H39: 0.011172091 | I39: 0.011172091 | J39: 0.011172091 | K39: 0.011172091
C41: Pessimistic Case 2 | E41: ='BS Ratios'!$K$10 -> 0.011115882 | F41: {=AVERAGE(LARGE('BS Ratios'!$E$10:$K$10,_xlfn.SEQUENCE(2)))} -> 0.011172091 | G41: {=AVERAGE(LARGE('BS Ratios'!$E$10:$K$10,_xlfn.SEQUENCE(2)))} -> 0.011172091 | H41: {=AVERAGE(LARGE('BS Ratios'!$E$10:$K$10,_xlfn.SEQUENCE(2)))} -> 0.011172091 | I41: {=AVERAGE(LARGE('BS Ratios'!$E$10:$K$10,_xlfn.SEQUENCE(2)))} -> 0.011172091 | J41: {=AVERAGE(LARGE('BS Ratios'!$E$10:$K$10,_xlfn.SEQUENCE(2)))} -> 0.011172091 | K41: {=AVERAGE(LARGE('BS Ratios'!$E$10:$K$10,_xlfn.SEQUENCE(2)))} -> 0.011172091
C42: Pessimistic Case 1 | E42: {=AVERAGE(LARGE('BS Ratios'!$E$10:$K$10,_xlfn.SEQUENCE(2)))} -> 0.011172091 | F42: {=AVERAGE(LARGE('BS Ratios'!$E$10:$K$10,_xlfn.SEQUENCE(2)))} -> 0.011172091 | G42: {=AVERAGE(LARGE('BS Ratios'!$E$10:$K$10,_xlfn.SEQUENCE(2)))} -> 0.011172091 | H42: {=AVERAGE(LARGE('BS Ratios'!$E$10:$K$10,_xlfn.SEQUENCE(2)))} -> 0.011172091 | I42: {=AVERAGE(LARGE('BS Ratios'!$E$10:$K$10,_xlfn.SEQUENCE(2)))} -> 0.011172091 | J42: {=AVERAGE(LARGE('BS Ratios'!$E$10:$K$10,_xlfn.SEQUENCE(2)))} -> 0.011172091 | K42: {=AVERAGE(LARGE('BS Ratios'!$E$10:$K$10,_xlfn.SEQUENCE(2)))} -> 0.011172091
C43: Base Case | E43: {=AVERAGE(LARGE('BS Ratios'!$E$10:$K$10,_xlfn.SEQUENCE(2)))} -> 0.011172091 | F43: {=AVERAGE(LARGE('BS Ratios'!$E$10:$K$10,_xlfn.SEQUENCE(2)))} -> 0.011172091 | G43: {=AVERAGE(LARGE('BS Ratios'!$E$10:$K$10,_xlfn.SEQUENCE(2)))} -> 0.011172091 | H43: {=AVERAGE(LARGE('BS Ratios'!$E$10:$K$10,_xlfn.SEQUENCE(2)))} -> 0.011172091 | I43: {=AVERAGE(LARGE('BS Ratios'!$E$10:$K$10,_xlfn.SEQUENCE(2)))} -> 0.011172091 | J43: {=AVERAGE(LARGE('BS Ratios'!$E$10:$K$10,_xlfn.SEQUENCE(2)))} -> 0.011172091 | K43: {=AVERAGE(LARGE('BS Ratios'!$E$10:$K$10,_xlfn.SEQUENCE(2)))} -> 0.011172091
C44: Optimistic Case 1 | E44: {=AVERAGE(LARGE('BS Ratios'!$E$10:$K$10,_xlfn.SEQUENCE(2)))} -> 0.011172091 | F44: {=AVERAGE(LARGE('BS Ratios'!$E$10:$K$10,_xlfn.SEQUENCE(2)))} -> 0.011172091 | G44: {=AVERAGE(LARGE('BS Ratios'!$E$10:$K$10,_xlfn.SEQUENCE(2)))} -> 0.011172091 | H44: {=AVERAGE(LARGE('BS Ratios'!$E$10:$K$10,_xlfn.SEQUENCE(2)))} -> 0.011172091 | I44: {=AVERAGE(LARGE('BS Ratios'!$E$10:$K$10,_xlfn.SEQUENCE(2)))} -> 0.011172091 | J44: {=AVERAGE(LARGE('BS Ratios'!$E$10:$K$10,_xlfn.SEQUENCE(2)))} -> 0.011172091 | K44: {=AVERAGE(LARGE('BS Ratios'!$E$10:$K$10,_xlfn.SEQUENCE(2)))} -> 0.011172091
C45: Optimistic Case 2 | E45: {=AVERAGE(LARGE('BS Ratios'!$E$10:$K$10,_xlfn.SEQUENCE(2)))} -> 0.011172091 | F45: {=AVERAGE(LARGE('BS Ratios'!$E$10:$K$10,_xlfn.SEQUENCE(2)))} -> 0.011172091 | G45: {=AVERAGE(LARGE('BS Ratios'!$E$10:$K$10,_xlfn.SEQUENCE(2)))} -> 0.011172091 | H45: {=AVERAGE(LARGE('BS Ratios'!$E$10:$K$10,_xlfn.SEQUENCE(2)))} -> 0.011172091 | I45: {=AVERAGE(LARGE('BS Ratios'!$E$10:$K$10,_xlfn.SEQUENCE(2)))} -> 0.011172091 | J45: {=AVERAGE(LARGE('BS Ratios'!$E$10:$K$10,_xlfn.SEQUENCE(2)))} -> 0.011172091 | K45: {=AVERAGE(LARGE('BS Ratios'!$E$10:$K$10,_xlfn.SEQUENCE(2)))} -> 0.011172091
E48: Furniture & Fittings
C49: Selected Case | E49: {=_xlfn.XLOOKUP($B$3,$C$11:$C$15,E51:K55)} -> 0.0049450951 | F49: 0.0049450951 | G49: 0.0049450951 | H49: 0.0049450951 | I49: 0.0049450951 | J49: 0.0049450951 | K49: 0.0049450951
C51: Pessimistic Case 2 | E51: {=AVERAGE(SMALL('BS Ratios'!$E$11:$K$11,_xlfn.SEQUENCE(1)))} -> 0.0042248476 | F51: {=AVERAGE(SMALL('BS Ratios'!$E$11:$K$11,_xlfn.SEQUENCE(1)))} -> 0.0042248476 | G51: {=AVERAGE(SMALL('BS Ratios'!$E$11:$K$11,_xlfn.SEQUENCE(1)))} -> 0.0042248476 | H51: {=AVERAGE(SMALL('BS Ratios'!$E$11:$K$11,_xlfn.SEQUENCE(1)))} -> 0.0042248476 | I51: {=AVERAGE(SMALL('BS Ratios'!$E$11:$K$11,_xlfn.SEQUENCE(1)))} -> 0.0042248476 | J51: {=AVERAGE(SMALL('BS Ratios'!$E$11:$K$11,_xlfn.SEQUENCE(1)))} -> 0.0042248476 | K51: {=AVERAGE(SMALL('BS Ratios'!$E$11:$K$11,_xlfn.SEQUENCE(1)))} -> 0.0042248476
C52: Pessimistic Case 1 | E52: {=AVERAGE(SMALL('BS Ratios'!$E$11:$K$11,_xlfn.SEQUENCE(2)))} -> 0.0045300202 | F52: {=AVERAGE(SMALL('BS Ratios'!$E$11:$K$11,_xlfn.SEQUENCE(2)))} -> 0.0045300202 | G52: {=AVERAGE(SMALL('BS Ratios'!$E$11:$K$11,_xlfn.SEQUENCE(2)))} -> 0.0045300202 | H52: {=AVERAGE(SMALL('BS Ratios'!$E$11:$K$11,_xlfn.SEQUENCE(2)))} -> 0.0045300202 | I52: {=AVERAGE(SMALL('BS Ratios'!$E$11:$K$11,_xlfn.SEQUENCE(2)))} -> 0.0045300202 | J52: {=AVERAGE(SMALL('BS Ratios'!$E$11:$K$11,_xlfn.SEQUENCE(2)))} -> 0.0045300202 | K52: {=AVERAGE(SMALL('BS Ratios'!$E$11:$K$11,_xlfn.SEQUENCE(2)))} -> 0.0045300202
C53: Base Case | E53: {=AVERAGE(SMALL('BS Ratios'!$E$11:$K$11,_xlfn.SEQUENCE(3)))} -> 0.0049450951 | F53: {=AVERAGE(SMALL('BS Ratios'!$E$11:$K$11,_xlfn.SEQUENCE(3)))} -> 0.0049450951 | G53: {=AVERAGE(SMALL('BS Ratios'!$E$11:$K$11,_xlfn.SEQUENCE(3)))} -> 0.0049450951 | H53: {=AVERAGE(SMALL('BS Ratios'!$E$11:$K$11,_xlfn.SEQUENCE(3)))} -> 0.0049450951 | I53: {=AVERAGE(SMALL('BS Ratios'!$E$11:$K$11,_xlfn.SEQUENCE(3)))} -> 0.0049450951 | J53: {=AVERAGE(SMALL('BS Ratios'!$E$11:$K$11,_xlfn.SEQUENCE(3)))} -> 0.0049450951 | K53: {=AVERAGE(SMALL('BS Ratios'!$E$11:$K$11,_xlfn.SEQUENCE(3)))} -> 0.0049450951
C54: Optimistic Case 1 | E54: {=AVERAGE(SMALL('BS Ratios'!$E$11:$K$11,_xlfn.SEQUENCE(4)))} -> 0.0054609765 | F54: {=AVERAGE(SMALL('BS Ratios'!$E$11:$K$11,_xlfn.SEQUENCE(4)))} -> 0.0054609765 | G54: {=AVERAGE(SMALL('BS Ratios'!$E$11:$K$11,_xlfn.SEQUENCE(4)))} -> 0.0054609765 | H54: {=AVERAGE(SMALL('BS Ratios'!$E$11:$K$11,_xlfn.SEQUENCE(4)))} -> 0.0054609765 | I54: {=AVERAGE(SMALL('BS Ratios'!$E$11:$K$11,_xlfn.SEQUENCE(4)))} -> 0.0054609765 | J54: {=AVERAGE(SMALL('BS Ratios'!$E$11:$K$11,_xlfn.SEQUENCE(4)))} -> 0.0054609765 | K54: {=AVERAGE(SMALL('BS Ratios'!$E$11:$K$11,_xlfn.SEQUENCE(4)))} -> 0.0054609765
C55: Optimistic Case 2 | E55: ='BS Ratios'!$C$11 -> 0.0075939514 | F55: ='BS Ratios'!$C$11 -> 0.0075939514 | G55: ='BS Ratios'!$C$11 -> 0.0075939514 | H55: ='BS Ratios'!$C$11 -> 0.0075939514 | I55: ='BS Ratios'!$C$11 -> 0.0075939514 | J55: ='BS Ratios'!$C$11 -> 0.0075939514 | K55: ='BS Ratios'!$C$11 -> 0.0075939514
E58: Leasehold Improvements
C59: Selected Case | E59: {=_xlfn.XLOOKUP($B$3,$C$11:$C$15,E61:K65)} -> 0.019111095 | F59: 0.019111095 | G59: 0.019111095 | H59: 0.019111095 | I59: 0.019111095 | J59: 0.019111095 | K59: 0.019111095
C61: Pessimistic Case 2 | E61: {=AVERAGE(SMALL('BS Ratios'!$E$12:$K$12,_xlfn.SEQUENCE(1)))} -> 0.019111095 | F61: {=AVERAGE(SMALL('BS Ratios'!$E$12:$K$12,_xlfn.SEQUENCE(1)))} -> 0.019111095 | G61: {=AVERAGE(SMALL('BS Ratios'!$E$12:$K$12,_xlfn.SEQUENCE(1)))} -> 0.019111095 | H61: {=AVERAGE(SMALL('BS Ratios'!$E$12:$K$12,_xlfn.SEQUENCE(1)))} -> 0.019111095 | I61: {=AVERAGE(SMALL('BS Ratios'!$E$12:$K$12,_xlfn.SEQUENCE(1)))} -> 0.019111095 | J61: {=AVERAGE(SMALL('BS Ratios'!$E$12:$K$12,_xlfn.SEQUENCE(1)))} -> 0.019111095 | K61: {=AVERAGE(SMALL('BS Ratios'!$E$12:$K$12,_xlfn.SEQUENCE(1)))} -> 0.019111095
C62: Pessimistic Case 1 | E62: {=AVERAGE(SMALL('BS Ratios'!$E$12:$K$12,_xlfn.SEQUENCE(1)))} -> 0.019111095 | F62: {=AVERAGE(SMALL('BS Ratios'!$E$12:$K$12,_xlfn.SEQUENCE(1)))} -> 0.019111095 | G62: {=AVERAGE(SMALL('BS Ratios'!$E$12:$K$12,_xlfn.SEQUENCE(1)))} -> 0.019111095 | H62: {=AVERAGE(SMALL('BS Ratios'!$E$12:$K$12,_xlfn.SEQUENCE(1)))} -> 0.019111095 | I62: {=AVERAGE(SMALL('BS Ratios'!$E$12:$K$12,_xlfn.SEQUENCE(1)))} -> 0.019111095 | J62: {=AVERAGE(SMALL('BS Ratios'!$E$12:$K$12,_xlfn.SEQUENCE(1)))} -> 0.019111095 | K62: {=AVERAGE(SMALL('BS Ratios'!$E$12:$K$12,_xlfn.SEQUENCE(1)))} -> 0.019111095
C63: Base Case | E63: {=AVERAGE(SMALL('BS Ratios'!$E$12:$K$12,_xlfn.SEQUENCE(1)))} -> 0.019111095 | F63: {=AVERAGE(SMALL('BS Ratios'!$E$12:$K$12,_xlfn.SEQUENCE(1)))} -> 0.019111095 | G63: {=AVERAGE(SMALL('BS Ratios'!$E$12:$K$12,_xlfn.SEQUENCE(1)))} -> 0.019111095 | H63: {=AVERAGE(SMALL('BS Ratios'!$E$12:$K$12,_xlfn.SEQUENCE(1)))} -> 0.019111095 | I63: {=AVERAGE(SMALL('BS Ratios'!$E$12:$K$12,_xlfn.SEQUENCE(1)))} -> 0.019111095 | J63: {=AVERAGE(SMALL('BS Ratios'!$E$12:$K$12,_xlfn.SEQUENCE(1)))} -> 0.019111095 | K63: {=AVERAGE(SMALL('BS Ratios'!$E$12:$K$12,_xlfn.SEQUENCE(1)))} -> 0.019111095
C64: Optimistic Case 1 | E64: {=AVERAGE(SMALL('BS Ratios'!$E$12:$K$12,_xlfn.SEQUENCE(3)))} -> 0.026769971 | F64: {=AVERAGE(SMALL('BS Ratios'!$E$12:$K$12,_xlfn.SEQUENCE(3)))} -> 0.026769971 | G64: {=AVERAGE(SMALL('BS Ratios'!$E$12:$K$12,_xlfn.SEQUENCE(3)))} -> 0.026769971 | H64: {=AVERAGE(SMALL('BS Ratios'!$E$12:$K$12,_xlfn.SEQUENCE(3)))} -> 0.026769971 | I64: {=AVERAGE(SMALL('BS Ratios'!$E$12:$K$12,_xlfn.SEQUENCE(3)))} -> 0.026769971 | J64: {=AVERAGE(SMALL('BS Ratios'!$E$12:$K$12,_xlfn.SEQUENCE(3)))} -> 0.026769971 | K64: {=AVERAGE(SMALL('BS Ratios'!$E$12:$K$12,_xlfn.SEQUENCE(3)))} -> 0.026769971
C65: Optimistic Case 2 | E65: {=AVERAGE(SMALL('BS Ratios'!$E$12:$K$12,_xlfn.SEQUENCE(4)))} -> 0.028785915 | F65: {=AVERAGE(SMALL('BS Ratios'!$E$12:$K$12,_xlfn.SEQUENCE(4)))} -> 0.028785915 | G65: {=AVERAGE(SMALL('BS Ratios'!$E$12:$K$12,_xlfn.SEQUENCE(4)))} -> 0.028785915 | H65: {=AVERAGE(SMALL('BS Ratios'!$E$12:$K$12,_xlfn.SEQUENCE(4)))} -> 0.028785915 | I65: {=AVERAGE(SMALL('BS Ratios'!$E$12:$K$12,_xlfn.SEQUENCE(4)))} -> 0.028785915 | J65: {=AVERAGE(SMALL('BS Ratios'!$E$12:$K$12,_xlfn.SEQUENCE(4)))} -> 0.028785915 | K65: {=AVERAGE(SMALL('BS Ratios'!$E$12:$K$12,_xlfn.SEQUENCE(4)))} -> 0.028785915
E68: Operating Lease Right-Of-Use Assets/Revenue
C69: Selected Case | E69: {=_xlfn.XLOOKUP($B$3,$C$11:$C$15,E71:K75)} -> 114.059 | F69: 114.059 | G69: 114.059 | H69: 114.059 | I69: 114.059 | J69: 114.059 | K69: 114.059
C71: Pessimistic Case 2 | E71: ='BS Intergrated'!$K$33 -> 114.059 | F71: ='BS Intergrated'!$K$33 -> 114.059 | G71: ='BS Intergrated'!$K$33 -> 114.059 | H71: ='BS Intergrated'!$K$33 -> 114.059 | I71: ='BS Intergrated'!$K$33 -> 114.059 | J71: ='BS Intergrated'!$K$33 -> 114.059 | K71: ='BS Intergrated'!$K$33 -> 114.059
C72: Pessimistic Case 1 | E72: ='BS Intergrated'!$K$33 -> 114.059 | F72: ='BS Intergrated'!$K$33 -> 114.059 | G72: ='BS Intergrated'!$K$33 -> 114.059 | H72: ='BS Intergrated'!$K$33 -> 114.059 | I72: ='BS Intergrated'!$K$33 -> 114.059 | J72: ='BS Intergrated'!$K$33 -> 114.059 | K72: ='BS Intergrated'!$K$33 -> 114.059
C73: Base Case | E73: ='BS Intergrated'!$K$33 -> 114.059 | F73: ='BS Intergrated'!$K$33 -> 114.059 | G73: ='BS Intergrated'!$K$33 -> 114.059 | H73: ='BS Intergrated'!$K$33 -> 114.059 | I73: ='BS Intergrated'!$K$33 -> 114.059 | J73: ='BS Intergrated'!$K$33 -> 114.059 | K73: ='BS Intergrated'!$K$33 -> 114.059
C74: Optimistic Case 1 | E74: ='BS Intergrated'!$K$33 -> 114.059 | F74: ='BS Intergrated'!$K$33 -> 114.059 | G74: ='BS Intergrated'!$K$33 -> 114.059 | H74: ='BS Intergrated'!$K$33 -> 114.059 | I74: ='BS Intergrated'!$K$33 -> 114.059 | J74: ='BS Intergrated'!$K$33 -> 114.059 | K74: ='BS Intergrated'!$K$33 -> 114.059
C75: Optimistic Case 2 | E75: ='BS Intergrated'!$K$33 -> 114.059 | F75: ='BS Intergrated'!$K$33 -> 114.059 | G75: ='BS Intergrated'!$K$33 -> 114.059 | H75: ='BS Intergrated'!$K$33 -> 114.059 | I75: ='BS Intergrated'!$K$33 -> 114.059 | J75: ='BS Intergrated'!$K$33 -> 114.059 | K75: ='BS Intergrated'!$K$33 -> 114.059
E78: Deferred Tax Assets
C79: Selected Case | E79: {=_xlfn.XLOOKUP($B$3,$C$11:$C$15,E81:K85)} -> 4.088 | F79: 4.088 | G79: 4.088 | H79: 4.088 | I79: 4.088 | J79: 4.088 | K79: 4.088
C81: Pessimistic Case 2 | E81: ='BS Intergrated'!$K$34 -> 4.088 | F81: ='BS Intergrated'!$K$34 -> 4.088 | G81: ='BS Intergrated'!$K$34 -> 4.088 | H81: ='BS Intergrated'!$K$34 -> 4.088 | I81: ='BS Intergrated'!$K$34 -> 4.088 | J81: ='BS Intergrated'!$K$34 -> 4.088 | K81: ='BS Intergrated'!$K$34 -> 4.088
C82: Pessimistic Case 1 | E82: ='BS Intergrated'!$K$34 -> 4.088 | F82: ='BS Intergrated'!$K$34 -> 4.088 | G82: ='BS Intergrated'!$K$34 -> 4.088 | H82: ='BS Intergrated'!$K$34 -> 4.088 | I82: ='BS Intergrated'!$K$34 -> 4.088 | J82: ='BS Intergrated'!$K$34 -> 4.088 | K82: ='BS Intergrated'!$K$34 -> 4.088
C83: Base Case | E83: ='BS Intergrated'!$K$34 -> 4.088 | F83: ='BS Intergrated'!$K$34 -> 4.088 | G83: ='BS Intergrated'!$K$34 -> 4.088 | H83: ='BS Intergrated'!$K$34 -> 4.088 | I83: ='BS Intergrated'!$K$34 -> 4.088 | J83: ='BS Intergrated'!$K$34 -> 4.088 | K83: ='BS Intergrated'!$K$34 -> 4.088
C84: Optimistic Case 1 | E84: ='BS Intergrated'!$K$34 -> 4.088 | F84: ='BS Intergrated'!$K$34 -> 4.088 | G84: ='BS Intergrated'!$K$34 -> 4.088 | H84: ='BS Intergrated'!$K$34 -> 4.088 | I84: ='BS Intergrated'!$K$34 -> 4.088 | J84: ='BS Intergrated'!$K$34 -> 4.088 | K84: ='BS Intergrated'!$K$34 -> 4.088
C85: Optimistic Case 2 | E85: ='BS Intergrated'!$K$34 -> 4.088 | F85: ='BS Intergrated'!$K$34 -> 4.088 | G85: ='BS Intergrated'!$K$34 -> 4.088 | H85: ='BS Intergrated'!$K$34 -> 4.088 | I85: ='BS Intergrated'!$K$34 -> 4.088 | J85: ='BS Intergrated'!$K$34 -> 4.088 | K85: ='BS Intergrated'!$K$34 -> 4.088
E88: Other Non-Current Assets
C89: Selected Case | E89: {=_xlfn.XLOOKUP($B$3,$C$11:$C$15,E91:K95)} -> 0.02782415 | F89: 0.02782415 | G89: 0.02782415 | H89: 0.02782415 | I89: 0.02782415 | J89: 0.02782415 | K89: 0.02782415
C91: Pessimistic Case 2 | E91: {=AVERAGE(SMALL('BS Ratios'!$E$13:$K$13,_xlfn.SEQUENCE(1)))} -> 0.014251814 | F91: {=AVERAGE(SMALL('BS Ratios'!$E$13:$K$13,_xlfn.SEQUENCE(1)))} -> 0.014251814 | G91: {=AVERAGE(SMALL('BS Ratios'!$E$13:$K$13,_xlfn.SEQUENCE(1)))} -> 0.014251814 | H91: {=AVERAGE(SMALL('BS Ratios'!$E$13:$K$13,_xlfn.SEQUENCE(1)))} -> 0.014251814 | I91: {=AVERAGE(SMALL('BS Ratios'!$E$13:$K$13,_xlfn.SEQUENCE(1)))} -> 0.014251814 | J91: {=AVERAGE(SMALL('BS Ratios'!$E$13:$K$13,_xlfn.SEQUENCE(1)))} -> 0.014251814 | K91: {=AVERAGE(SMALL('BS Ratios'!$E$13:$K$13,_xlfn.SEQUENCE(1)))} -> 0.014251814
C92: Pessimistic Case 1 | E92: {=AVERAGE(SMALL('BS Ratios'!$E$13:$K$13,_xlfn.SEQUENCE(2)))} -> 0.016133476 | F92: {=AVERAGE(SMALL('BS Ratios'!$E$13:$K$13,_xlfn.SEQUENCE(2)))} -> 0.016133476 | G92: {=AVERAGE(SMALL('BS Ratios'!$E$13:$K$13,_xlfn.SEQUENCE(2)))} -> 0.016133476 | H92: {=AVERAGE(SMALL('BS Ratios'!$E$13:$K$13,_xlfn.SEQUENCE(2)))} -> 0.016133476 | I92: {=AVERAGE(SMALL('BS Ratios'!$E$13:$K$13,_xlfn.SEQUENCE(2)))} -> 0.016133476 | J92: {=AVERAGE(SMALL('BS Ratios'!$E$13:$K$13,_xlfn.SEQUENCE(2)))} -> 0.016133476 | K92: {=AVERAGE(SMALL('BS Ratios'!$E$13:$K$13,_xlfn.SEQUENCE(2)))} -> 0.016133476
C93: Base Case | E93: ='BS Ratios'!$C$13 -> 0.02782415 | F93: ='BS Ratios'!$C$13 -> 0.02782415 | G93: ='BS Ratios'!$C$13 -> 0.02782415 | H93: ='BS Ratios'!$C$13 -> 0.02782415 | I93: ='BS Ratios'!$C$13 -> 0.02782415 | J93: ='BS Ratios'!$C$13 -> 0.02782415 | K93: ='BS Ratios'!$C$13 -> 0.02782415
C94: Optimistic Case 1 | E94: {=AVERAGE(LARGE('BS Ratios'!$E$13:$K$13,_xlfn.SEQUENCE(2)))} -> 0.050351186 | F94: {=AVERAGE(LARGE('BS Ratios'!$E$13:$K$13,_xlfn.SEQUENCE(2)))} -> 0.050351186 | G94: {=AVERAGE(LARGE('BS Ratios'!$E$13:$K$13,_xlfn.SEQUENCE(2)))} -> 0.050351186 | H94: {=AVERAGE(LARGE('BS Ratios'!$E$13:$K$13,_xlfn.SEQUENCE(2)))} -> 0.050351186 | I94: {=AVERAGE(LARGE('BS Ratios'!$E$13:$K$13,_xlfn.SEQUENCE(2)))} -> 0.050351186 | J94: {=AVERAGE(LARGE('BS Ratios'!$E$13:$K$13,_xlfn.SEQUENCE(2)))} -> 0.050351186 | K94: {=AVERAGE(LARGE('BS Ratios'!$E$13:$K$13,_xlfn.SEQUENCE(2)))} -> 0.050351186
C95: Optimistic Case 2 | E95: {=AVERAGE(LARGE('BS Ratios'!$E$13:$K$13,_xlfn.SEQUENCE(1)))} -> 0.077299026 | F95: {=AVERAGE(LARGE('BS Ratios'!$E$13:$K$13,_xlfn.SEQUENCE(1)))} -> 0.077299026 | G95: {=AVERAGE(LARGE('BS Ratios'!$E$13:$K$13,_xlfn.SEQUENCE(1)))} -> 0.077299026 | H95: {=AVERAGE(LARGE('BS Ratios'!$E$13:$K$13,_xlfn.SEQUENCE(1)))} -> 0.077299026 | I95: {=AVERAGE(LARGE('BS Ratios'!$E$13:$K$13,_xlfn.SEQUENCE(1)))} -> 0.077299026 | J95: {=AVERAGE(LARGE('BS Ratios'!$E$13:$K$13,_xlfn.SEQUENCE(1)))} -> 0.077299026 | K95: {=AVERAGE(LARGE('BS Ratios'!$E$13:$K$13,_xlfn.SEQUENCE(1)))} -> 0.077299026
E98: Strategic Investments
C99: Selected Case | E99: {=_xlfn.XLOOKUP($B$3,$C$11:$C$15,E101:K105)} -> 213.147 | F99: 213.147 | G99: 213.147 | H99: 213.147 | I99: 213.147 | J99: 213.147 | K99: 213.147
C101: Pessimistic Case 2 | E101: ='BS Intergrated'!$K$37 -> 213.147 | F101: ='BS Intergrated'!$K$37 -> 213.147 | G101: ='BS Intergrated'!$K$37 -> 213.147 | H101: ='BS Intergrated'!$K$37 -> 213.147 | I101: ='BS Intergrated'!$K$37 -> 213.147 | J101: ='BS Intergrated'!$K$37 -> 213.147 | K101: ='BS Intergrated'!$K$37 -> 213.147
C102: Pessimistic Case 1 | E102: ='BS Intergrated'!$K$37 -> 213.147 | F102: ='BS Intergrated'!$K$37 -> 213.147 | G102: ='BS Intergrated'!$K$37 -> 213.147 | H102: ='BS Intergrated'!$K$37 -> 213.147 | I102: ='BS Intergrated'!$K$37 -> 213.147 | J102: ='BS Intergrated'!$K$37 -> 213.147 | K102: ='BS Intergrated'!$K$37 -> 213.147
C103: Base Case | E103: ='BS Intergrated'!$K$37 -> 213.147 | F103: ='BS Intergrated'!$K$37 -> 213.147 | G103: ='BS Intergrated'!$K$37 -> 213.147 | H103: ='BS Intergrated'!$K$37 -> 213.147 | I103: ='BS Intergrated'!$K$37 -> 213.147 | J103: ='BS Intergrated'!$K$37 -> 213.147 | K103: ='BS Intergrated'!$K$37 -> 213.147
C104: Optimistic Case 1 | E104: ='BS Intergrated'!$K$37 -> 213.147 | F104: ='BS Intergrated'!$K$37 -> 213.147 | G104: ='BS Intergrated'!$K$37 -> 213.147 | H104: ='BS Intergrated'!$K$37 -> 213.147 | I104: ='BS Intergrated'!$K$37 -> 213.147 | J104: ='BS Intergrated'!$K$37 -> 213.147 | K104: ='BS Intergrated'!$K$37 -> 213.147
C105: Optimistic Case 2 | E105: ='BS Intergrated'!$K$37 -> 213.147 | F105: ='BS Intergrated'!$K$37 -> 213.147 | G105: ='BS Intergrated'!$K$37 -> 213.147 | H105: ='BS Intergrated'!$K$37 -> 213.147 | I105: ='BS Intergrated'!$K$37 -> 213.147 | J105: ='BS Intergrated'!$K$37 -> 213.147 | K105: ='BS Intergrated'!$K$37 -> 213.147
E108: Goodwill
C109: Selected Case | E109: {=_xlfn.XLOOKUP($B$3,$C$11:$C$15,E111:K115)} -> 2792.5451 | F109: 3477.0594 | G109: 4412.9154 | H109: 5645.1702 | I109: 7184.6843 | J109: 9041.9547 | K109: 0
C111: Pessimistic Case 2 | E111: ='BS Intergrated'!$K$35+(E$199*'IS Intergrated'!L$10) -> 2792.5451 | F111: ='BS Intergrated'!$L$35+(F$199*'IS Intergrated'!M$10) -> 3477.0594 | G111: ='BS Intergrated'!$M$35+(G$199*'IS Intergrated'!N$10) -> 4412.9154 | H111: ='BS Intergrated'!$N$35+(H$199*'IS Intergrated'!O$10) -> 5645.1702 | I111: ='BS Intergrated'!$O$35+(I$199*'IS Intergrated'!P$10) -> 7184.6843 | J111: ='BS Intergrated'!$P$35+(J$199*'IS Intergrated'!Q$10) -> 9041.9547
C112: Pessimistic Case 1 | E112: ='BS Intergrated'!$K$35+(E$199*'IS Intergrated'!L$10) -> 2792.5451 | F112: ='BS Intergrated'!$L$35+(F$199*'IS Intergrated'!M$10) -> 3477.0594 | G112: ='BS Intergrated'!$M$35+(G$199*'IS Intergrated'!N$10) -> 4412.9154 | H112: ='BS Intergrated'!$N$35+(H$199*'IS Intergrated'!O$10) -> 5645.1702 | I112: ='BS Intergrated'!$O$35+(I$199*'IS Intergrated'!P$10) -> 7184.6843 | J112: ='BS Intergrated'!$P$35+(J$199*'IS Intergrated'!Q$10) -> 9041.9547
C113: Base Case | E113: ='BS Intergrated'!$K$35+(E$199*'IS Intergrated'!L$10) -> 2792.5451 | F113: ='BS Intergrated'!$L$35+(F$199*'IS Intergrated'!M$10) -> 3477.0594 | G113: ='BS Intergrated'!$M$35+(G$199*'IS Intergrated'!N$10) -> 4412.9154 | H113: ='BS Intergrated'!$N$35+(H$199*'IS Intergrated'!O$10) -> 5645.1702 | I113: ='BS Intergrated'!$O$35+(I$199*'IS Intergrated'!P$10) -> 7184.6843 | J113: ='BS Intergrated'!$P$35+(J$199*'IS Intergrated'!Q$10) -> 9041.9547
C114: Optimistic Case 1 | E114: ='BS Intergrated'!$K$35+(E$199*'IS Intergrated'!L$10) -> 2792.5451 | F114: ='BS Intergrated'!$L$35+(F$199*'IS Intergrated'!M$10) -> 3477.0594 | G114: ='BS Intergrated'!$M$35+(G$199*'IS Intergrated'!N$10) -> 4412.9154 | H114: ='BS Intergrated'!$N$35+(H$199*'IS Intergrated'!O$10) -> 5645.1702 | I114: ='BS Intergrated'!$O$35+(I$199*'IS Intergrated'!P$10) -> 7184.6843 | J114: ='BS Intergrated'!$P$35+(J$199*'IS Intergrated'!Q$10) -> 9041.9547
C115: Optimistic Case 2 | E115: ='BS Intergrated'!$K$35+(E$199*'IS Intergrated'!L$10) -> 2792.5451 | F115: ='BS Intergrated'!$L$35+(F$199*'IS Intergrated'!M$10) -> 3477.0594 | G115: ='BS Intergrated'!$M$35+(G$199*'IS Intergrated'!N$10) -> 4412.9154 | H115: ='BS Intergrated'!$N$35+(H$199*'IS Intergrated'!O$10) -> 5645.1702 | I115: ='BS Intergrated'!$O$35+(I$199*'IS Intergrated'!P$10) -> 7184.6843 | J115: ='BS Intergrated'!$P$35+(J$199*'IS Intergrated'!Q$10) -> 9041.9547
E118: Amortization Schedule
C119: Selected Case | E119: {=_xlfn.XLOOKUP($B$3,$C$11:$C$15,E121:K125)} -> 101.49 | F119: 101.49 | G119: 101.49 | H119: 101.49 | I119: 101.49 | J119: 101.49 | K119: 101.49
C121: Pessimistic Case 2 | E121: 101.49 | F121: 101.49 | G121: 101.49 | H121: 101.49 | I121: 101.49 | J121: 101.49 | K121: 101.49
C122: Pessimistic Case 1 | E122: 101.49 | F122: 101.49 | G122: 101.49 | H122: 101.49 | I122: 101.49 | J122: 101.49 | K122: 101.49
C123: Base Case | E123: 101.49 | F123: 101.49 | G123: 101.49 | H123: 101.49 | I123: 101.49 | J123: 101.49 | K123: 101.49
C124: Optimistic Case 1 | E124: 101.49 | F124: 101.49 | G124: 101.49 | H124: 101.49 | I124: 101.49 | J124: 101.49 | K124: 101.49
C125: Optimistic Case 2 | E125: 101.49 | F125: 101.49 | G125: 101.49 | H125: 101.49 | I125: 101.49 | J125: 101.49 | K125: 101.49
E128: Deferred Tax Assets
E129: {=_xlfn.XLOOKUP($B$3,$C$11:$C$15,E131:K135)} -> 4.088 | F129: 4.088 | G129: 4.088 | H129: 4.088 | I129: 4.088 | J129: 4.088 | K129: 4.088
C131: Pessimistic Case 2 | E131: ='BS Intergrated'!$K$34 -> 4.088 | F131: ='BS Intergrated'!$K$34 -> 4.088 | G131: ='BS Intergrated'!$K$34 -> 4.088 | H131: ='BS Intergrated'!$K$34 -> 4.088 | I131: ='BS Intergrated'!$K$34 -> 4.088 | J131: ='BS Intergrated'!$K$34 -> 4.088 | K131: ='BS Intergrated'!$K$34 -> 4.088
C132: Pessimistic Case 1 | E132: ='BS Intergrated'!$K$34 -> 4.088 | F132: ='BS Intergrated'!$K$34 -> 4.088 | G132: ='BS Intergrated'!$K$34 -> 4.088 | H132: ='BS Intergrated'!$K$34 -> 4.088 | I132: ='BS Intergrated'!$K$34 -> 4.088 | J132: ='BS Intergrated'!$K$34 -> 4.088 | K132: ='BS Intergrated'!$K$34 -> 4.088
C133: Base Case | E133: ='BS Intergrated'!$K$34 -> 4.088 | F133: ='BS Intergrated'!$K$34 -> 4.088 | G133: ='BS Intergrated'!$K$34 -> 4.088 | H133: ='BS Intergrated'!$K$34 -> 4.088 | I133: ='BS Intergrated'!$K$34 -> 4.088 | J133: ='BS Intergrated'!$K$34 -> 4.088 | K133: ='BS Intergrated'!$K$34 -> 4.088
C134: Optimistic Case 1 | E134: ='BS Intergrated'!$K$34 -> 4.088 | F134: ='BS Intergrated'!$K$34 -> 4.088 | G134: ='BS Intergrated'!$K$34 -> 4.088 | H134: ='BS Intergrated'!$K$34 -> 4.088 | I134: ='BS Intergrated'!$K$34 -> 4.088 | J134: ='BS Intergrated'!$K$34 -> 4.088 | K134: ='BS Intergrated'!$K$34 -> 4.088
